{
    "searchParameters": {
        "q": "Digital camera",
        "type": "images",
        "num": 100,
        "engine": "google"
    },
    "images": [
        {
            "title": "Canon IXY200 Compact Digital Camera Optical 8X Zoom Silver ...",
            "imageUrl": "https://i.ebayimg.com/images/g/m3YAAOSwSDRjmEhX/s-l1200.jpg",
            "imageWidth": 1080,
            "imageHeight": 709,
            "thumbnailUrl": "https://encrypted-tbn0.gstatic.com/images?q=tbn:ANd9GcRbwvnIinB_AxqpEBswHwQALiHNPqv97lpXMA&s",
            "thumbnailWidth": 277,
            "thumbnailHeight": 182,
            "source": "eBay",
            "domain": "www.ebay.com",
            "link": "https://www.ebay.com/itm/385291902331",
            "googleUrl": "https://www.google.com/imgres?imgurl=https%3A%2F%2Fi.ebayimg.com%2Fimages%2Fg%2Fm3YAAOSwSDRjmEhX%2Fs-l1200.jpg&tbnid=zAjPL0fy6m2vuM&imgrefurl=https%3A%2F%2Fwww.ebay.com%2Fitm%2F385291902331&docid=fhUxmyWRPeJW_M&w=1080&h=709",
            "position": 12
        },
        {
            "title": "How to Choose the Best Digital Camera For You | 8 Questions ...",
            "imageUrl": "https://www.digitalphotomentor.com/photography/2020/07/best-digital-camera-beginner.jpg",
            "imageWidth": 750,
            "imageHeight": 582,
            "thumbnailUrl": "https://encrypted-tbn0.gstatic.com/images?q=tbn:ANd9GcQyR02v4Z66ctD5DhRcGUAYp-ko6ic8w7rS_g&s",
            "thumbnailWidth": 255,
            "thumbnailHeight": 198,
            "source": "Digital Photo Mentor",
            "domain": "www.digitalphotomentor.com",
            "link": "https://www.digitalphotomentor.com/choose-best-digital-camera/",
            "googleUrl": "https://www.google.com/imgres?imgurl=https%3A%2F%2Fwww.digitalphotomentor.com%2Fphotography%2F2020%2F07%2Fbest-digital-camera-beginner.jpg&tbnid=neIoJeia-g-mUM&imgrefurl=https%3A%2F%2Fwww.digitalphotomentor.com%2Fchoose-best-digital-camera%2F&docid=QbRYUi9xYd9WSM&w=750&h=582",
            "position": 13
        },
        {
            "title": "NBD 4K 48MP Digital Camera for Photography, Vlogging with ...",
            "imageUrl": "https://i5.walmartimages.com/asr/b39cecd6-7da6-417b-85cd-2b230133dd24.f972be5de0e40d5d0c5981ab09023c8a.jpeg?odnHeight=768&odnWidth=768&odnBg=FFFFFF",
            "imageWidth": 768,
            "imageHeight": 768,
            "thumbnailUrl": "https://encrypted-tbn0.gstatic.com/images?q=tbn:ANd9GcQiaDe9JTCjXfItlKUJFzalfMI_Avy41psetg&s",
            "thumbnailWidth": 225,
            "thumbnailHeight": 225,
            "source": "Walmart",
            "domain": "www.walmart.com",
            "link": "https://www.walmart.com/ip/NBD-Digital-Camera-for-Photography-4K-48MP-Vlogging-Camera-for-YouTube-with-32GB-TF-Card/5590810792",
            "googleUrl": "https://www.google.com/imgres?imgurl=https%3A%2F%2Fi5.walmartimages.com%2Fasr%2Fb39cecd6-7da6-417b-85cd-2b230133dd24.f972be5de0e40d5d0c5981ab09023c8a.jpeg%3FodnHeight%3D768%26odnWidth%3D768%26odnBg%3DFFFFFF&tbnid=oVgwa7UsJDMBLM&imgrefurl=https%3A%2F%2Fwww.walmart.com%2Fip%2FNBD-Digital-Camera-for-Photography-4K-48MP-Vlogging-Camera-for-YouTube-with-32GB-TF-Card%2F5590810792&docid=ZlesyETtHQOScM&w=768&h=768",
            "position": 14
        },
        {
            "title": "DCZV1/B",
            "imageUrl": "https://d1ncau8tqf99kp.cloudfront.net/converted/75654_original_local_1200x1050_v3_converted.webp",
            "imageWidth": 1200,
            "imageHeight": 1050,
            "thumbnailUrl": "https://encrypted-tbn0.gstatic.com/images?q=tbn:ANd9GcQfLee_V55os9jJld6yJrNJLeX2VBcRFb8eXA&s",
            "thumbnailWidth": 240,
            "thumbnailHeight": 210,
            "source": "Sony Electronics",
            "domain": "electronics.sony.com",
            "link": "https://electronics.sony.com/imaging/compact-cameras/all-vlog-compact-cameras/p/dczv1-b",
            "googleUrl": "https://www.google.com/imgres?imgurl=https%3A%2F%2Fd1ncau8tqf99kp.cloudfront.net%2Fconverted%2F75654_original_local_1200x1050_v3_converted.webp&tbnid=lldBxgPGf_iqrM&imgrefurl=https%3A%2F%2Felectronics.sony.com%2Fimaging%2Fcompact-cameras%2Fall-vlog-compact-cameras%2Fp%2Fdczv1-b&docid=XPhARO_SJNfWuM&w=1200&h=1050",
            "position": 15
        },
        {
            "title": "The Best Digital Cameras for 2024 | PCMag",
            "imageUrl": "https://i.pcmag.com/imagery/roundups/018cwxjHcVMwiaDIpTnZJ8H-60.fit_lim.size_1200x630.v1708542714.jpg",
            "imageWidth": 1120,
            "imageHeight": 630,
            "thumbnailUrl": "https://encrypted-tbn0.gstatic.com/images?q=tbn:ANd9GcR7jtB9vxDN7c7yod8CFjQ45IIHLgJ0iBGzKQ&s",
            "thumbnailWidth": 300,
            "thumbnailHeight": 168,
            "source": "PCMag",
            "domain": "www.pcmag.com",
            "link": "https://www.pcmag.com/picks/the-best-digital-cameras",
            "googleUrl": "https://www.google.com/imgres?imgurl=https%3A%2F%2Fi.pcmag.com%2Fimagery%2Froundups%2F018cwxjHcVMwiaDIpTnZJ8H-60.fit_lim.size_1200x630.v1708542714.jpg&tbnid=LO1eyqIJdJylsM&imgrefurl=https%3A%2F%2Fwww.pcmag.com%2Fpicks%2Fthe-best-digital-cameras&docid=y_Q-rvrSVMFaSM&w=1120&h=630",
            "position": 16
        },
        {
            "title": "Digital camera - Wikipedia",
            "imageUrl": "https://upload.wikimedia.org/wikipedia/commons/9/99/Canon_PowerShot_A95_-_front_and_back.jpg",
            "imageWidth": 586,
            "imageHeight": 872,
            "thumbnailUrl": "https://encrypted-tbn0.gstatic.com/images?q=tbn:ANd9GcQJgclYHK2-O3ZFh3kSUZB113_ZxbK4j-2zjg&s",
            "thumbnailWidth": 184,
            "thumbnailHeight": 274,
            "source": "Wikipedia",
            "domain": "en.wikipedia.org",
            "link": "https://en.wikipedia.org/wiki/Digital_camera",
            "googleUrl": "https://www.google.com/imgres?imgurl=https%3A%2F%2Fupload.wikimedia.org%2Fwikipedia%2Fcommons%2F9%2F99%2FCanon_PowerShot_A95_-_front_and_back.jpg&tbnid=zUdEEjDNm_QjbM&imgrefurl=https%3A%2F%2Fen.wikipedia.org%2Fwiki%2FDigital_camera&docid=UmeIPsunLsI-PM&w=586&h=872",
            "position": 17
        },
        {
            "title": "Digital Camera, 4K Video NBD Camera for YouTube with WiFi, 3.0\" Flip  Screen, Wide Angle Lens, Macro Lens, 16X Zoom",
            "imageUrl": "https://www.nbd-direct.com/cdn/shop/products/11_38536cfd-91c9-4c34-89c5-356641e4286e.jpg?v=1677575897&width=1024",
            "imageWidth": 1024,
            "imageHeight": 1024,
            "thumbnailUrl": "https://encrypted-tbn0.gstatic.com/images?q=tbn:ANd9GcS3fl1UWbYs7z8CMgDXXiAC0XQrXpIXWyJ7Dw&s",
            "thumbnailWidth": 225,
            "thumbnailHeight": 225,
            "source": "NBD-Direct",
            "domain": "www.nbd-direct.com",
            "link": "https://www.nbd-direct.com/products/digital-camera-nbd-nbro-1-cf",
            "googleUrl": "https://www.google.com/imgres?imgurl=https%3A%2F%2Fwww.nbd-direct.com%2Fcdn%2Fshop%2Fproducts%2F11_38536cfd-91c9-4c34-89c5-356641e4286e.jpg%3Fv%3D1677575897%26width%3D1024&tbnid=fbBAMRL-vmyQEM&imgrefurl=https%3A%2F%2Fwww.nbd-direct.com%2Fproducts%2Fdigital-camera-nbd-nbro-1-cf&docid=26DRjk2jWqIcLM&w=1024&h=1024",
            "position": 18
        },
        {
            "title": "Nikon Z50 Mirrorless Digital Camera with 16-50mm Lens ...",
            "imageUrl": "https://pascocamera.com/wp-content/uploads/Nikon-Z50-Kit.jpg",
            "imageWidth": 500,
            "imageHeight": 500,
            "thumbnailUrl": "https://encrypted-tbn0.gstatic.com/images?q=tbn:ANd9GcRcPfxo-uCmEN2zUh0V-wPUynFy97gAe2dFvw&s",
            "thumbnailWidth": 225,
            "thumbnailHeight": 225,
            "source": "Pasco Camera Exchange",
            "domain": "pascocamera.com",
            "link": "https://pascocamera.com/nikon-d750-w-24-120mm-lens-or-body-only/",
            "googleUrl": "https://www.google.com/imgres?imgurl=https%3A%2F%2Fpascocamera.com%2Fwp-content%2Fuploads%2FNikon-Z50-Kit.jpg&tbnid=0ylhy4POaEdYaM&imgrefurl=https%3A%2F%2Fpascocamera.com%2Fnikon-d750-w-24-120mm-lens-or-body-only%2F&docid=Z-atTrNzXPckLM&w=500&h=500",
            "position": 19
        },
        {
            "title": "NBD Digital Camera 4K Ultra HD 48MP All-in-One Vlogging Camera with Wide  Angle Lens, Digital Zoom 16x and 3\" Screen",
            "imageUrl": "https://i5.walmartimages.com/seo/NBD-Digital-Camera-4K-Ultra-HD-48MP-All-in-One-Vlogging-Camera-with-Wide-Angle-Lens-Digital-Zoom-16x-and-3-Screen_a746886f-27db-4433-aea9-5b95e8ff4708.e3cf0eb7f759233e94ae79723cfec566.jpeg",
            "imageWidth": 1500,
            "imageHeight": 1499,
            "thumbnailUrl": "https://encrypted-tbn0.gstatic.com/images?q=tbn:ANd9GcQIHwi2r_pjUL8PWnLBf1UpTcFGNnBDs1LchQ&s",
            "thumbnailWidth": 225,
            "thumbnailHeight": 224,
            "source": "Walmart Business",
            "domain": "business.walmart.com",
            "link": "https://business.walmart.com/ip/NBD-Digital-Camera-4K-Ultra-HD-48MP-All-in-One-Vlogging-Camera-with-Wide-Angle-Lens-Digital-Zoom-16x-and-3-Screen/711035416",
            "googleUrl": "https://www.google.com/imgres?imgurl=https%3A%2F%2Fi5.walmartimages.com%2Fseo%2FNBD-Digital-Camera-4K-Ultra-HD-48MP-All-in-One-Vlogging-Camera-with-Wide-Angle-Lens-Digital-Zoom-16x-and-3-Screen_a746886f-27db-4433-aea9-5b95e8ff4708.e3cf0eb7f759233e94ae79723cfec566.jpeg&tbnid=0J8Px2278KNDQM&imgrefurl=https%3A%2F%2Fbusiness.walmart.com%2Fip%2FNBD-Digital-Camera-4K-Ultra-HD-48MP-All-in-One-Vlogging-Camera-with-Wide-Angle-Lens-Digital-Zoom-16x-and-3-Screen%2F711035416&docid=gVldQmq0yfd-WM&w=1500&h=1499",
            "position": 20
        },
        {
            "title": "The 9 Best Mirrorless Cameras (2024): Full-Frame, APS-C, and ...",
            "imageUrl": "https://media.wired.com/photos/61e8b269b92104f9e83d15b8/191:100/w_2580,c_limit/Gear-Sony-A7IV.jpg",
            "imageWidth": 2009,
            "imageHeight": 1051,
            "thumbnailUrl": "https://encrypted-tbn0.gstatic.com/images?q=tbn:ANd9GcSRgMbqEm_kr_83sh94IafzR2bTEZXIUxgZKA&s",
            "thumbnailWidth": 311,
            "thumbnailHeight": 162,
            "source": "WIRED",
            "domain": "www.wired.com",
            "link": "https://www.wired.com/gallery/best-mirrorless-cameras/",
            "googleUrl": "https://www.google.com/imgres?imgurl=https%3A%2F%2Fmedia.wired.com%2Fphotos%2F61e8b269b92104f9e83d15b8%2F191%3A100%2Fw_2580%2Cc_limit%2FGear-Sony-A7IV.jpg&tbnid=Gpr8zMMZgaCl7M&imgrefurl=https%3A%2F%2Fwww.wired.com%2Fgallery%2Fbest-mirrorless-cameras%2F&docid=BQiOf5cH4wn-eM&w=2009&h=1051",
            "position": 21
        },
        {
            "title": "4K Digital Camera for Beginners, Vlogging Camera for Photography and Video  64MP 18X Digital Zoom Compact Point and Shoot Digital Cameras Autofocus for  ...",
            "imageUrl": "https://m.media-amazon.com/images/I/71Nna4jvHgL._AC_UF894,1000_QL80_.jpg",
            "imageWidth": 894,
            "imageHeight": 909,
            "thumbnailUrl": "https://encrypted-tbn0.gstatic.com/images?q=tbn:ANd9GcQUETTpgzpJh4bBPagikfAPu36VjAtyYD8cpQ&s",
            "thumbnailWidth": 223,
            "thumbnailHeight": 226,
            "source": "Amazon.com",
            "domain": "www.amazon.com",
            "link": "https://www.amazon.com/Beginners-Vlogging-Photography-Autofocus-Beginner/dp/B0CZ42LKVH",
            "googleUrl": "https://www.google.com/imgres?imgurl=https%3A%2F%2Fm.media-amazon.com%2Fimages%2FI%2F71Nna4jvHgL._AC_UF894%2C1000_QL80_.jpg&tbnid=vPsXczSfN4apkM&imgrefurl=https%3A%2F%2Fwww.amazon.com%2FBeginners-Vlogging-Photography-Autofocus-Beginner%2Fdp%2FB0CZ42LKVH&docid=F0AI46gapvsQQM&w=894&h=909",
            "position": 22
        },
        {
            "title": "Sony ZV-1F Vlog Camera for Content Creators and Vloggers ...",
            "imageUrl": "https://d1ncau8tqf99kp.cloudfront.net/converted/108159_original_local_1200x1050_v3_converted.webp",
            "imageWidth": 1200,
            "imageHeight": 1050,
            "thumbnailUrl": "https://encrypted-tbn0.gstatic.com/images?q=tbn:ANd9GcR1jNnknbH5kJ-wmdBVo3nCtGexKK0fQ-ZdYA&s",
            "thumbnailWidth": 240,
            "thumbnailHeight": 210,
            "source": "Sony Electronics",
            "domain": "electronics.sony.com",
            "link": "https://electronics.sony.com/imaging/compact-cameras/all-vlog-compact-cameras/p/zv1f-b",
            "googleUrl": "https://www.google.com/imgres?imgurl=https%3A%2F%2Fd1ncau8tqf99kp.cloudfront.net%2Fconverted%2F108159_original_local_1200x1050_v3_converted.webp&tbnid=3CUZMcqkOVQ35M&imgrefurl=https%3A%2F%2Felectronics.sony.com%2Fimaging%2Fcompact-cameras%2Fall-vlog-compact-cameras%2Fp%2Fzv1f-b&docid=i4UzDIrWeg9JUM&w=1200&h=1050",
            "position": 23
        },
        {
            "title": "Digital Camera FHD 4K 48MP Vlogging Camera with Autofocus Dual Camera 16X  Digital Zoom with 32GB Card Small Digital Cameras for Pictures Portable ...",
            "imageUrl": "https://m.media-amazon.com/images/I/71Ev+hK8PGL._AC_UF894,1000_QL80_.jpg",
            "imageWidth": 894,
            "imageHeight": 944,
            "thumbnailUrl": "https://encrypted-tbn0.gstatic.com/images?q=tbn:ANd9GcRgJXQ9D5Ga3CtvIT1nzZQrwxMZs38MJG1AkA&s",
            "thumbnailWidth": 218,
            "thumbnailHeight": 231,
            "source": "Amazon.com",
            "domain": "www.amazon.com",
            "link": "https://www.amazon.com/Digital-Vlogging-Autofocus-Pictures-Portable/dp/B0CM3Q9QMJ",
            "googleUrl": "https://www.google.com/imgres?imgurl=https%3A%2F%2Fm.media-amazon.com%2Fimages%2FI%2F71Ev%2BhK8PGL._AC_UF894%2C1000_QL80_.jpg&tbnid=RA5cSudKVSGrLM&imgrefurl=https%3A%2F%2Fwww.amazon.com%2FDigital-Vlogging-Autofocus-Pictures-Portable%2Fdp%2FB0CM3Q9QMJ&docid=eXJuE1qP6vumFM&w=894&h=944",
            "position": 24
        },
        {
            "title": "Canon Digital Camera IXY180SL 20 MP 8X zoom",
            "imageUrl": "https://i.ebayimg.com/images/g/HJAAAOSwtAtbrt8F/s-l1200.jpg",
            "imageWidth": 500,
            "imageHeight": 363,
            "thumbnailUrl": "https://encrypted-tbn0.gstatic.com/images?q=tbn:ANd9GcQ75l_92z6wB_j86xmQF0J0ffbNhbQYEiJQtw&s",
            "thumbnailWidth": 264,
            "thumbnailHeight": 191,
            "source": "eBay",
            "domain": "www.ebay.com",
            "link": "https://www.ebay.com/itm/283185577614",
            "googleUrl": "https://www.google.com/imgres?imgurl=https%3A%2F%2Fi.ebayimg.com%2Fimages%2Fg%2FHJAAAOSwtAtbrt8F%2Fs-l1200.jpg&tbnid=_QTEB5oBBiqkKM&imgrefurl=https%3A%2F%2Fwww.ebay.com%2Fitm%2F283185577614&docid=yqtEbB8U4cVxFM&w=500&h=363",
            "position": 25
        },
        {
            "title": "Canon Powershot G7 X Mark Iii 20.1 Megapixel Digital Camera ...",
            "imageUrl": "https://target.scene7.com/is/image/Target/GUEST_d1b28464-ad77-4252-9e3d-9d9b8b9f6846?wid=488&hei=488&fmt=pjpeg",
            "imageWidth": 488,
            "imageHeight": 488,
            "thumbnailUrl": "https://encrypted-tbn0.gstatic.com/images?q=tbn:ANd9GcR1y2YaFa5hMBxe82gXTr5BmNWY4BX7VyeXvQ&s",
            "thumbnailWidth": 225,
            "thumbnailHeight": 225,
            "source": "Target",
            "domain": "www.target.com",
            "link": "https://www.target.com/p/canon-powershot-g7-x-mark-iii-20-1-megapixel-digital-camera-black/-/A-91467769",
            "googleUrl": "https://www.google.com/imgres?imgurl=https%3A%2F%2Ftarget.scene7.com%2Fis%2Fimage%2FTarget%2FGUEST_d1b28464-ad77-4252-9e3d-9d9b8b9f6846%3Fwid%3D488%26hei%3D488%26fmt%3Dpjpeg&tbnid=F-60Ty4XquYmUM&imgrefurl=https%3A%2F%2Fwww.target.com%2Fp%2Fcanon-powershot-g7-x-mark-iii-20-1-megapixel-digital-camera-black%2F-%2FA-91467769&docid=mqgn0b5T2pzYtM&w=488&h=488",
            "position": 26
        },
        {
            "title": "Nikon D3500 Review | PCMag",
            "imageUrl": "https://i.pcmag.com/imagery/reviews/05KU5NmyTcDrIOcF9n5F2vz-30.fit_lim.size_1200x630.v1569479607.jpg",
            "imageWidth": 810,
            "imageHeight": 456,
            "thumbnailUrl": "https://encrypted-tbn0.gstatic.com/images?q=tbn:ANd9GcSF88bCKl3wyR11p6-Aneaqhp3GZIxP5JsKWw&s",
            "thumbnailWidth": 299,
            "thumbnailHeight": 168,
            "source": "PCMag",
            "domain": "www.pcmag.com",
            "link": "https://www.pcmag.com/reviews/nikon-d3500",
            "googleUrl": "https://www.google.com/imgres?imgurl=https%3A%2F%2Fi.pcmag.com%2Fimagery%2Freviews%2F05KU5NmyTcDrIOcF9n5F2vz-30.fit_lim.size_1200x630.v1569479607.jpg&tbnid=uwCJ25fl3FJ4bM&imgrefurl=https%3A%2F%2Fwww.pcmag.com%2Freviews%2Fnikon-d3500&docid=CG1BZR9NY6Y04M&w=810&h=456",
            "position": 27
        },
      
        
        {
            "title": "Smartphone vs Digital Camera: Which is better? | Amateur ...",
            "imageUrl": "https://amateurphotographer.com/wp-content/uploads/sites/7/2023/06/tamron-50-400mm-di-III-vc-VXD-JW-AP-P6120004.jpg?w=1024",
            "imageWidth": 1024,
            "imageHeight": 682,
            "thumbnailUrl": "https://encrypted-tbn0.gstatic.com/images?q=tbn:ANd9GcTxcT0N-xBcwneWz3tdgwf0oRtB0YDkONvvvA&s",
            "thumbnailWidth": 275,
            "thumbnailHeight": 183,
            "source": "Amateur Photographer",
            "domain": "amateurphotographer.com",
            "link": "https://amateurphotographer.com/buying-advice/smartphone-vs-digital-camera-which-is-better/",
            "googleUrl": "https://www.google.com/imgres?imgurl=https%3A%2F%2Famateurphotographer.com%2Fwp-content%2Fuploads%2Fsites%2F7%2F2023%2F06%2Ftamron-50-400mm-di-III-vc-VXD-JW-AP-P6120004.jpg%3Fw%3D1024&tbnid=7HmQyhM_P1tR1M&imgrefurl=https%3A%2F%2Famateurphotographer.com%2Fbuying-advice%2Fsmartphone-vs-digital-camera-which-is-better%2F&docid=MSWRBfCaYLcxDM&w=1024&h=682",
            "position": 33
        },
        {
            "title": "The Best Compact Point-and-Shoot Cameras of 2024 | Reviews ...",
            "imageUrl": "https://d1b5h9psu9yexj.cloudfront.net/61612/Sony-RX100-VII_20240426-133717_full.jpeg",
            "imageWidth": 399,
            "imageHeight": 266,
            "thumbnailUrl": "https://encrypted-tbn0.gstatic.com/images?q=tbn:ANd9GcQzfdbvgONpRaTLT7qmiqkGwyTbAKsiJk7eVA&s",
            "thumbnailWidth": 275,
            "thumbnailHeight": 183,
            "source": "The New York Times",
            "domain": "www.nytimes.com",
            "link": "https://www.nytimes.com/wirecutter/reviews/best-point-and-shoot-camera/",
            "googleUrl": "https://www.google.com/imgres?imgurl=https%3A%2F%2Fd1b5h9psu9yexj.cloudfront.net%2F61612%2FSony-RX100-VII_20240426-133717_full.jpeg&tbnid=8f3wVbis8MdIwM&imgrefurl=https%3A%2F%2Fwww.nytimes.com%2Fwirecutter%2Freviews%2Fbest-point-and-shoot-camera%2F&docid=A5J1OSR3xMSXGM&w=399&h=266",
            "position": 34
        },
        {
            "title": "Digital Camera, Kids Camera with 32GB Card FHD 1080P 44MP Vlogging Camera  with LCD Screen 16X Zoom Compact Portable Mini Rechargeable Camera Gifts  for ...",
            "imageUrl": "https://m.media-amazon.com/images/I/51wdj4l8TLL._AC_.jpg",
            "imageWidth": 499,
            "imageHeight": 489,
            "thumbnailUrl": "https://encrypted-tbn0.gstatic.com/images?q=tbn:ANd9GcQlT1xo-xQgV1f9J5ySnOGRYcXNw3HkEL08HA&s",
            "thumbnailWidth": 227,
            "thumbnailHeight": 222,
            "source": "Amazon.com",
            "domain": "www.amazon.com",
            "link": "https://www.amazon.com/Vlogging-Portable-Rechargeable-Students-Boys-Pink/dp/B0BHSMHHCR",
            "googleUrl": "https://www.google.com/imgres?imgurl=https%3A%2F%2Fm.media-amazon.com%2Fimages%2FI%2F51wdj4l8TLL._AC_.jpg&tbnid=_hDqBzcEYHFCYM&imgrefurl=https%3A%2F%2Fwww.amazon.com%2FVlogging-Portable-Rechargeable-Students-Boys-Pink%2Fdp%2FB0BHSMHHCR&docid=hmhYKk0EWIvKzM&w=499&h=489",
            "position": 35
        },
        {
            "title": "Sony ZV-1 review: Digital Photography Review",
            "imageUrl": "https://www.dpreview.com/files/p/E~C139x0S2223x1667T600x450~articles/4610395725/Beauty/Sony-ZV-1-02.jpeg",
            "imageWidth": 600,
            "imageHeight": 450,
            "thumbnailUrl": "https://encrypted-tbn0.gstatic.com/images?q=tbn:ANd9GcQrmykeDspx8lkM4KtZo-BPJ_NlabW7RvdnYQ&s",
            "thumbnailWidth": 259,
            "thumbnailHeight": 194,
            "source": "Digital Photography Review",
            "domain": "www.dpreview.com",
            "link": "https://www.dpreview.com/reviews/sony-zv-1-review",
            "googleUrl": "https://www.google.com/imgres?imgurl=https%3A%2F%2Fwww.dpreview.com%2Ffiles%2Fp%2FE~C139x0S2223x1667T600x450~articles%2F4610395725%2FBeauty%2FSony-ZV-1-02.jpeg&tbnid=RutoK7xp0alCAM&imgrefurl=https%3A%2F%2Fwww.dpreview.com%2Freviews%2Fsony-zv-1-review&docid=nXoTb-_LIVFBjM&w=600&h=450",
            "position": 36
        },
        {
            "title": "Digital camera | Definition & Facts | Britannica",
            "imageUrl": "https://cdn.britannica.com/67/92867-050-BC3DC984/cameras-camera-reviews-crystal-displays-photographs-film.jpg",
            "imageWidth": 1600,
            "imageHeight": 1121,
            "thumbnailUrl": "https://encrypted-tbn0.gstatic.com/images?q=tbn:ANd9GcR34YMBfx94RgRaNN48fbxxD61t_QZBLew0PQ&s",
            "thumbnailWidth": 268,
            "thumbnailHeight": 188,
            "source": "Britannica",
            "domain": "www.britannica.com",
            "link": "https://www.britannica.com/technology/digital-camera",
            "googleUrl": "https://www.google.com/imgres?imgurl=https%3A%2F%2Fcdn.britannica.com%2F67%2F92867-050-BC3DC984%2Fcameras-camera-reviews-crystal-displays-photographs-film.jpg&tbnid=14TXQ7kWUwLr0M&imgrefurl=https%3A%2F%2Fwww.britannica.com%2Ftechnology%2Fdigital-camera&docid=sB3zUX5Bwoj-hM&w=1600&h=1121",
            "position": 37
        },
        {
            "title": "NBD Digital Camera 4K 48MP Vlogging Camera, Perfect Camera for Photography  with 32GB SD Card, 52mm Wide Angle & Macro Lens，16x Digital Zoom, An Ideal  ...",
            "imageUrl": "http://www.nbd-direct.com/cdn/shop/files/20230906181518.jpg?v=1693995369&width=2048",
            "imageWidth": 1451,
            "imageHeight": 1439,
            "thumbnailUrl": "https://encrypted-tbn0.gstatic.com/images?q=tbn:ANd9GcR0g7YIUFSrnw8T-GCZoYO3eSDef8lrDosZww&s",
            "thumbnailWidth": 225,
            "thumbnailHeight": 224,
            "source": "NBD-Direct",
            "domain": "www.nbd-direct.com",
            "link": "https://www.nbd-direct.com/products/nbd-digital-camera-4k-48mp-vlogging-camera-perfect-camera-for-photography-with-32gb-sd-card-52mm-wide-angle-macro-lens-16x-digital-zoom-an-ideal-compact-camera-for-beginners",
            "googleUrl": "https://www.google.com/imgres?imgurl=http%3A%2F%2Fwww.nbd-direct.com%2Fcdn%2Fshop%2Ffiles%2F20230906181518.jpg%3Fv%3D1693995369%26width%3D2048&tbnid=K2G5iH0wuFNWiM&imgrefurl=https%3A%2F%2Fwww.nbd-direct.com%2Fproducts%2Fnbd-digital-camera-4k-48mp-vlogging-camera-perfect-camera-for-photography-with-32gb-sd-card-52mm-wide-angle-macro-lens-16x-digital-zoom-an-ideal-compact-camera-for-beginners&docid=7a5BHxAyA0m-yM&w=1451&h=1439",
            "position": 38
        },
        {
            "title": "Product List - Digital Compact Cameras - Canon South ...",
            "imageUrl": "https://asia.canon/media/image/2018/11/19/b639ce271d2b450c974112ee3a7246ba_PowerShot-SX70-HS-Front-Slant.png",
            "imageWidth": 362,
            "imageHeight": 320,
            "thumbnailUrl": "https://encrypted-tbn0.gstatic.com/images?q=tbn:ANd9GcRrEmz7EvqVqZkMuYcj9KUwxlLmtyGE6ZSvOA&s",
            "thumbnailWidth": 239,
            "thumbnailHeight": 211,
            "source": "Canon Asia",
            "domain": "asia.canon",
            "link": "https://asia.canon/en/consumer/products/search?category=photography&subCategory=digital-compact-cameras",
            "googleUrl": "https://www.google.com/imgres?imgurl=https%3A%2F%2Fasia.canon%2Fmedia%2Fimage%2F2018%2F11%2F19%2Fb639ce271d2b450c974112ee3a7246ba_PowerShot-SX70-HS-Front-Slant.png&tbnid=auhv-wpTQ5xN3M&imgrefurl=https%3A%2F%2Fasia.canon%2Fen%2Fconsumer%2Fproducts%2Fsearch%3Fcategory%3Dphotography%26subCategory%3Ddigital-compact-cameras&docid=PR1R7wVTetEScM&w=362&h=320",
            "copyright": "CANON.INC",
            "position": 39
        },
        {
            "title": "Best Camera to Buy in 2024 - CNET",
            "imageUrl": "https://www.cnet.com/a/img/resize/f869d25313c4666d09a7ed30670dd792d6fc9c98/hub/2022/08/30/4d7ba89a-2816-4329-b6a8-92f775841356/best-camera-cnet-2022-canon-sony-nikon-fujifilm-17.jpg?auto=webp&fit=crop&height=576&width=768",
            "imageWidth": 768,
            "imageHeight": 576,
            "thumbnailUrl": "https://encrypted-tbn0.gstatic.com/images?q=tbn:ANd9GcSRkJTX2xeUq6t9qfCWTVPjHsN20ljVgg5Naw&s",
            "thumbnailWidth": 259,
            "thumbnailHeight": 194,
            "source": "CNET",
            "domain": "www.cnet.com",
            "link": "https://www.cnet.com/tech/computing/best-camera-to-buy/",
            "googleUrl": "https://www.google.com/imgres?imgurl=https%3A%2F%2Fwww.cnet.com%2Fa%2Fimg%2Fresize%2Ff869d25313c4666d09a7ed30670dd792d6fc9c98%2Fhub%2F2022%2F08%2F30%2F4d7ba89a-2816-4329-b6a8-92f775841356%2Fbest-camera-cnet-2022-canon-sony-nikon-fujifilm-17.jpg%3Fauto%3Dwebp%26fit%3Dcrop%26height%3D576%26width%3D768&tbnid=Kj6aTRLWC5ioPM&imgrefurl=https%3A%2F%2Fwww.cnet.com%2Ftech%2Fcomputing%2Fbest-camera-to-buy%2F&docid=V9cYz7Rm8TQLSM&w=768&h=576",
            "position": 40
        },
        {
            "title": "Compact Camera, 4K LCD 2.7 Inch Digital Camera, Internal Filling for  Shooting (Silver)",
            "imageUrl": "https://m.media-amazon.com/images/I/61KIcUcdxRL.jpg",
            "imageWidth": 1601,
            "imageHeight": 1601,
            "thumbnailUrl": "https://encrypted-tbn0.gstatic.com/images?q=tbn:ANd9GcSF_CjvkdoE1UJZVXvGLl6PzDsz_awOkiLBVA&s",
            "thumbnailWidth": 225,
            "thumbnailHeight": 225,
            "source": "Amazon.com",
            "domain": "www.amazon.com",
            "link": "https://www.amazon.com/Compact-Digital-Internal-Filling-Shooting/dp/B0BPQY4YTH",
            "googleUrl": "https://www.google.com/imgres?imgurl=https%3A%2F%2Fm.media-amazon.com%2Fimages%2FI%2F61KIcUcdxRL.jpg&tbnid=KL_sxreNbsccMM&imgrefurl=https%3A%2F%2Fwww.amazon.com%2FCompact-Digital-Internal-Filling-Shooting%2Fdp%2FB0BPQY4YTH&docid=A4dO08tFJpShhM&w=1601&h=1601",
            "position": 41
        },
        {
            "title": "Find Out Why Digital Cameras May Still Be Worth It",
            "imageUrl": "https://cdn.aarp.net/content/dam/aarp/home-and-family/personal-technology/2022/12/1140-digital-camera-viewfinder.jpg",
            "imageWidth": 1140,
            "imageHeight": 640,
            "thumbnailUrl": "https://encrypted-tbn0.gstatic.com/images?q=tbn:ANd9GcRHIkl_WAoI36qNEGzOp5GvOHNpz6FP0IzVzw&s",
            "thumbnailWidth": 300,
            "thumbnailHeight": 168,
            "source": "AARP",
            "domain": "www.aarp.org",
            "link": "https://www.aarp.org/home-family/personal-technology/info-2022/standalone-digital-cameras.html",
            "googleUrl": "https://www.google.com/imgres?imgurl=https%3A%2F%2Fcdn.aarp.net%2Fcontent%2Fdam%2Faarp%2Fhome-and-family%2Fpersonal-technology%2F2022%2F12%2F1140-digital-camera-viewfinder.jpg&tbnid=VPFMgxaSc-d8BM&imgrefurl=https%3A%2F%2Fwww.aarp.org%2Fhome-family%2Fpersonal-technology%2Finfo-2022%2Fstandalone-digital-cameras.html&docid=vGkbdIhGAT8vZM&w=1140&h=640",
            "creator": "Enrique Alcala / EyeEm",
            "credit": "Getty Images/EyeEm",
            "position": 42
        },
        {
            "title": "The First Digital Camera Was the Size of a Toaster - IEEE ...",
            "imageUrl": "https://spectrum.ieee.org/media-library/less-than-p-greater-than-steven-j-sasson-inventor-of-the-first-digital-camera-comparing-his-device-with-todays-digital-cameras-less-than-p-greater-than.jpg?id=29644015",
            "imageWidth": 1200,
            "imageHeight": 900,
            "thumbnailUrl": "https://encrypted-tbn0.gstatic.com/images?q=tbn:ANd9GcR8Mf8NsbFrD6XQ-ylI2mxo2WQcJjoA6J0o2g&s",
            "thumbnailWidth": 259,
            "thumbnailHeight": 194,
            "source": "IEEE Spectrum",
            "domain": "spectrum.ieee.org",
            "link": "https://spectrum.ieee.org/first-digital-camera-history",
            "googleUrl": "https://www.google.com/imgres?imgurl=https%3A%2F%2Fspectrum.ieee.org%2Fmedia-library%2Fless-than-p-greater-than-steven-j-sasson-inventor-of-the-first-digital-camera-comparing-his-device-with-todays-digital-cameras-less-than-p-greater-than.jpg%3Fid%3D29644015&tbnid=qCxvTsDyzvzIbM&imgrefurl=https%3A%2F%2Fspectrum.ieee.org%2Ffirst-digital-camera-history&docid=VRB4KoeR4N1LdM&w=1200&h=900",
            "position": 43
        },
        {
            "title": "Upgraded 4K 64MP Digital Camera for Photography Beginners, Video, YouTube  Vlog, 4\" WiFi Touch Screen with Flash, 32GB SD Card, Lens Hood, 3000mAH ...",
            "imageUrl": "https://img.kentfaith.com/cache/catalog/products/us/GW41.0104/GW41.0104-1-518x518.jpg",
            "imageWidth": 518,
            "imageHeight": 518,
            "thumbnailUrl": "https://encrypted-tbn0.gstatic.com/images?q=tbn:ANd9GcSk1W5CXNmLbcuD8hl_8m9Ttn9T8aZ46dhOrg&s",
            "thumbnailWidth": 225,
            "thumbnailHeight": 225,
            "source": "K&F Concept",
            "domain": "www.kentfaith.com",
            "link": "https://www.kentfaith.com/GW41.0104_4k-digital-camera-for-photography-video-64mp-wifi-touch-screen-vlogging-camera-for-youtube-with-flas",
            "googleUrl": "https://www.google.com/imgres?imgurl=https%3A%2F%2Fimg.kentfaith.com%2Fcache%2Fcatalog%2Fproducts%2Fus%2FGW41.0104%2FGW41.0104-1-518x518.jpg&tbnid=AH_6X_xTMDE3QM&imgrefurl=https%3A%2F%2Fwww.kentfaith.com%2FGW41.0104_4k-digital-camera-for-photography-video-64mp-wifi-touch-screen-vlogging-camera-for-youtube-with-flas&docid=BKYcjUAfboM3tM&w=518&h=518",
            "position": 44
        },
        {
            "title": "Sony Cyber-shot DSC-WX7 16.2MP Digital Camera Pink Carl ...",
            "imageUrl": "https://i.ebayimg.com/images/g/8dQAAOSwST9j9Mfs/s-l1200.jpg",
            "imageWidth": 1080,
            "imageHeight": 1080,
            "thumbnailUrl": "https://encrypted-tbn0.gstatic.com/images?q=tbn:ANd9GcShZiFJGRr695iFt48b10RKJK8OWJyga8sz9A&s",
            "thumbnailWidth": 225,
            "thumbnailHeight": 225,
            "source": "eBay",
            "domain": "www.ebay.com",
            "link": "https://www.ebay.com/itm/385432232108",
            "googleUrl": "https://www.google.com/imgres?imgurl=https%3A%2F%2Fi.ebayimg.com%2Fimages%2Fg%2F8dQAAOSwST9j9Mfs%2Fs-l1200.jpg&tbnid=vc4-ROkH2xmwlM&imgrefurl=https%3A%2F%2Fwww.ebay.com%2Fitm%2F385432232108&docid=oSF1Yazl5Hed0M&w=1080&h=1080",
            "position": 45
        },
        {
            "title": "Ricoh GR III and GR IIIx Digital Camera Review: Nearly the ...",
            "imageUrl": "https://media.wired.com/photos/66bbb29e8cd2099bda5c316e/2:3/w_1200,h_1800,c_limit/Ricoh-GR-IIIx-Compact-Camera-Reviewer-Collage-082024-SOURCE-Scott-Gilbertson.jpg",
            "imageWidth": 1200,
            "imageHeight": 1800,
            "thumbnailUrl": "https://encrypted-tbn0.gstatic.com/images?q=tbn:ANd9GcRIqUBMXvOSXflWo03Za1oa903g_5KMsq06kA&s",
            "thumbnailWidth": 183,
            "thumbnailHeight": 275,
            "source": "WIRED",
            "domain": "www.wired.com",
            "link": "https://www.wired.com/review/ricoh-gr-iii-and-gr-iiix-digital-cameras/",
            "googleUrl": "https://www.google.com/imgres?imgurl=https%3A%2F%2Fmedia.wired.com%2Fphotos%2F66bbb29e8cd2099bda5c316e%2F2%3A3%2Fw_1200%2Ch_1800%2Cc_limit%2FRicoh-GR-IIIx-Compact-Camera-Reviewer-Collage-082024-SOURCE-Scott-Gilbertson.jpg&tbnid=eISn_SqzicF9CM&imgrefurl=https%3A%2F%2Fwww.wired.com%2Freview%2Fricoh-gr-iii-and-gr-iiix-digital-cameras%2F&docid=DXoICEIjJppgyM&w=1200&h=1800",
            "position": 46
        },
        {
            "title": "Best cameras for photos and videos 2024: From beginner to ...",
            "imageUrl": "https://cdn.mos.cms.futurecdn.net/GXHa4PWwDPx7tGQG9MDQvK.jpg",
            "imageWidth": 2133,
            "imageHeight": 1200,
            "thumbnailUrl": "https://encrypted-tbn0.gstatic.com/images?q=tbn:ANd9GcRlzPtROZNDH2a5yFEtxZdXPMtOGTsmxvLi8Q&s",
            "thumbnailWidth": 299,
            "thumbnailHeight": 168,
            "source": "Space.com",
            "domain": "www.space.com",
            "link": "https://www.space.com/best-cameras",
            "googleUrl": "https://www.google.com/imgres?imgurl=https%3A%2F%2Fcdn.mos.cms.futurecdn.net%2FGXHa4PWwDPx7tGQG9MDQvK.jpg&tbnid=n-9gzgOscfeMeM&imgrefurl=https%3A%2F%2Fwww.space.com%2Fbest-cameras&docid=1ToIAdcCA7MIiM&w=2133&h=1200",
            "position": 47
        },
        {
            "title": "1080P Pink Digital Camera Mini Camera for Photography, Vlogging Camera with  Anti-Shake, 44 Million, 16x Digital Zoom, 2.5in LCD Screen, Continuous ...",
            "imageUrl": "https://m.media-amazon.com/images/I/51SkHoKF0+L._AC_UF894,1000_QL80_.jpg",
            "imageWidth": 894,
            "imageHeight": 483,
            "thumbnailUrl": "https://encrypted-tbn0.gstatic.com/images?q=tbn:ANd9GcQpkAqMkKKv0Ie1v6daJRrK3AtXxgO-ciAriw&s",
            "thumbnailWidth": 306,
            "thumbnailHeight": 165,
            "source": "Amazon.com",
            "domain": "www.amazon.com",
            "link": "https://www.amazon.com/Photography-Vlogging-Anti-Shake-Continuous-Professional/dp/B0CDKXQQ9W",
            "googleUrl": "https://www.google.com/imgres?imgurl=https%3A%2F%2Fm.media-amazon.com%2Fimages%2FI%2F51SkHoKF0%2BL._AC_UF894%2C1000_QL80_.jpg&tbnid=J8Xemy3LoBx1iM&imgrefurl=https%3A%2F%2Fwww.amazon.com%2FPhotography-Vlogging-Anti-Shake-Continuous-Professional%2Fdp%2FB0CDKXQQ9W&docid=Ysr7sDseMCKTRM&w=894&h=483",
            "position": 48
        },
        {
            "title": "NBD Digital Camera 4K 48MP Compact Camera, 3.0 Inch Ultra ...",
            "imageUrl": "https://i.ebayimg.com/images/g/3HsAAOSwjW5jLbuy/s-l1200.jpg",
            "imageWidth": 612,
            "imageHeight": 612,
            "thumbnailUrl": "https://encrypted-tbn0.gstatic.com/images?q=tbn:ANd9GcRqkpxYJg93kGnLkb4h2d5i94fXPNdrUypNQA&s",
            "thumbnailWidth": 225,
            "thumbnailHeight": 225,
            "source": "eBay",
            "domain": "www.ebay.com",
            "link": "https://www.ebay.com/itm/363990526007",
            "googleUrl": "https://www.google.com/imgres?imgurl=https%3A%2F%2Fi.ebayimg.com%2Fimages%2Fg%2F3HsAAOSwjW5jLbuy%2Fs-l1200.jpg&tbnid=aK-meIt6TQwJoM&imgrefurl=https%3A%2F%2Fwww.ebay.com%2Fitm%2F363990526007&docid=NTD5ahsGDhrYRM&w=612&h=612",
            "position": 49
        },
        {
            "title": "6 best point-and-shoot cameras of 2024, tested by our editors",
            "imageUrl": "https://media-cldnry.s-nbcnews.com/image/upload/t_fit-560w,f_auto,q_auto:best/rockcms/2023-12/231204-point-and-shoots-vl-main-d9f771.jpg",
            "imageWidth": 560,
            "imageHeight": 280,
            "thumbnailUrl": "https://encrypted-tbn0.gstatic.com/images?q=tbn:ANd9GcSf0rRkqsd3pL817zrzJiF3ZhH9Zuu90_MTkw&s",
            "thumbnailWidth": 318,
            "thumbnailHeight": 159,
            "source": "NBC News",
            "domain": "www.nbcnews.com",
            "link": "https://www.nbcnews.com/select/shopping/best-point-and-shoot-cameras-rcna130454",
            "googleUrl": "https://www.google.com/imgres?imgurl=https%3A%2F%2Fmedia-cldnry.s-nbcnews.com%2Fimage%2Fupload%2Ft_fit-560w%2Cf_auto%2Cq_auto%3Abest%2Frockcms%2F2023-12%2F231204-point-and-shoots-vl-main-d9f771.jpg&tbnid=DStSMFFx1HbbHM&imgrefurl=https%3A%2F%2Fwww.nbcnews.com%2Fselect%2Fshopping%2Fbest-point-and-shoot-cameras-rcna130454&docid=SpSTw1kRwiFDZM&w=560&h=280",
            "position": 50
        },
        {
            "title": "MARVUE Digital Camera 4K UHD 44MP Vlogging Camera, Autofocus Compact Camera  with 16X Digital Zoom, Point and Shoot Digital Camera with 32GB SD Card &  ...",
            "imageUrl": "https://i5.walmartimages.com/seo/MARVUE-Digital-Camera-4K-UHD-44MP-Vlogging-Camera-Autofocus-Compact-16X-Zoom-Point-Shoot-32GB-SD-Card-2-Batteries-Blue_f7a51c0f-dc14-41ab-8dbd-62ebdc297575.6242bc53d525da48e17fcda4d948b528.jpeg",
            "imageWidth": 1600,
            "imageHeight": 1600,
            "thumbnailUrl": "https://encrypted-tbn0.gstatic.com/images?q=tbn:ANd9GcRcUCv4NYp0QWS17oId_kgaByvj0YCEOOQkzg&s",
            "thumbnailWidth": 225,
            "thumbnailHeight": 225,
            "source": "Walmart",
            "domain": "www.walmart.com",
            "link": "https://www.walmart.com/ip/MARVUE-Digital-Camera-4K-UHD-44MP-Vlogging-Camera-Autofocus-Compact-16X-Zoom-Point-Shoot-32GB-SD-Card-2-Batteries-Blue/5252237341",
            "googleUrl": "https://www.google.com/imgres?imgurl=https%3A%2F%2Fi5.walmartimages.com%2Fseo%2FMARVUE-Digital-Camera-4K-UHD-44MP-Vlogging-Camera-Autofocus-Compact-16X-Zoom-Point-Shoot-32GB-SD-Card-2-Batteries-Blue_f7a51c0f-dc14-41ab-8dbd-62ebdc297575.6242bc53d525da48e17fcda4d948b528.jpeg&tbnid=ke28XT2Tu92q_M&imgrefurl=https%3A%2F%2Fwww.walmart.com%2Fip%2FMARVUE-Digital-Camera-4K-UHD-44MP-Vlogging-Camera-Autofocus-Compact-16X-Zoom-Point-Shoot-32GB-SD-Card-2-Batteries-Blue%2F5252237341&docid=oywlfSacWAn5xM&w=1600&h=1600",
            "position": 51
        },
        {
            "title": "Best camera for photography 2024: top picks for any budget ...",
            "imageUrl": "https://cdn.mos.cms.futurecdn.net/poQoJs9cdG3GKMtaKeqXrG.png",
            "imageWidth": 2000,
            "imageHeight": 1125,
            "thumbnailUrl": "https://encrypted-tbn0.gstatic.com/images?q=tbn:ANd9GcSEZ7aSX80WZ4cVA6OkHe-YBsIURJZOW2TlNw&s",
            "thumbnailWidth": 300,
            "thumbnailHeight": 168,
            "source": "TechRadar",
            "domain": "www.techradar.com",
            "link": "https://www.techradar.com/news/best-camera",
            "googleUrl": "https://www.google.com/imgres?imgurl=https%3A%2F%2Fcdn.mos.cms.futurecdn.net%2FpoQoJs9cdG3GKMtaKeqXrG.png&tbnid=EgeeO69wGNw6kM&imgrefurl=https%3A%2F%2Fwww.techradar.com%2Fnews%2Fbest-camera&docid=hZ-tcg0WJ1cDrM&w=2000&h=1125",
            "position": 52
        },
        {
            "title": "Canon EOS R5 Mirrorless Digital Camera (R5 Camera Body) B&H ...",
            "imageUrl": "https://www.bhphotovideo.com/cdn-cgi/image/fit=scale-down,width=500,quality=95/https://www.bhphotovideo.com/images/images500x500/canon_eos_r5_mirrorless_digital_1594282826_1547009.jpg",
            "imageWidth": 500,
            "imageHeight": 500,
            "thumbnailUrl": "https://encrypted-tbn0.gstatic.com/images?q=tbn:ANd9GcS0yoeUOHvpe8f7NvLDB5ki9maC7vWA5cDXZQ&s",
            "thumbnailWidth": 225,
            "thumbnailHeight": 225,
            "source": "B&H",
            "domain": "www.bhphotovideo.com",
            "link": "https://www.bhphotovideo.com/c/product/1547009-REG/canon_eos_r5_mirrorless_digital.html",
            "googleUrl": "https://www.google.com/imgres?imgurl=https%3A%2F%2Fwww.bhphotovideo.com%2Fcdn-cgi%2Fimage%2Ffit%3Dscale-down%2Cwidth%3D500%2Cquality%3D95%2Fhttps%3A%2F%2Fwww.bhphotovideo.com%2Fimages%2Fimages500x500%2Fcanon_eos_r5_mirrorless_digital_1594282826_1547009.jpg&tbnid=C3DHHygIpR1AeM&imgrefurl=https%3A%2F%2Fwww.bhphotovideo.com%2Fc%2Fproduct%2F1547009-REG%2Fcanon_eos_r5_mirrorless_digital.html&docid=uDBBSORpTAJQEM&w=500&h=500",
            "position": 53
        },
        {
            "title": "How to Choose a Camera (2024): Sensors, Megapixels, Terms ...",
            "imageUrl": "http://media.wired.com/photos/66600785cbcdb04f5b0f4316/master/pass/How-to-Buy-a-Camera-collage-062024-SOURCE-Scott-Gilbertson.jpg",
            "imageWidth": 2400,
            "imageHeight": 1800,
            "thumbnailUrl": "https://encrypted-tbn0.gstatic.com/images?q=tbn:ANd9GcREkRH8-lCIRfqlKIyPYx2ZntVKzwa3sQY9WA&s",
            "thumbnailWidth": 259,
            "thumbnailHeight": 194,
            "source": "WIRED",
            "domain": "www.wired.com",
            "link": "https://www.wired.com/story/how-to-choose-a-camera/",
            "googleUrl": "https://www.google.com/imgres?imgurl=http%3A%2F%2Fmedia.wired.com%2Fphotos%2F66600785cbcdb04f5b0f4316%2Fmaster%2Fpass%2FHow-to-Buy-a-Camera-collage-062024-SOURCE-Scott-Gilbertson.jpg&tbnid=EfT6g8_OlnKzyM&imgrefurl=https%3A%2F%2Fwww.wired.com%2Fstory%2Fhow-to-choose-a-camera%2F&docid=ql7OK3jv0_zOZM&w=2400&h=1800",
            "position": 54
        },
        {
            "title": "HD Digital Camera 44MP 1080P FHD Photography Camera Video Camcorder 16X  Zoom Portable Vlogging Camera for Kids Adults Beginners - AliExpress",
            "imageUrl": "https://ae01.alicdn.com/kf/S010316b6e1e1444cbc433e84822108a61/HD-Digital-Camera-44MP-1080P-FHD-Photography-Camera-Video-Camcorder-16X-Zoom-Portable-Vlogging-Camera-for.png",
            "imageWidth": 1600,
            "imageHeight": 1600,
            "thumbnailUrl": "https://encrypted-tbn0.gstatic.com/images?q=tbn:ANd9GcS1g2tzDHmDkcI-0HLCwpWiUOflf6_jG_JBFg&s",
            "thumbnailWidth": 225,
            "thumbnailHeight": 225,
            "source": "AliExpress",
            "domain": "www.aliexpress.com",
            "link": "https://www.aliexpress.com/item/1005005227533379.html",
            "googleUrl": "https://www.google.com/imgres?imgurl=https%3A%2F%2Fae01.alicdn.com%2Fkf%2FS010316b6e1e1444cbc433e84822108a61%2FHD-Digital-Camera-44MP-1080P-FHD-Photography-Camera-Video-Camcorder-16X-Zoom-Portable-Vlogging-Camera-for.png&tbnid=-sVOQy3sGi2CRM&imgrefurl=https%3A%2F%2Fwww.aliexpress.com%2Fitem%2F1005005227533379.html&docid=5-wqXsZgZk5snM&w=1600&h=1600",
            "position": 55
        },
        {
            "title": "8 Best Digital Cameras for Beginners Under $1,000 2018 | The ...",
            "imageUrl": "https://pyxis.nymag.com/v1/imgs/dfb/03c/bbf932df3accf8c09ebbbae70a438f45d4-2----.rhorizontal.w600.jpg",
            "imageWidth": 600,
            "imageHeight": 400,
            "thumbnailUrl": "https://encrypted-tbn0.gstatic.com/images?q=tbn:ANd9GcQQ4khjGSZiOS7ST7aE86KO3UBcfLkwROyPRA&s",
            "thumbnailWidth": 275,
            "thumbnailHeight": 183,
            "source": "New York Magazine",
            "domain": "nymag.com",
            "link": "https://nymag.com/strategist/article/best-digital-cameras-beginners-under-usd1000.html",
            "googleUrl": "https://www.google.com/imgres?imgurl=https%3A%2F%2Fpyxis.nymag.com%2Fv1%2Fimgs%2Fdfb%2F03c%2Fbbf932df3accf8c09ebbbae70a438f45d4-2----.rhorizontal.w600.jpg&tbnid=5R1iUDhNOgiECM&imgrefurl=https%3A%2F%2Fnymag.com%2Fstrategist%2Farticle%2Fbest-digital-cameras-beginners-under-usd1000.html&docid=O8T81Gdo1xB2aM&w=600&h=400",
            "position": 56
        },
        {
            "title": "Shop Cameras at Target",
            "imageUrl": "https://target.scene7.com/is/image/Target/GUEST_69b0f1ed-9a10-4559-891b-de4e55043419",
            "imageWidth": 400,
            "imageHeight": 400,
            "thumbnailUrl": "https://encrypted-tbn0.gstatic.com/images?q=tbn:ANd9GcRTK2LRQFnpIKu0zWgswQPL3MJ7jrn0aXw2tQ&s",
            "thumbnailWidth": 225,
            "thumbnailHeight": 225,
            "source": "Target",
            "domain": "www.target.com",
            "link": "https://www.target.com/c/cameras-camcorders-electronics/-/N-5xtez",
            "googleUrl": "https://www.google.com/imgres?imgurl=https%3A%2F%2Ftarget.scene7.com%2Fis%2Fimage%2FTarget%2FGUEST_69b0f1ed-9a10-4559-891b-de4e55043419&tbnid=-bDdvgqKe8lUTM&imgrefurl=https%3A%2F%2Fwww.target.com%2Fc%2Fcameras-camcorders-electronics%2F-%2FN-5xtez&docid=IKejKxwLzlJQ1M&w=400&h=400",
            "position": 57
        },
        {
            "title": "6 Best high-end cameras: Digital Photography Review",
            "imageUrl": "https://2.img-dpreview.com/files/p/E~TS590x0~articles/5685078226/sony_a7cr.jpeg",
            "imageWidth": 590,
            "imageHeight": 393,
            "thumbnailUrl": "https://encrypted-tbn0.gstatic.com/images?q=tbn:ANd9GcSYxf9hNpldJHKBufuKmLeDthU9MAQkjb9qXg&s",
            "thumbnailWidth": 275,
            "thumbnailHeight": 183,
            "source": "Digital Photography Review",
            "domain": "www.dpreview.com",
            "link": "https://www.dpreview.com/reviews/buying-guide-best-high-end-cameras",
            "googleUrl": "https://www.google.com/imgres?imgurl=https%3A%2F%2F2.img-dpreview.com%2Ffiles%2Fp%2FE~TS590x0~articles%2F5685078226%2Fsony_a7cr.jpeg&tbnid=hcd1sERRNbSAkM&imgrefurl=https%3A%2F%2Fwww.dpreview.com%2Freviews%2Fbuying-guide-best-high-end-cameras&docid=bZuSRHfV5AJtCM&w=590&h=393",
            "position": 58
        },
        {
            "title": "How Often You Should Replace Your Digital Camera & How To ...",
            "imageUrl": "https://images.squarespace-cdn.com/content/v1/53a2b3a1e4b0a5020bebe676/1612444085880-GNREGFNPULILPOHHAR5A/How-Often-Should-You-Replace-Your-Digital-Camera.jpg",
            "imageWidth": 1000,
            "imageHeight": 672,
            "thumbnailUrl": "https://encrypted-tbn0.gstatic.com/images?q=tbn:ANd9GcQeH6gwrrc5znyG5GgN51BUynBqcbtU0cFAMw&s",
            "thumbnailWidth": 274,
            "thumbnailHeight": 184,
            "source": "Nicholas Goodden",
            "domain": "www.nicholasgooddenphotography.co.uk",
            "link": "https://www.nicholasgooddenphotography.co.uk/london-blog/how-often-should-you-replace-your-digital-camera",
            "googleUrl": "https://www.google.com/imgres?imgurl=https%3A%2F%2Fimages.squarespace-cdn.com%2Fcontent%2Fv1%2F53a2b3a1e4b0a5020bebe676%2F1612444085880-GNREGFNPULILPOHHAR5A%2FHow-Often-Should-You-Replace-Your-Digital-Camera.jpg&tbnid=NlFJE5kNJ8LAjM&imgrefurl=https%3A%2F%2Fwww.nicholasgooddenphotography.co.uk%2Flondon-blog%2Fhow-often-should-you-replace-your-digital-camera&docid=4ruhGni2h3e9YM&w=1000&h=672",
            "position": 59
        },
        {
            "title": "Best Camera to Buy in 2024 - CNET",
            "imageUrl": "https://www.cnet.com/a/img/resize/23475c0cad276d40f336890a158561a64662c77b/hub/2022/08/30/2a8b8b93-d0ce-45bb-80b9-1b3874c027c9/best-camera-cnet-2022-canon-sony-nikon-fujifilm.jpg?auto=webp&width=1200",
            "imageWidth": 1200,
            "imageHeight": 800,
            "thumbnailUrl": "https://encrypted-tbn0.gstatic.com/images?q=tbn:ANd9GcTDqnAkrqHl_PGwvMfpFmf-P3M6IUlPF90kYg&s",
            "thumbnailWidth": 275,
            "thumbnailHeight": 183,
            "source": "CNET",
            "domain": "www.cnet.com",
            "link": "https://www.cnet.com/tech/computing/best-camera-to-buy/",
            "googleUrl": "https://www.google.com/imgres?imgurl=https%3A%2F%2Fwww.cnet.com%2Fa%2Fimg%2Fresize%2F23475c0cad276d40f336890a158561a64662c77b%2Fhub%2F2022%2F08%2F30%2F2a8b8b93-d0ce-45bb-80b9-1b3874c027c9%2Fbest-camera-cnet-2022-canon-sony-nikon-fujifilm.jpg%3Fauto%3Dwebp%26width%3D1200&tbnid=2K198Oa-JTln2M&imgrefurl=https%3A%2F%2Fwww.cnet.com%2Ftech%2Fcomputing%2Fbest-camera-to-buy%2F&docid=V9cYz7Rm8TQLSM&w=1200&h=800",
            "position": 60
        },
        {
            "title": "Sony W830 Compact Camera with 8x Optical Zoom",
            "imageUrl": "https://www.sony.com/image/b2e494fbba7667cdbe3dbd60e7f7ff50?fmt=jpeg&wid=1160&qlt=43",
            "imageWidth": 1160,
            "imageHeight": 920,
            "thumbnailUrl": "https://encrypted-tbn0.gstatic.com/images?q=tbn:ANd9GcRTWGBDmnn14zFgYHAP6px8ufHJ5qYEGculmA&s",
            "thumbnailWidth": 252,
            "thumbnailHeight": 200,
            "source": "Sony",
            "domain": "www.sony.com",
            "link": "https://www.sony.com/ug/electronics/cyber-shot-compact-cameras/dsc-w830",
            "googleUrl": "https://www.google.com/imgres?imgurl=https%3A%2F%2Fwww.sony.com%2Fimage%2Fb2e494fbba7667cdbe3dbd60e7f7ff50%3Ffmt%3Djpeg%26wid%3D1160%26qlt%3D43&tbnid=uSUmw5wvYf1jNM&imgrefurl=https%3A%2F%2Fwww.sony.com%2Fug%2Felectronics%2Fcyber-shot-compact-cameras%2Fdsc-w830&docid=kIwHHwJKOYqtUM&w=1160&h=920",
            "position": 61
        },
        {
            "title": "Ricoh GR III and GR IIIx Digital Camera Review: Nearly the ...",
            "imageUrl": "https://media.wired.com/photos/66bbb29e8cd2099bda5c316e/191:100/w_1280,c_limit/Ricoh-GR-IIIx-Compact-Camera-Reviewer-Collage-082024-SOURCE-Scott-Gilbertson.jpg",
            "imageWidth": 1280,
            "imageHeight": 670,
            "thumbnailUrl": "https://encrypted-tbn0.gstatic.com/images?q=tbn:ANd9GcRhjMvGJrXmneo2K_kyUOLoXXCNQrDtijpe_Q&s",
            "thumbnailWidth": 310,
            "thumbnailHeight": 162,
            "source": "WIRED",
            "domain": "www.wired.com",
            "link": "https://www.wired.com/review/ricoh-gr-iii-and-gr-iiix-digital-cameras/",
            "googleUrl": "https://www.google.com/imgres?imgurl=https%3A%2F%2Fmedia.wired.com%2Fphotos%2F66bbb29e8cd2099bda5c316e%2F191%3A100%2Fw_1280%2Cc_limit%2FRicoh-GR-IIIx-Compact-Camera-Reviewer-Collage-082024-SOURCE-Scott-Gilbertson.jpg&tbnid=jMn8O_oesgE57M&imgrefurl=https%3A%2F%2Fwww.wired.com%2Freview%2Fricoh-gr-iii-and-gr-iiix-digital-cameras%2F&docid=DXoICEIjJppgyM&w=1280&h=670",
            "position": 62
        },
        {
            "title": "The best point and shoot camera in 2024 | Digital Camera World",
            "imageUrl": "https://cdn.mos.cms.futurecdn.net/y7UbkLexq6qH2soxysPFeT-1200-80.jpg",
            "imageWidth": 1200,
            "imageHeight": 675,
            "thumbnailUrl": "https://encrypted-tbn0.gstatic.com/images?q=tbn:ANd9GcSX4DwMJZDY91LzEJnd4z_C3yrAWJA6rlWluw&s",
            "thumbnailWidth": 300,
            "thumbnailHeight": 168,
            "source": "Digital Camera World",
            "domain": "www.digitalcameraworld.com",
            "link": "https://www.digitalcameraworld.com/buying-guides/best-point-and-shoot-cameras",
            "googleUrl": "https://www.google.com/imgres?imgurl=https%3A%2F%2Fcdn.mos.cms.futurecdn.net%2Fy7UbkLexq6qH2soxysPFeT-1200-80.jpg&tbnid=N5ufnHGBVgKOhM&imgrefurl=https%3A%2F%2Fwww.digitalcameraworld.com%2Fbuying-guides%2Fbest-point-and-shoot-cameras&docid=HKR-DubynqMb-M&w=1200&h=675",
            "position": 63
        },
        {
            "title": "Why digital cameras are making a comeback",
            "imageUrl": "https://i.ytimg.com/vi/2yujDMEbREU/hq720.jpg?sqp=-oaymwEhCK4FEIIDSFryq4qpAxMIARUAAAAAGAElAADIQj0AgKJD&rs=AOn4CLDxL4F69doFiEV58C4cHBerj6vrTA",
            "imageWidth": 686,
            "imageHeight": 386,
            "thumbnailUrl": "https://encrypted-tbn0.gstatic.com/images?q=tbn:ANd9GcQNJtz4e-5fCI52Y9zq3p00wMC29_4xnzpNog&s",
            "thumbnailWidth": 299,
            "thumbnailHeight": 168,
            "source": "YouTube",
            "domain": "m.youtube.com",
            "link": "https://m.youtube.com/watch?v=2yujDMEbREU",
            "googleUrl": "https://www.google.com/imgres?imgurl=https%3A%2F%2Fi.ytimg.com%2Fvi%2F2yujDMEbREU%2Fhq720.jpg%3Fsqp%3D-oaymwEhCK4FEIIDSFryq4qpAxMIARUAAAAAGAElAADIQj0AgKJD%26rs%3DAOn4CLDxL4F69doFiEV58C4cHBerj6vrTA&tbnid=XRsV8R2AtFXgPM&imgrefurl=https%3A%2F%2Fm.youtube.com%2Fwatch%3Fv%3D2yujDMEbREU&docid=CQFy19WoXevylM&w=686&h=386",
            "position": 64
        },
        {
            "title": "Digital Photography 101: A Beginners Guide To Photography ...",
            "imageUrl": "https://i.ytimg.com/vi/51QoR-RDpPM/sddefault.jpg",
            "imageWidth": 640,
            "imageHeight": 480,
            "thumbnailUrl": "https://encrypted-tbn0.gstatic.com/images?q=tbn:ANd9GcSgSGrIjS4YRNQIkfmXhKgP1zLXf_fTUnT-LQ&s",
            "thumbnailWidth": 259,
            "thumbnailHeight": 194,
            "source": "YouTube",
            "domain": "m.youtube.com",
            "link": "https://m.youtube.com/watch?v=51QoR-RDpPM",
            "googleUrl": "https://www.google.com/imgres?imgurl=https%3A%2F%2Fi.ytimg.com%2Fvi%2F51QoR-RDpPM%2Fsddefault.jpg&tbnid=w-uOae9BZfPGMM&imgrefurl=https%3A%2F%2Fm.youtube.com%2Fwatch%3Fv%3D51QoR-RDpPM&docid=fuJGiN5JMQbWJM&w=640&h=480",
            "position": 65
        },
        {
            "title": "Beginner's Guide to Types of Cameras for Digital Photography ...",
            "imageUrl": "https://ipt.images.tshiftcdn.com/206727/x/0/1-types-of-cameras-digital.jpg?ar=1.91%3A1&w=1200&fit=crop",
            "imageWidth": 1200,
            "imageHeight": 801,
            "thumbnailUrl": "https://encrypted-tbn0.gstatic.com/images?q=tbn:ANd9GcRBxpWcKyPsZWKB3uJy5QZL1KzFt4M6qTZweA&s",
            "thumbnailWidth": 275,
            "thumbnailHeight": 183,
            "source": "Iceland Photo Tours",
            "domain": "iceland-photo-tours.com",
            "link": "https://iceland-photo-tours.com/articles/camera-and-gear-reviews/beginner-s-guide-to-types-of-cameras-for-photography",
            "googleUrl": "https://www.google.com/imgres?imgurl=https%3A%2F%2Fipt.images.tshiftcdn.com%2F206727%2Fx%2F0%2F1-types-of-cameras-digital.jpg%3Far%3D1.91%253A1%26w%3D1200%26fit%3Dcrop&tbnid=F9DbCdja7gL7AM&imgrefurl=https%3A%2F%2Ficeland-photo-tours.com%2Farticles%2Fcamera-and-gear-reviews%2Fbeginner-s-guide-to-types-of-cameras-for-photography&docid=1InK3S_XLhkemM&w=1200&h=801",
            "position": 66
        },
        {
            "title": "History of Digital Cameras – Legacybox",
            "imageUrl": "https://legacybox.com/cdn/shop/articles/photo-1543785832-0781599790c2_1920x.progressive.jpg?v=1613403332",
            "imageWidth": 1399,
            "imageHeight": 934,
            "thumbnailUrl": "https://encrypted-tbn0.gstatic.com/images?q=tbn:ANd9GcSY9cSV4LYG4OXguvxs3WPABJ_nVUEL2VeNlA&s",
            "thumbnailWidth": 275,
            "thumbnailHeight": 183,
            "source": "Legacybox",
            "domain": "legacybox.com",
            "link": "https://legacybox.com/blogs/analog/history-of-digital-cameras",
            "googleUrl": "https://www.google.com/imgres?imgurl=https%3A%2F%2Flegacybox.com%2Fcdn%2Fshop%2Farticles%2Fphoto-1543785832-0781599790c2_1920x.progressive.jpg%3Fv%3D1613403332&tbnid=RgTkJx-wnd0hTM&imgrefurl=https%3A%2F%2Flegacybox.com%2Fblogs%2Fanalog%2Fhistory-of-digital-cameras&docid=4Ew_GpwrVjoURM&w=1399&h=934",
            "position": 67
        },
        {
            "title": "Saneen Digital Cameras for Photography 4K 48MP Vlogging Camera 3.0 inch  Ultra HD Screen 16X Digital Zoom Manual Focus Students Compact Camera with  ...",
            "imageUrl": "https://i5.walmartimages.com/seo/Saneen-Digital-Camera-for-Photography-and-Video-4K-48MP-Vlogging-Camera-for-YouTube-Black-Perfect-for-Beginners_955efb9d-50ca-492f-b20e-4cbd30861c30.e751e5a38ee20ff510caf44f8fdb0b8a.jpeg",
            "imageWidth": 1600,
            "imageHeight": 1600,
            "thumbnailUrl": "https://encrypted-tbn0.gstatic.com/images?q=tbn:ANd9GcQzjwnM0j8kR-37aR44htzhAqkZE2fNGLwksQ&s",
            "thumbnailWidth": 225,
            "thumbnailHeight": 225,
            "source": "Walmart",
            "domain": "www.walmart.com",
            "link": "https://www.walmart.com/ip/Saneen-Digital-Camera-for-Photography-and-Video-4K-48MP-Vlogging-Camera-for-YouTube-Black-Perfect-for-Beginners/3037478429",
            "googleUrl": "https://www.google.com/imgres?imgurl=https%3A%2F%2Fi5.walmartimages.com%2Fseo%2FSaneen-Digital-Camera-for-Photography-and-Video-4K-48MP-Vlogging-Camera-for-YouTube-Black-Perfect-for-Beginners_955efb9d-50ca-492f-b20e-4cbd30861c30.e751e5a38ee20ff510caf44f8fdb0b8a.jpeg&tbnid=VBCFEgQ8PPjoxM&imgrefurl=https%3A%2F%2Fwww.walmart.com%2Fip%2FSaneen-Digital-Camera-for-Photography-and-Video-4K-48MP-Vlogging-Camera-for-YouTube-Black-Perfect-for-Beginners%2F3037478429&docid=wdWtQWILjRCCjM&w=1600&h=1600",
            "position": 68
        },
        {
            "title": "SONY Cyber-Shot DSC-W830 Digital Camera Bundle. Value Kit ...",
            "imageUrl": "https://images.jdmagicbox.com/quickquotes/images_main/sony-cyber-shot-dsc-w830-digital-camera-bundle-value-kit-with-accessories-145332269-1s4wv.jpg",
            "imageWidth": 500,
            "imageHeight": 500,
            "thumbnailUrl": "https://encrypted-tbn0.gstatic.com/images?q=tbn:ANd9GcSJVWPXYHrpa1aQL4vubv1yTisL47vSZn9Byw&s",
            "thumbnailWidth": 225,
            "thumbnailHeight": 225,
            "source": "Justdial",
            "domain": "www.justdial.com",
            "link": "https://www.justdial.com/jdmart/Delhi/SONY-Cyber-Shot-DSC-W830-Digital-Camera-Bundle-Value-Kit-with-Accessories/pid-145332269/011PXX11-XX11-171110164104-R4G7",
            "googleUrl": "https://www.google.com/imgres?imgurl=https%3A%2F%2Fimages.jdmagicbox.com%2Fquickquotes%2Fimages_main%2Fsony-cyber-shot-dsc-w830-digital-camera-bundle-value-kit-with-accessories-145332269-1s4wv.jpg&tbnid=cR6CUeAlKiY4TM&imgrefurl=https%3A%2F%2Fwww.justdial.com%2Fjdmart%2FDelhi%2FSONY-Cyber-Shot-DSC-W830-Digital-Camera-Bundle-Value-Kit-with-Accessories%2Fpid-145332269%2F011PXX11-XX11-171110164104-R4G7&docid=SiRcHqoUBu-7wM&w=500&h=500",
            "position": 69
        },
        {
            "title": "Sony FX30 Digital Cinema Camera ILME-FX30B B&H Photo Video",
            "imageUrl": "https://www.bhphotovideo.com/images/fb/sony_ilme_fx30_fx30_digital_cinema_camera_1729317.jpg",
            "imageWidth": 2971,
            "imageHeight": 1560,
            "thumbnailUrl": "https://encrypted-tbn0.gstatic.com/images?q=tbn:ANd9GcSUSMSRxFKjEzMk5W4SCa-P1vF_f_yIuFKRYg&s",
            "thumbnailWidth": 310,
            "thumbnailHeight": 163,
            "source": "B&H",
            "domain": "www.bhphotovideo.com",
            "link": "https://www.bhphotovideo.com/c/product/1729317-REG/sony_ilme_fx30_fx30_digital_cinema_camera.html",
            "googleUrl": "https://www.google.com/imgres?imgurl=https%3A%2F%2Fwww.bhphotovideo.com%2Fimages%2Ffb%2Fsony_ilme_fx30_fx30_digital_cinema_camera_1729317.jpg&tbnid=ER0ilaS1y_NdzM&imgrefurl=https%3A%2F%2Fwww.bhphotovideo.com%2Fc%2Fproduct%2F1729317-REG%2Fsony_ilme_fx30_fx30_digital_cinema_camera.html&docid=dkWeRjGaIKz4NM&w=2971&h=1560",
            "position": 70
        },
        {
            "title": "6 Best Digital Cameras Under $100: Reviews, Prices, Top ...",
            "imageUrl": "https://www.billboard.com/wp-content/uploads/2024/03/4k-digital-camera-under-100.jpg?w=1024",
            "imageWidth": 1024,
            "imageHeight": 1009,
            "thumbnailUrl": "https://encrypted-tbn0.gstatic.com/images?q=tbn:ANd9GcRO7bJs8INJVYDKugSzTKN2B_GjGptCyd0udA&s",
            "thumbnailWidth": 226,
            "thumbnailHeight": 223,
            "source": "Billboard",
            "domain": "www.billboard.com",
            "link": "https://www.billboard.com/culture/product-recommendations/best-digital-camera-under-100-dollars-1235621225/",
            "googleUrl": "https://www.google.com/imgres?imgurl=https%3A%2F%2Fwww.billboard.com%2Fwp-content%2Fuploads%2F2024%2F03%2F4k-digital-camera-under-100.jpg%3Fw%3D1024&tbnid=lsNbVpj_xiySRM&imgrefurl=https%3A%2F%2Fwww.billboard.com%2Fculture%2Fproduct-recommendations%2Fbest-digital-camera-under-100-dollars-1235621225%2F&docid=uWtVwQnlQ0GnDM&w=1024&h=1009",
            "position": 71
        },
        {
            "title": "What My Vintage Digital Camera Obsession Has Taught Me ...",
            "imageUrl": "https://cdn.thewirecutter.com/wp-content/media/2024/05/lessonsobsoletecameras-2048px-DSCF2606-2x1-1.jpg?width=2048&quality=75&crop=2:1&auto=webp",
            "imageWidth": 2048,
            "imageHeight": 1024,
            "thumbnailUrl": "https://encrypted-tbn0.gstatic.com/images?q=tbn:ANd9GcQ_30EiLY-vTKY-BAIKZCeirVADdYeFCznjgA&s",
            "thumbnailWidth": 318,
            "thumbnailHeight": 159,
            "source": "The New York Times",
            "domain": "www.nytimes.com",
            "link": "https://www.nytimes.com/wirecutter/reviews/vintage-digital-camera-obsession/",
            "googleUrl": "https://www.google.com/imgres?imgurl=https%3A%2F%2Fcdn.thewirecutter.com%2Fwp-content%2Fmedia%2F2024%2F05%2Flessonsobsoletecameras-2048px-DSCF2606-2x1-1.jpg%3Fwidth%3D2048%26quality%3D75%26crop%3D2%3A1%26auto%3Dwebp&tbnid=5s0cNgSaHgzhbM&imgrefurl=https%3A%2F%2Fwww.nytimes.com%2Fwirecutter%2Freviews%2Fvintage-digital-camera-obsession%2F&docid=idVZAwT6dLqhlM&w=2048&h=1024",
            "position": 72
        },
        {
            "title": "Minolta MN40WP 48.0 Megapixel Waterproof Digital Camera Blue ...",
            "imageUrl": "https://pisces.bbystatic.com/image2/BestBuy_US/images/products/6530/6530063_sd.jpg",
            "imageWidth": 3622,
            "imageHeight": 2077,
            "thumbnailUrl": "https://encrypted-tbn0.gstatic.com/images?q=tbn:ANd9GcQxGhCQ1X6ZIZGJ4Sm36o0ATQK7HxTL-G3Y_g&s",
            "thumbnailWidth": 297,
            "thumbnailHeight": 170,
            "source": "Best Buy",
            "domain": "www.bestbuy.com",
            "link": "https://www.bestbuy.com/site/minolta-mn40wp-48-0-megapixel-waterproof-digital-camera-blue/6530063.p?skuId=6530063",
            "googleUrl": "https://www.google.com/imgres?imgurl=https%3A%2F%2Fpisces.bbystatic.com%2Fimage2%2FBestBuy_US%2Fimages%2Fproducts%2F6530%2F6530063_sd.jpg&tbnid=kM16P31x5t5wXM&imgrefurl=https%3A%2F%2Fwww.bestbuy.com%2Fsite%2Fminolta-mn40wp-48-0-megapixel-waterproof-digital-camera-blue%2F6530063.p%3FskuId%3D6530063&docid=LxIE1C-hNcUwoM&w=3622&h=2077",
            "position": 73
        },
        {
            "title": "Compact Cameras | Sony Morocco",
            "imageUrl": "https://sony.scene7.com/is/image/sonyglobalsolutions/ZV-1m2?$goldenAreaImage$&fmt=png-alpha",
            "imageWidth": 764,
            "imageHeight": 470,
            "thumbnailUrl": "https://encrypted-tbn0.gstatic.com/images?q=tbn:ANd9GcTJMI5nvdDtFRKAoP0xMgXAcN_1fus5kNC9SQ&s",
            "thumbnailWidth": 286,
            "thumbnailHeight": 176,
            "source": "Sony",
            "domain": "www.sony.com",
            "link": "https://www.sony.com/en-ma/compact-cameras",
            "googleUrl": "https://www.google.com/imgres?imgurl=https%3A%2F%2Fsony.scene7.com%2Fis%2Fimage%2Fsonyglobalsolutions%2FZV-1m2%3F%24goldenAreaImage%24%26fmt%3Dpng-alpha&tbnid=bTs6i3t5k0a-jM&imgrefurl=https%3A%2F%2Fwww.sony.com%2Fen-ma%2Fcompact-cameras&docid=4eSoW4q5zWkPbM&w=764&h=470",
            "position": 74
        },
        {
            "title": "Vintage digital cameras you should actually buy | Amateur ...",
            "imageUrl": "https://amateurphotographer.com/wp-content/uploads/sites/7/2023/03/Canon-Powershot-G2-AW1-2000px.jpg?w=1024",
            "imageWidth": 1024,
            "imageHeight": 682,
            "thumbnailUrl": "https://encrypted-tbn0.gstatic.com/images?q=tbn:ANd9GcSR9dWoYToXya7WUIBej08OM-gCFQLPFXbBGQ&s",
            "thumbnailWidth": 275,
            "thumbnailHeight": 183,
            "source": "Amateur Photographer",
            "domain": "amateurphotographer.com",
            "link": "https://amateurphotographer.com/second-hand/vintage-digital-cameras-you-should-actually-buy/",
            "googleUrl": "https://www.google.com/imgres?imgurl=https%3A%2F%2Famateurphotographer.com%2Fwp-content%2Fuploads%2Fsites%2F7%2F2023%2F03%2FCanon-Powershot-G2-AW1-2000px.jpg%3Fw%3D1024&tbnid=l0qAj-AcR4yxVM&imgrefurl=https%3A%2F%2Famateurphotographer.com%2Fsecond-hand%2Fvintage-digital-cameras-you-should-actually-buy%2F&docid=8ENsVCMHRSD7MM&w=1024&h=682",
            "position": 75
        },
        {
            "title": "The best cameras in 2024 | Tom's Guide",
            "imageUrl": "https://cdn.mos.cms.futurecdn.net/4wpKrH93D37dDPTisdqGy4.jpg",
            "imageWidth": 2000,
            "imageHeight": 1125,
            "thumbnailUrl": "https://encrypted-tbn0.gstatic.com/images?q=tbn:ANd9GcRNqV1tfB4BP5W-acPcRcTXG9cHzqOKPkirNw&s",
            "thumbnailWidth": 300,
            "thumbnailHeight": 168,
            "source": "Tom's Guide",
            "domain": "www.tomsguide.com",
            "link": "https://www.tomsguide.com/us/best-cameras,review-2196.html",
            "googleUrl": "https://www.google.com/imgres?imgurl=https%3A%2F%2Fcdn.mos.cms.futurecdn.net%2F4wpKrH93D37dDPTisdqGy4.jpg&tbnid=sYlrDSolH3_u3M&imgrefurl=https%3A%2F%2Fwww.tomsguide.com%2Fus%2Fbest-cameras%2Creview-2196.html&docid=bbDiOgOXWWDUfM&w=2000&h=1125",
            "position": 76
        },
        {
            "title": "Digital vs. Film | Differences, Opinions, and Thoughts on a ...",
            "imageUrl": "https://cdn.sanity.io/images/soj3d0g3/production/1cc2d457548d375ee8d983d8a7188cdd1a23cbc1-2560x1920.jpg",
            "imageWidth": 2560,
            "imageHeight": 1920,
            "thumbnailUrl": "https://encrypted-tbn0.gstatic.com/images?q=tbn:ANd9GcS2GjcX1d7cSDQt2lUXeGW2A88SFdthATzT9g&s",
            "thumbnailWidth": 259,
            "thumbnailHeight": 194,
            "source": "Moment",
            "domain": "www.shopmoment.com",
            "link": "https://www.shopmoment.com/reviews/digital-vs-film-differences-opinions-and-thoughts-on-a-big-debate",
            "googleUrl": "https://www.google.com/imgres?imgurl=https%3A%2F%2Fcdn.sanity.io%2Fimages%2Fsoj3d0g3%2Fproduction%2F1cc2d457548d375ee8d983d8a7188cdd1a23cbc1-2560x1920.jpg&tbnid=-ub72DPYhea2AM&imgrefurl=https%3A%2F%2Fwww.shopmoment.com%2Freviews%2Fdigital-vs-film-differences-opinions-and-thoughts-on-a-big-debate&docid=GkpT6rurWxCoGM&w=2560&h=1920",
            "position": 77
        },
        {
            "title": "Digital Camera, Kids Camera with 32GB Card FHD 1080P 44MP Vlogging LCD  Screen 16X Zoom Compact Portable Mini Rechargeable Gifts for Students Teens  Adults Girls Boys-Black, (DC403Black)",
            "imageUrl": "https://m.media-amazon.com/images/I/7174tl2r1gL._AC_SL1500_.jpg",
            "imageWidth": 1500,
            "imageHeight": 1471,
            "thumbnailUrl": "https://encrypted-tbn0.gstatic.com/images?q=tbn:ANd9GcSSh4LAtFMFVIBuceRmNM5zvugC27DAN8Qo6A&s",
            "thumbnailWidth": 227,
            "thumbnailHeight": 222,
            "source": "Ubuy Palestine",
            "domain": "www.ubuy.com.ps",
            "link": "https://www.ubuy.com.ps/en/product/B4955DJZ4-digital-camera-kids-camera-with-32gb-card-fhd-1080p-44mp-vlogging-camera-with-lcd-screen-16x-zoom-compact-portable-mini-rechargeable-camera-gifts-for",
            "googleUrl": "https://www.google.com/imgres?imgurl=https%3A%2F%2Fm.media-amazon.com%2Fimages%2FI%2F7174tl2r1gL._AC_SL1500_.jpg&tbnid=kCRlbzfYhwNEkM&imgrefurl=https%3A%2F%2Fwww.ubuy.com.ps%2Fen%2Fproduct%2FB4955DJZ4-digital-camera-kids-camera-with-32gb-card-fhd-1080p-44mp-vlogging-camera-with-lcd-screen-16x-zoom-compact-portable-mini-rechargeable-camera-gifts-for&docid=o8tvavYNaQZSqM&w=1500&h=1471",
            "position": 78
        },
        {
            "title": "NBD 4K Vlogging Camera 48MP for Beginners, Compact & Small ...",
            "imageUrl": "https://i5.walmartimages.com/seo/NBD-Vlogging-Camera-4K-48MP-Digital-Photography-Compact-YouTube-Flip-Screen-Autofocus-16X-Zoom-52mm-Wide-Angle-MacroLens-32GB-TF-Card_fe3c1fac-b9e8-475a-8434-317d17e08daa.9d7170b6666bba6b0a5d3d779d3f4717.jpeg?odnHeight=768&odnWidth=768&odnBg=FFFFFF",
            "imageWidth": 768,
            "imageHeight": 768,
            "thumbnailUrl": "https://encrypted-tbn0.gstatic.com/images?q=tbn:ANd9GcTASF2Y8EDdXe3B0QbH8osWllrxZHikaNMQtg&s",
            "thumbnailWidth": 225,
            "thumbnailHeight": 225,
            "source": "Walmart",
            "domain": "www.walmart.com",
            "link": "https://www.walmart.com/ip/NBD-Vlogging-Camera-4K-48MP-Digital-Photography-Compact-YouTube-Flip-Screen-Autofocus-16X-Zoom-52mm-Wide-Angle-MacroLens-32GB-TF-Card/1924358000",
            "googleUrl": "https://www.google.com/imgres?imgurl=https%3A%2F%2Fi5.walmartimages.com%2Fseo%2FNBD-Vlogging-Camera-4K-48MP-Digital-Photography-Compact-YouTube-Flip-Screen-Autofocus-16X-Zoom-52mm-Wide-Angle-MacroLens-32GB-TF-Card_fe3c1fac-b9e8-475a-8434-317d17e08daa.9d7170b6666bba6b0a5d3d779d3f4717.jpeg%3FodnHeight%3D768%26odnWidth%3D768%26odnBg%3DFFFFFF&tbnid=hb-s6M7N99URTM&imgrefurl=https%3A%2F%2Fwww.walmart.com%2Fip%2FNBD-Vlogging-Camera-4K-48MP-Digital-Photography-Compact-YouTube-Flip-Screen-Autofocus-16X-Zoom-52mm-Wide-Angle-MacroLens-32GB-TF-Card%2F1924358000&docid=htcEyDmJLDeWoM&w=768&h=768",
            "position": 79
        },
        {
            "title": "Digital Camera, FHD 1080P Kids Camera 44MP Point and Shoot Digital Cameras  with 32GB SD Card, 16X Zoom, Two Batteries, Lanyard, Compact Small Camera  ...",
            "imageUrl": "https://m.media-amazon.com/images/I/6121MRPGyJL.jpg",
            "imageWidth": 1200,
            "imageHeight": 1500,
            "thumbnailUrl": "https://encrypted-tbn0.gstatic.com/images?q=tbn:ANd9GcTmyEGoYs1qdDwmjwODepdne7stez9VkmrCxw&s",
            "thumbnailWidth": 201,
            "thumbnailHeight": 251,
            "source": "Amazon.com",
            "domain": "www.amazon.com",
            "link": "https://www.amazon.com/Digital-Cameras-Batteries-Students-Seniors-Black/dp/B0BRM31SQ1",
            "googleUrl": "https://www.google.com/imgres?imgurl=https%3A%2F%2Fm.media-amazon.com%2Fimages%2FI%2F6121MRPGyJL.jpg&tbnid=SbMQw2YSzobw5M&imgrefurl=https%3A%2F%2Fwww.amazon.com%2FDigital-Cameras-Batteries-Students-Seniors-Black%2Fdp%2FB0BRM31SQ1&docid=SvjMlRXb07ZBAM&w=1200&h=1500",
            "position": 80
        },
        {
            "title": "What to know before buying your first interchangeable lens ...",
            "imageUrl": "https://www.dpreview.com/files/p/articles/1328199596/Hero_Image.jpeg",
            "imageWidth": 2700,
            "imageHeight": 1800,
            "thumbnailUrl": "https://encrypted-tbn0.gstatic.com/images?q=tbn:ANd9GcROHPUWEIoH2etDd6pNskeTSF78xrLsb5sKYA&s",
            "thumbnailWidth": 275,
            "thumbnailHeight": 183,
            "source": "Digital Photography Review",
            "domain": "www.dpreview.com",
            "link": "https://www.dpreview.com/articles/1328199596/buying-guide-what-to-know-before-buying-your-first-interchangeable-lens-digital-camera",
            "googleUrl": "https://www.google.com/imgres?imgurl=https%3A%2F%2Fwww.dpreview.com%2Ffiles%2Fp%2Farticles%2F1328199596%2FHero_Image.jpeg&tbnid=x0hhUVZxxIU17M&imgrefurl=https%3A%2F%2Fwww.dpreview.com%2Farticles%2F1328199596%2Fbuying-guide-what-to-know-before-buying-your-first-interchangeable-lens-digital-camera&docid=GzS_r1gaxfQ4dM&w=2700&h=1800",
            "position": 81
        },
        {
            "title": "The Best DSLR for Beginners in 2024 | Reviews by Wirecutter",
            "imageUrl": "https://cdn.thewirecutter.com/wp-content/media/2020/10/beginnerdslr2020-2048px-9799.jpg?auto=webp&quality=75&crop=1.91:1&width=1200",
            "imageWidth": 1200,
            "imageHeight": 628,
            "thumbnailUrl": "https://encrypted-tbn0.gstatic.com/images?q=tbn:ANd9GcToVQZj_QhZpz4VU1n6FtQ2ztG6hEEk1Nwr-Q&s",
            "thumbnailWidth": 311,
            "thumbnailHeight": 162,
            "source": "The New York Times",
            "domain": "www.nytimes.com",
            "link": "https://www.nytimes.com/wirecutter/reviews/best-budget-dslr-camera/",
            "googleUrl": "https://www.google.com/imgres?imgurl=https%3A%2F%2Fcdn.thewirecutter.com%2Fwp-content%2Fmedia%2F2020%2F10%2Fbeginnerdslr2020-2048px-9799.jpg%3Fauto%3Dwebp%26quality%3D75%26crop%3D1.91%3A1%26width%3D1200&tbnid=hlPCYGUSydLp8M&imgrefurl=https%3A%2F%2Fwww.nytimes.com%2Fwirecutter%2Freviews%2Fbest-budget-dslr-camera%2F&docid=0SRLZclEnUbPQM&w=1200&h=628",
            "position": 82
        },
        {
            "title": "The best video camera 2024: top choices for filmmakers ...",
            "imageUrl": "https://cdn.mos.cms.futurecdn.net/2GwZo7VLVJxHTZsWWKBHdc.png",
            "imageWidth": 2000,
            "imageHeight": 1125,
            "thumbnailUrl": "https://encrypted-tbn0.gstatic.com/images?q=tbn:ANd9GcSNstyTrB1Tj61tf_TfjEGT5xvjcRvkBgqBBA&s",
            "thumbnailWidth": 300,
            "thumbnailHeight": 168,
            "source": "TechRadar",
            "domain": "www.techradar.com",
            "link": "https://www.techradar.com/best/best-video-camera",
            "googleUrl": "https://www.google.com/imgres?imgurl=https%3A%2F%2Fcdn.mos.cms.futurecdn.net%2F2GwZo7VLVJxHTZsWWKBHdc.png&tbnid=upP2ade6hB8eXM&imgrefurl=https%3A%2F%2Fwww.techradar.com%2Fbest%2Fbest-video-camera&docid=1cy64Gt0DI0J1M&w=2000&h=1125",
            "position": 83
        },
        {
            "title": "Sony RX100 VII Premium Compact Camera with 1.0-type stacked ...",
            "imageUrl": "https://d1ncau8tqf99kp.cloudfront.net/converted/74957_original_local_1200x1050_v3_converted.webp",
            "imageWidth": 1200,
            "imageHeight": 1050,
            "thumbnailUrl": "https://encrypted-tbn0.gstatic.com/images?q=tbn:ANd9GcRefPMQqVlA-VTxNduFgl3kuVrCpVsswpQjow&s",
            "thumbnailWidth": 240,
            "thumbnailHeight": 210,
            "source": "Sony Electronics",
            "domain": "electronics.sony.com",
            "link": "https://electronics.sony.com/imaging/compact-cameras/all-vlog-compact-cameras/p/dscrx100m7-b",
            "googleUrl": "https://www.google.com/imgres?imgurl=https%3A%2F%2Fd1ncau8tqf99kp.cloudfront.net%2Fconverted%2F74957_original_local_1200x1050_v3_converted.webp&tbnid=uSUF4e4j_zqs3M&imgrefurl=https%3A%2F%2Felectronics.sony.com%2Fimaging%2Fcompact-cameras%2Fall-vlog-compact-cameras%2Fp%2Fdscrx100m7-b&docid=h6Uw9_H3fos5LM&w=1200&h=1050",
            "position": 84
        },
        {
            "title": "Shop Cameras at Target",
            "imageUrl": "https://target.scene7.com/is/image/Target/GUEST_2dd7eefe-ddea-4f76-9a94-ba682ca42459",
            "imageWidth": 400,
            "imageHeight": 400,
            "thumbnailUrl": "https://encrypted-tbn0.gstatic.com/images?q=tbn:ANd9GcTXE2E2y44Umo-c0uUrVQ_VkHtJRia4Kcz15Q&s",
            "thumbnailWidth": 225,
            "thumbnailHeight": 225,
            "source": "Target",
            "domain": "www.target.com",
            "link": "https://www.target.com/c/cameras-camcorders-electronics/-/N-5xtez",
            "googleUrl": "https://www.google.com/imgres?imgurl=https%3A%2F%2Ftarget.scene7.com%2Fis%2Fimage%2FTarget%2FGUEST_2dd7eefe-ddea-4f76-9a94-ba682ca42459&tbnid=BD1BZuX_K7OKFM&imgrefurl=https%3A%2F%2Fwww.target.com%2Fc%2Fcameras-camcorders-electronics%2F-%2FN-5xtez&docid=IKejKxwLzlJQ1M&w=400&h=400",
            "position": 85
        },
        {
            "title": "Everyone is Buying Vintage Digicams Because of This... - YouTube",
            "imageUrl": "https://i.ytimg.com/vi/Vb4FMtpoSUw/sddefault.jpg",
            "imageWidth": 640,
            "imageHeight": 480,
            "thumbnailUrl": "https://encrypted-tbn0.gstatic.com/images?q=tbn:ANd9GcSSPOHAF9fTXLEXrcb78_hk-sgbcyzatssyJw&s",
            "thumbnailWidth": 259,
            "thumbnailHeight": 194,
            "source": "YouTube",
            "domain": "m.youtube.com",
            "link": "https://m.youtube.com/watch?v=Vb4FMtpoSUw",
            "googleUrl": "https://www.google.com/imgres?imgurl=https%3A%2F%2Fi.ytimg.com%2Fvi%2FVb4FMtpoSUw%2Fsddefault.jpg&tbnid=1qxULns2abqRDM&imgrefurl=https%3A%2F%2Fm.youtube.com%2Fwatch%3Fv%3DVb4FMtpoSUw&docid=Xm_BJjcaqm4DPM&w=640&h=480",
            "position": 86
        },
        {
            "title": "The best cameras for beginners in 2023 | PopPhoto | Popular ...",
            "imageUrl": "https://www.popphoto.com/uploads/2021/11/27/best-camera-for-beginners.jpg?auto=webp",
            "imageWidth": 2000,
            "imageHeight": 1300,
            "thumbnailUrl": "https://encrypted-tbn0.gstatic.com/images?q=tbn:ANd9GcQ_ZeDVNy_PwYRzaM4I9OghVZBKgWgz8DgTFw&s",
            "thumbnailWidth": 279,
            "thumbnailHeight": 181,
            "source": "Popular Photography",
            "domain": "www.popphoto.com",
            "link": "https://www.popphoto.com/reviews/best-camera-for-beginners/",
            "googleUrl": "https://www.google.com/imgres?imgurl=https%3A%2F%2Fwww.popphoto.com%2Fuploads%2F2021%2F11%2F27%2Fbest-camera-for-beginners.jpg%3Fauto%3Dwebp&tbnid=rxj9PtKQ-w16uM&imgrefurl=https%3A%2F%2Fwww.popphoto.com%2Freviews%2Fbest-camera-for-beginners%2F&docid=hAmXwGSLuPzOvM&w=2000&h=1300",
            "position": 87
        },
        {
            "title": "What is a DSLR camera for beginners | Adobe",
            "imageUrl": "https://www.adobe.com/creativecloud/photography/discover/media_16d66f4e9a84e10d6a1f58a32cd316e24e847e667.jpeg?width=750&format=jpeg&optimize=medium",
            "imageWidth": 720,
            "imageHeight": 350,
            "thumbnailUrl": "https://encrypted-tbn0.gstatic.com/images?q=tbn:ANd9GcSxZpnxaOIuSItxXIrajfycalj52IfDbfxL_Q&s",
            "thumbnailWidth": 322,
            "thumbnailHeight": 156,
            "source": "Adobe",
            "domain": "www.adobe.com",
            "link": "https://www.adobe.com/creativecloud/photography/discover/dslr-camera.html",
            "googleUrl": "https://www.google.com/imgres?imgurl=https%3A%2F%2Fwww.adobe.com%2Fcreativecloud%2Fphotography%2Fdiscover%2Fmedia_16d66f4e9a84e10d6a1f58a32cd316e24e847e667.jpeg%3Fwidth%3D750%26format%3Djpeg%26optimize%3Dmedium&tbnid=Bxkvuxcpxe77ZM&imgrefurl=https%3A%2F%2Fwww.adobe.com%2Fcreativecloud%2Fphotography%2Fdiscover%2Fdslr-camera.html&docid=GtrAXwbSbfSwoM&w=720&h=350",
            "position": 88
        },
        {
            "title": "Sony a6700 Mirrorless Camera (Alpha a6700 camera) B&H Photo",
            "imageUrl": "https://www.bhphotovideo.com/images/fb/sony_a6700_mirrorless_camera_1776281.jpg",
            "imageWidth": 2681,
            "imageHeight": 1408,
            "thumbnailUrl": "https://encrypted-tbn0.gstatic.com/images?q=tbn:ANd9GcT87Q3EtvkVR1nB1dpSKfCpQ05MyxvEf_KKZA&s",
            "thumbnailWidth": 310,
            "thumbnailHeight": 163,
            "source": "B&H",
            "domain": "www.bhphotovideo.com",
            "link": "https://www.bhphotovideo.com/c/product/1776281-REG/sony_a6700_mirrorless_camera.html",
            "googleUrl": "https://www.google.com/imgres?imgurl=https%3A%2F%2Fwww.bhphotovideo.com%2Fimages%2Ffb%2Fsony_a6700_mirrorless_camera_1776281.jpg&tbnid=ClPDo81oeNR9TM&imgrefurl=https%3A%2F%2Fwww.bhphotovideo.com%2Fc%2Fproduct%2F1776281-REG%2Fsony_a6700_mirrorless_camera.html&docid=J_LnclC-vj0vAM&w=2681&h=1408",
            "position": 89
        }
    ],
    "credits": 2
}