{
    "searchParameters": {
        "q": "Mobiles",
        "type": "images",
        "num": 100,
        "engine": "google"
    },
    "images": [
        {
            "title": "Mobiles - SFMOMA Museum Store",
            "imageUrl": "https://museumstore.sfmoma.org/cdn/shop/files/Small-Planets-Mobile.jpg?v=1724716301&width=1600",
            "imageWidth": 1000,
            "imageHeight": 1000,
            "thumbnailUrl": "https://encrypted-tbn0.gstatic.com/images?q=tbn:ANd9GcQTfJ9Bg3m_HflmyKl-HOPIaOoLOypF91dXXQ&s",
            "thumbnailWidth": 225,
            "thumbnailHeight": 225,
            "source": "SFMOMA Museum Store",
            "domain": "museumstore.sfmoma.org",
            "link": "https://museumstore.sfmoma.org/collections/mobiles",
            "googleUrl": "https://www.google.com/imgres?imgurl=https%3A%2F%2Fmuseumstore.sfmoma.org%2Fcdn%2Fshop%2Ffiles%2FSmall-Planets-Mobile.jpg%3Fv%3D1724716301%26width%3D1600&tbnid=fdYxUkYtdmt9wM&imgrefurl=https%3A%2F%2Fmuseumstore.sfmoma.org%2Fcollections%2Fmobiles&docid=8tQBUqSXmJ3OjM&w=1000&h=1000",
            "position": 21
        },
        {
            "title": "Mobiles, Stabiles and Sculptures by Alexander Calder | OEN",
            "imageUrl": "https://the189.com/wp-content/uploads/2012/03/Mobiles-Stabiles-and-Sculptures-by-Alexander-Calder-1.jpg",
            "imageWidth": 620,
            "imageHeight": 480,
            "thumbnailUrl": "https://encrypted-tbn0.gstatic.com/images?q=tbn:ANd9GcTG9FZ2bAElg9LRLWiLLiqNWprzFaaaPsOtdA&s",
            "thumbnailWidth": 255,
            "thumbnailHeight": 197,
            "source": "OEN",
            "domain": "the189.com",
            "link": "https://the189.com/sculpture/mobiles-stabiles-and-sculptures-by-alexander-calder/",
            "googleUrl": "https://www.google.com/imgres?imgurl=https%3A%2F%2Fthe189.com%2Fwp-content%2Fuploads%2F2012%2F03%2FMobiles-Stabiles-and-Sculptures-by-Alexander-Calder-1.jpg&tbnid=ud4xrpmzOH4ovM&imgrefurl=https%3A%2F%2Fthe189.com%2Fsculpture%2Fmobiles-stabiles-and-sculptures-by-alexander-calder%2F&docid=PA9V7YVhYLeNNM&w=620&h=480",
            "position": 22
        },
        {
            "title": "Samsung All New Mobiles Price List 2024",
            "imageUrl": "https://i.ytimg.com/vi/UR1FjflHdyA/hq720.jpg?sqp=-oaymwEhCK4FEIIDSFryq4qpAxMIARUAAAAAGAElAADIQj0AgKJD&rs=AOn4CLC-GfDopFYdeP84NHkmrsfshwLFlA",
            "imageWidth": 686,
            "imageHeight": 386,
            "thumbnailUrl": "https://encrypted-tbn0.gstatic.com/images?q=tbn:ANd9GcQedGac4h5YRe-oEOXWjEdvMXrt5T7lZSVtLA&s",
            "thumbnailWidth": 299,
            "thumbnailHeight": 168,
            "source": "YouTube",
            "domain": "m.youtube.com",
            "link": "https://m.youtube.com/watch?v=UR1FjflHdyA",
            "googleUrl": "https://www.google.com/imgres?imgurl=https%3A%2F%2Fi.ytimg.com%2Fvi%2FUR1FjflHdyA%2Fhq720.jpg%3Fsqp%3D-oaymwEhCK4FEIIDSFryq4qpAxMIARUAAAAAGAElAADIQj0AgKJD%26rs%3DAOn4CLC-GfDopFYdeP84NHkmrsfshwLFlA&tbnid=hoyaidvXEIfWVM&imgrefurl=https%3A%2F%2Fm.youtube.com%2Fwatch%3Fv%3DUR1FjflHdyA&docid=NMarCjmo1vFxlM&w=686&h=386",
            "position": 23
        },
        {
            "title": "Mobiles",
            "imageUrl": "https://lightart.imgix.net/marketing/LIGHTART-ACOUTIC-MOBILE-1ALT_BLUE-web.jpg?auto=compress%2Cformat&crop=focalpoint&fit=crop&fp-x=0.5&fp-y=0.5&h=483&q=80&w=724&s=855d560f8543cc0c6f3c8201095e451c",
            "imageWidth": 724,
            "imageHeight": 483,
            "thumbnailUrl": "https://encrypted-tbn0.gstatic.com/images?q=tbn:ANd9GcS0V9PmngW2LvHCL5DbVyP-TjDoAockkvviTg&s",
            "thumbnailWidth": 275,
            "thumbnailHeight": 183,
            "source": "LightArt",
            "domain": "lightart.com",
            "link": "https://lightart.com/products/types/mobiles",
            "googleUrl": "https://www.google.com/imgres?imgurl=https%3A%2F%2Flightart.imgix.net%2Fmarketing%2FLIGHTART-ACOUTIC-MOBILE-1ALT_BLUE-web.jpg%3Fauto%3Dcompress%252Cformat%26crop%3Dfocalpoint%26fit%3Dcrop%26fp-x%3D0.5%26fp-y%3D0.5%26h%3D483%26q%3D80%26w%3D724%26s%3D855d560f8543cc0c6f3c8201095e451c&tbnid=wS42Bpf94IaBUM&imgrefurl=https%3A%2F%2Flightart.com%2Fproducts%2Ftypes%2Fmobiles&docid=De5N97r58iYJxM&w=724&h=483",
            "position": 24
        },
        {
            "title": "mobiles made in germany, mobiles made in germany Suppliers ...",
            "imageUrl": "https://s.alicdn.com/@sc04/kf/Hdb380b9ffc6044a4bddd38b559603853k.jpg_300x300.jpg",
            "imageWidth": 300,
            "imageHeight": 300,
            "thumbnailUrl": "https://encrypted-tbn0.gstatic.com/images?q=tbn:ANd9GcT3LDnI1M6WNgSiDZ2lPVcQdKo4k4FrCx2JAg&s",
            "thumbnailWidth": 225,
            "thumbnailHeight": 225,
            "source": "Alibaba.com",
            "domain": "www.alibaba.com",
            "link": "https://www.alibaba.com/showroom/mobiles-made-in-germany.html",
            "googleUrl": "https://www.google.com/imgres?imgurl=https%3A%2F%2Fs.alicdn.com%2F%40sc04%2Fkf%2FHdb380b9ffc6044a4bddd38b559603853k.jpg_300x300.jpg&tbnid=aSgl6Ub1hUeOcM&imgrefurl=https%3A%2F%2Fwww.alibaba.com%2Fshowroom%2Fmobiles-made-in-germany.html&docid=_90ld-ZgmW6kpM&w=300&h=300",
            "position": 25
        },
        {
            "title": "All Nokia Mobiles Evolution From First to Last 1982 - 2020",
            "imageUrl": "https://i.ytimg.com/vi/V0jQJqVmSVk/hq720.jpg?sqp=-oaymwEhCK4FEIIDSFryq4qpAxMIARUAAAAAGAElAADIQj0AgKJD&rs=AOn4CLAtQbyVhZikZZvfFyZ9cA_EEv37lQ",
            "imageWidth": 686,
            "imageHeight": 386,
            "thumbnailUrl": "https://encrypted-tbn0.gstatic.com/images?q=tbn:ANd9GcS-1Kd_BqRwsv1V5-RYyrwq33ST22sNkS4MMQ&s",
            "thumbnailWidth": 299,
            "thumbnailHeight": 168,
            "source": "YouTube",
            "domain": "m.youtube.com",
            "link": "https://m.youtube.com/watch?v=V0jQJqVmSVk",
            "googleUrl": "https://www.google.com/imgres?imgurl=https%3A%2F%2Fi.ytimg.com%2Fvi%2FV0jQJqVmSVk%2Fhq720.jpg%3Fsqp%3D-oaymwEhCK4FEIIDSFryq4qpAxMIARUAAAAAGAElAADIQj0AgKJD%26rs%3DAOn4CLAtQbyVhZikZZvfFyZ9cA_EEv37lQ&tbnid=NVBZ9Tw2F-VGdM&imgrefurl=https%3A%2F%2Fm.youtube.com%2Fwatch%3Fv%3DV0jQJqVmSVk&docid=YYaeZJyiteHXoM&w=686&h=386",
            "position": 26
        },
        {
            "title": "Top 10 Mobile Accessories Manufacturers in China | MatchSourcing",
            "imageUrl": "https://www.matchsourcing.com/wp-content/uploads/2021/12/2.jpg",
            "imageWidth": 564,
            "imageHeight": 376,
            "thumbnailUrl": "https://encrypted-tbn0.gstatic.com/images?q=tbn:ANd9GcR0RkrHVpUuHbneYwCAb5P5jdw7GsrVALgAbQ&s",
            "thumbnailWidth": 275,
            "thumbnailHeight": 183,
            "source": "MatchSourcing",
            "domain": "www.matchsourcing.com",
            "link": "https://www.matchsourcing.com/mobile-accessories-manufacturers-in-china",
            "googleUrl": "https://www.google.com/imgres?imgurl=https%3A%2F%2Fwww.matchsourcing.com%2Fwp-content%2Fuploads%2F2021%2F12%2F2.jpg&tbnid=gjSOnElNaAws6M&imgrefurl=https%3A%2F%2Fwww.matchsourcing.com%2Fmobile-accessories-manufacturers-in-china&docid=6tFx6Q_jnwUK3M&w=564&h=376",
            "position": 27
        },
        {
            "title": "9 Ways Your Mobile Devices Can Help Grow Your Business ...",
            "imageUrl": "https://res.cloudinary.com/zenbusiness/q_auto,w_1200,h_800,c_lfill/v1/shared-assets/s2/raster/people-using-smart-phones.jpg",
            "imageWidth": 1200,
            "imageHeight": 800,
            "thumbnailUrl": "https://encrypted-tbn0.gstatic.com/images?q=tbn:ANd9GcT3vg7L8NlPQtY5mEFeZdDMvlcb_fhcE81u6A&s",
            "thumbnailWidth": 275,
            "thumbnailHeight": 183,
            "source": "ZenBusiness",
            "domain": "www.zenbusiness.com",
            "link": "https://www.zenbusiness.com/blog/9-ways-mobile-devices-can-help-grow-business/",
            "googleUrl": "https://www.google.com/imgres?imgurl=https%3A%2F%2Fres.cloudinary.com%2Fzenbusiness%2Fq_auto%2Cw_1200%2Ch_800%2Cc_lfill%2Fv1%2Fshared-assets%2Fs2%2Fraster%2Fpeople-using-smart-phones.jpg&tbnid=lFyvkdzmAeznxM&imgrefurl=https%3A%2F%2Fwww.zenbusiness.com%2Fblog%2F9-ways-mobile-devices-can-help-grow-business%2F&docid=DFx63HVVC_AJJM&w=1200&h=800",
            "position": 28
        },
        {
            "title": "full hd screen mobiles, full hd screen mobiles Suppliers and ...",
            "imageUrl": "https://s.alicdn.com/@sc04/kf/H047623be87b443eea4d0a6806a173d89s.jpg_300x300.jpg",
            "imageWidth": 300,
            "imageHeight": 300,
            "thumbnailUrl": "https://encrypted-tbn0.gstatic.com/images?q=tbn:ANd9GcS9gf7rIO1Q5cLfQoRjpA9nJSJ0U0xLd5d3DQ&s",
            "thumbnailWidth": 225,
            "thumbnailHeight": 225,
            "source": "Alibaba",
            "domain": "www.alibaba.com",
            "link": "https://www.alibaba.com/showroom/full-hd-screen-mobiles.html",
            "googleUrl": "https://www.google.com/imgres?imgurl=https%3A%2F%2Fs.alicdn.com%2F%40sc04%2Fkf%2FH047623be87b443eea4d0a6806a173d89s.jpg_300x300.jpg&tbnid=lSJ1WngbgH0ZHM&imgrefurl=https%3A%2F%2Fwww.alibaba.com%2Fshowroom%2Ffull-hd-screen-mobiles.html&docid=D6ARn6O_SdH1UM&w=300&h=300",
            "position": 29
        },
        {
            "title": "The History of Mobile Apps - Inventionland",
            "imageUrl": "https://inventionland.com/wp/wp-content/uploads/2018/12/inventionland-flying-apps-1.jpg",
            "imageWidth": 1000,
            "imageHeight": 667,
            "thumbnailUrl": "https://encrypted-tbn0.gstatic.com/images?q=tbn:ANd9GcQPzB3bS2psJF1lqzTj3Pg2HTuGIsAtRESANg&s",
            "thumbnailWidth": 275,
            "thumbnailHeight": 183,
            "source": "Inventionland",
            "domain": "inventionland.com",
            "link": "https://inventionland.com/blog/the-history-of-mobile-apps/",
            "googleUrl": "https://www.google.com/imgres?imgurl=https%3A%2F%2Finventionland.com%2Fwp%2Fwp-content%2Fuploads%2F2018%2F12%2Finventionland-flying-apps-1.jpg&tbnid=bRTZlxT7isYrvM&imgrefurl=https%3A%2F%2Finventionland.com%2Fblog%2Fthe-history-of-mobile-apps%2F&docid=oFUKfs_DD55rdM&w=1000&h=667",
            "position": 30
        },
        {
            "title": "Explore our Best Samsung Galaxy Smartphones | Samsung US",
            "imageUrl": "https://images.samsung.com/is/image/samsung/assets/us/2407/smartphones/smartphones-updates-scomb6q6-430/07012024/MobilePCD_FT03_fullbleed-Q6-B6-mo.jpg?$720_N_JPG$",
            "imageWidth": 720,
            "imageHeight": 1076,
            "thumbnailUrl": "https://encrypted-tbn0.gstatic.com/images?q=tbn:ANd9GcQ0LMvvycOj4TnSoe7ya9VlOHeJL9zhIbW0wA&s",
            "thumbnailWidth": 184,
            "thumbnailHeight": 275,
            "source": "Samsung",
            "domain": "www.samsung.com",
            "link": "https://www.samsung.com/us/smartphones/",
            "googleUrl": "https://www.google.com/imgres?imgurl=https%3A%2F%2Fimages.samsung.com%2Fis%2Fimage%2Fsamsung%2Fassets%2Fus%2F2407%2Fsmartphones%2Fsmartphones-updates-scomb6q6-430%2F07012024%2FMobilePCD_FT03_fullbleed-Q6-B6-mo.jpg%3F%24720_N_JPG%24&tbnid=RbGjhktd1Ud5LM&imgrefurl=https%3A%2F%2Fwww.samsung.com%2Fus%2Fsmartphones%2F&docid=tOZVgiOT4xkg7M&w=720&h=1076",
            "position": 31
        },
        {
            "title": "best mobile phones: 10 Best Mobile Phones from Samsung ...",
            "imageUrl": "https://img.etimg.com/photo/msid-101297861,imgsize-116722/RealmeNarzo50Pro5G.jpg",
            "imageWidth": 1500,
            "imageHeight": 1500,
            "thumbnailUrl": "https://encrypted-tbn0.gstatic.com/images?q=tbn:ANd9GcRRncCQaRPIMz63XQLZlF6lzcZhhYlDom5WRA&s",
            "thumbnailWidth": 225,
            "thumbnailHeight": 225,
            "source": "The Economic Times",
            "domain": "m.economictimes.com",
            "link": "https://m.economictimes.com/top-trending-products/mobile-phones/best-mobile-phones-from-samsung-apple-google-and-others/articleshow/101296609.cms",
            "googleUrl": "https://www.google.com/imgres?imgurl=https%3A%2F%2Fimg.etimg.com%2Fphoto%2Fmsid-101297861%2Cimgsize-116722%2FRealmeNarzo50Pro5G.jpg&tbnid=OUbWyKVv4mmpiM&imgrefurl=https%3A%2F%2Fm.economictimes.com%2Ftop-trending-products%2Fmobile-phones%2Fbest-mobile-phones-from-samsung-apple-google-and-others%2Farticleshow%2F101296609.cms&docid=3CssAMv3-2fBuM&w=1500&h=1500",
            "position": 32
        },
        {
            "title": "Rugged biometric handhelds",
            "imageUrl": "https://www.laxton.com/wp-content/uploads/Mobile-Header.webp",
            "imageWidth": 1920,
            "imageHeight": 800,
            "thumbnailUrl": "https://encrypted-tbn0.gstatic.com/images?q=tbn:ANd9GcRjkDlEBG-Lk_m44hDz0j9bJeraGyvZBM6MPw&s",
            "thumbnailWidth": 348,
            "thumbnailHeight": 145,
            "source": "Laxton",
            "domain": "www.laxton.com",
            "link": "https://www.laxton.com/mobiles/",
            "googleUrl": "https://www.google.com/imgres?imgurl=https%3A%2F%2Fwww.laxton.com%2Fwp-content%2Fuploads%2FMobile-Header.webp&tbnid=jYkg-vHuoG_98M&imgrefurl=https%3A%2F%2Fwww.laxton.com%2Fmobiles%2F&docid=OeNFzl-CtvyUUM&w=1920&h=800",
            "position": 33
        },
        {
            "title": "The Top Three Stores to buy Second-Hand Phones - I Need A ...",
            "imageUrl": "https://www.ineedamobile.com/wp-content/uploads/2018/04/Refurbished-Mobile-Phones.png",
            "imageWidth": 1032,
            "imageHeight": 577,
            "thumbnailUrl": "https://encrypted-tbn0.gstatic.com/images?q=tbn:ANd9GcReaPjaQEJf5G6AnzS1se-oeGaV58lSU8a3Jg&s",
            "thumbnailWidth": 300,
            "thumbnailHeight": 168,
            "source": "I Need A Mobile",
            "domain": "www.ineedamobile.com",
            "link": "https://www.ineedamobile.com/the-top-three-stores-to-buy-second-hand-phones/",
            "googleUrl": "https://www.google.com/imgres?imgurl=https%3A%2F%2Fwww.ineedamobile.com%2Fwp-content%2Fuploads%2F2018%2F04%2FRefurbished-Mobile-Phones.png&tbnid=gCUdXFkWK8buqM&imgrefurl=https%3A%2F%2Fwww.ineedamobile.com%2Fthe-top-three-stores-to-buy-second-hand-phones%2F&docid=Zlxu8YflOlO0GM&w=1032&h=577",
            "position": 34
        },
        {
            "title": "The best cheap phones 2024: top budget mobiles around ...",
            "imageUrl": "https://cdn.mos.cms.futurecdn.net/PpMiDTNnVjEQznLNfdreca-1200-80.jpg",
            "imageWidth": 1200,
            "imageHeight": 675,
            "thumbnailUrl": "https://encrypted-tbn0.gstatic.com/images?q=tbn:ANd9GcSTmz5kU4_VvnAcAXfsosf-FaYe4zVMG_ATVg&s",
            "thumbnailWidth": 300,
            "thumbnailHeight": 168,
            "source": "TechRadar",
            "domain": "www.techradar.com",
            "link": "https://www.techradar.com/uk/best/best-cheap-phones",
            "googleUrl": "https://www.google.com/imgres?imgurl=https%3A%2F%2Fcdn.mos.cms.futurecdn.net%2FPpMiDTNnVjEQznLNfdreca-1200-80.jpg&tbnid=yTst0w80ZX-PoM&imgrefurl=https%3A%2F%2Fwww.techradar.com%2Fuk%2Fbest%2Fbest-cheap-phones&docid=5TkfHclEZtlUuM&w=1200&h=675",
            "position": 35
        },
        {
            "title": "Business Mobiles | Radius Connect Solutions",
            "imageUrl": "https://www.radiusconnectsolutions.com/app/uploads/2021/10/Mobiles1.png",
            "imageWidth": 773,
            "imageHeight": 739,
            "thumbnailUrl": "https://encrypted-tbn0.gstatic.com/images?q=tbn:ANd9GcT1P8YNcZ7hTa7DnsPENkFJFF6rOURLrhlkUw&s",
            "thumbnailWidth": 230,
            "thumbnailHeight": 219,
            "source": "Radius Connect",
            "domain": "www.radiusconnectsolutions.com",
            "link": "https://www.radiusconnectsolutions.com/business-mobile/",
            "googleUrl": "https://www.google.com/imgres?imgurl=https%3A%2F%2Fwww.radiusconnectsolutions.com%2Fapp%2Fuploads%2F2021%2F10%2FMobiles1.png&tbnid=9Q2xzFEIY853BM&imgrefurl=https%3A%2F%2Fwww.radiusconnectsolutions.com%2Fbusiness-mobile%2F&docid=QWRriB4NSYp8aM&w=773&h=739",
            "position": 36
        },
        {
            "title": "Barrières Mobiles | éric la casa",
            "imageUrl": "https://f4.bcbits.com/img/a0718029225_65",
            "imageWidth": 700,
            "imageHeight": 700,
            "thumbnailUrl": "https://encrypted-tbn0.gstatic.com/images?q=tbn:ANd9GcRr0LqKAw94pZCB5MA3q7FYTl1RiMJ0CsTBVQ&s",
            "thumbnailWidth": 225,
            "thumbnailHeight": 225,
            "source": "Music | éric la casa - Bandcamp",
            "domain": "swarming.bandcamp.com",
            "link": "https://swarming.bandcamp.com/album/barri-res-mobiles",
            "googleUrl": "https://www.google.com/imgres?imgurl=https%3A%2F%2Ff4.bcbits.com%2Fimg%2Fa0718029225_65&tbnid=aBMUnYHfTL-w7M&imgrefurl=https%3A%2F%2Fswarming.bandcamp.com%2Falbum%2Fbarri-res-mobiles&docid=Ozv1mb_54r2S5M&w=700&h=700",
            "position": 37
        },
        {
            "title": "What is the refurbishing process in mobiles? - Budli.in Blog",
            "imageUrl": "https://budli.in/blog/wp-content/uploads/2021/06/5-what-is-refurbishing-process-in-smartphones.jpg",
            "imageWidth": 500,
            "imageHeight": 409,
            "thumbnailUrl": "https://encrypted-tbn0.gstatic.com/images?q=tbn:ANd9GcQdFHBnB6g9jfdHV06eLpwcNdMOHV-yn5_qnw&s",
            "thumbnailWidth": 248,
            "thumbnailHeight": 203,
            "source": "Budli.in",
            "domain": "budli.in",
            "link": "https://budli.in/blog/what-is-the-refurbishing-process-in-mobiles/",
            "googleUrl": "https://www.google.com/imgres?imgurl=https%3A%2F%2Fbudli.in%2Fblog%2Fwp-content%2Fuploads%2F2021%2F06%2F5-what-is-refurbishing-process-in-smartphones.jpg&tbnid=a050J3Ex7jiBYM&imgrefurl=https%3A%2F%2Fbudli.in%2Fblog%2Fwhat-is-the-refurbishing-process-in-mobiles%2F&docid=Pakfwyj_SWBC9M&w=500&h=409",
            "position": 38
        },
        {
            "title": "Mobiles Pictures | Download Free Images on Unsplash",
            "imageUrl": "https://plus.unsplash.com/premium_photo-1661658740167-45b56833412b?fm=jpg&q=60&w=3000&ixlib=rb-4.0.3&ixid=M3wxMjA3fDB8MHxzZWFyY2h8MXx8bW9iaWxlc3xlbnwwfHwwfHx8MA%3D%3D",
            "imageWidth": 3000,
            "imageHeight": 2000,
            "thumbnailUrl": "https://encrypted-tbn0.gstatic.com/images?q=tbn:ANd9GcS2iUhXFmqa_TjJiJL0zaWSSESpi7hYo4S_GQ&s",
            "thumbnailWidth": 275,
            "thumbnailHeight": 183,
            "source": "Unsplash",
            "domain": "unsplash.com",
            "link": "https://unsplash.com/s/photos/mobiles",
            "googleUrl": "https://www.google.com/imgres?imgurl=https%3A%2F%2Fplus.unsplash.com%2Fpremium_photo-1661658740167-45b56833412b%3Ffm%3Djpg%26q%3D60%26w%3D3000%26ixlib%3Drb-4.0.3%26ixid%3DM3wxMjA3fDB8MHxzZWFyY2h8MXx8bW9iaWxlc3xlbnwwfHwwfHx8MA%253D%253D&tbnid=v_23hgmxxzzH9M&imgrefurl=https%3A%2F%2Funsplash.com%2Fs%2Fphotos%2Fmobiles&docid=jigJmib6dbbV_M&w=3000&h=2000",
            "position": 39
        },
        {
            "title": "3 Ways to Make Mobiles - wikiHow",
            "imageUrl": "https://www.wikihow.com/images/thumb/f/f9/Make-Mobiles-Step-23.jpg/aid1378635-v4-1200px-Make-Mobiles-Step-23.jpg",
            "imageWidth": 1200,
            "imageHeight": 800,
            "thumbnailUrl": "https://encrypted-tbn0.gstatic.com/images?q=tbn:ANd9GcREVTRWdBj5f2iX-ol3RaZkX6zFPf5wEegWGw&s",
            "thumbnailWidth": 275,
            "thumbnailHeight": 183,
            "source": "wikiHow",
            "domain": "www.wikihow.com",
            "link": "https://www.wikihow.com/Make-Mobiles",
            "googleUrl": "https://www.google.com/imgres?imgurl=https%3A%2F%2Fwww.wikihow.com%2Fimages%2Fthumb%2Ff%2Ff9%2FMake-Mobiles-Step-23.jpg%2Faid1378635-v4-1200px-Make-Mobiles-Step-23.jpg&tbnid=eks3LDdMuf7C1M&imgrefurl=https%3A%2F%2Fwww.wikihow.com%2FMake-Mobiles&docid=D7UX8cgiz3geHM&w=1200&h=800",
            "position": 40
        },
        {
            "title": "Cell Phones & Smartphones : Target",
            "imageUrl": "https://target.scene7.com/is/image/Target/GUEST_b12134c9-b9af-4908-914b-7bff9be24d9b?qlt=65&fmt=pjpeg&hei=350&wid=350",
            "imageWidth": 350,
            "imageHeight": 350,
            "thumbnailUrl": "https://encrypted-tbn0.gstatic.com/images?q=tbn:ANd9GcR_LY4Yb8lf0CCer8P9Msknu6TihH-_GJmD5A&s",
            "thumbnailWidth": 225,
            "thumbnailHeight": 225,
            "source": "Target",
            "domain": "www.target.com",
            "link": "https://www.target.com/c/cell-phones-electronics/-/N-5xte8",
            "googleUrl": "https://www.google.com/imgres?imgurl=https%3A%2F%2Ftarget.scene7.com%2Fis%2Fimage%2FTarget%2FGUEST_b12134c9-b9af-4908-914b-7bff9be24d9b%3Fqlt%3D65%26fmt%3Dpjpeg%26hei%3D350%26wid%3D350&tbnid=ynQFeh9YSRCYRM&imgrefurl=https%3A%2F%2Fwww.target.com%2Fc%2Fcell-phones-electronics%2F-%2FN-5xte8&docid=NKpMV1xAKOgNVM&w=350&h=350",
            "position": 41
        },
        {
            "title": "Say Hello to the cutest Baby Mobiles — Rockabye Mommy",
            "imageUrl": "https://images.squarespace-cdn.com/content/v1/5cdb01fd16b6405b8efcdade/a0fcb580-523b-4f3e-a68a-c61cfc4ea66b/cutest-baby-mobiles-rockabye-mommy.jpg",
            "imageWidth": 1170,
            "imageHeight": 1293,
            "thumbnailUrl": "https://encrypted-tbn0.gstatic.com/images?q=tbn:ANd9GcSXwu57uUZ1PdxR_dfYDX3BBpfV5Er92ZG0PA&s",
            "thumbnailWidth": 214,
            "thumbnailHeight": 236,
            "source": "Rockabye Mommy",
            "domain": "www.rockabyemommy.com",
            "link": "https://www.rockabyemommy.com/posts/say-hello-to-the-cutest-baby-mobiles",
            "googleUrl": "https://www.google.com/imgres?imgurl=https%3A%2F%2Fimages.squarespace-cdn.com%2Fcontent%2Fv1%2F5cdb01fd16b6405b8efcdade%2Fa0fcb580-523b-4f3e-a68a-c61cfc4ea66b%2Fcutest-baby-mobiles-rockabye-mommy.jpg&tbnid=crtIjdnLYQKD_M&imgrefurl=https%3A%2F%2Fwww.rockabyemommy.com%2Fposts%2Fsay-hello-to-the-cutest-baby-mobiles&docid=kS6snVCYovTO3M&w=1170&h=1293",
            "position": 42
        },
        {
            "title": "Mobiles before Calder - Who Invented Mobiles - A History",
            "imageUrl": "https://www.marcomahler.com/himmeli-mobile.JPG",
            "imageWidth": 240,
            "imageHeight": 325,
            "thumbnailUrl": "https://encrypted-tbn0.gstatic.com/images?q=tbn:ANd9GcRwf-LCFeOkgxcUg7W2kXeICiP4_mc3AUsorw&s",
            "thumbnailWidth": 193,
            "thumbnailHeight": 261,
            "source": "Marco Mahler",
            "domain": "www.marcomahler.com",
            "link": "https://www.marcomahler.com/mobiles-before-calder-who-invented-mobiles-history/",
            "googleUrl": "https://www.google.com/imgres?imgurl=https%3A%2F%2Fwww.marcomahler.com%2Fhimmeli-mobile.JPG&tbnid=qbUinqZI7IvA6M&imgrefurl=https%3A%2F%2Fwww.marcomahler.com%2Fmobiles-before-calder-who-invented-mobiles-history%2F&docid=aQTXtxRCmJwzbM&w=240&h=325",
            "creator": "MM",
            "position": 43
        },
        {
            "title": "Top 10 Smartphone Brands in India With Key Features, Market ...",
            "imageUrl": "https://www.godigit.com/content/dam/godigit/directportal/en/realme-mobiles.jpg",
            "imageWidth": 291,
            "imageHeight": 343,
            "thumbnailUrl": "https://encrypted-tbn0.gstatic.com/images?q=tbn:ANd9GcQVIfVYybA-k27LPDXArr9hTJNObWhfekuzCA&s",
            "thumbnailWidth": 207,
            "thumbnailHeight": 244,
            "source": "Digit Insurance",
            "domain": "www.godigit.com",
            "link": "https://www.godigit.com/mobile-insurance/find/top-smartphones-brands-in-india",
            "googleUrl": "https://www.google.com/imgres?imgurl=https%3A%2F%2Fwww.godigit.com%2Fcontent%2Fdam%2Fgodigit%2Fdirectportal%2Fen%2Frealme-mobiles.jpg&tbnid=GDcqhWCBP_BswM&imgrefurl=https%3A%2F%2Fwww.godigit.com%2Fmobile-insurance%2Ffind%2Ftop-smartphones-brands-in-india&docid=GaL8Xyw-c0-7jM&w=291&h=343",
            "position": 44
        },
        {
            "title": "Cell Phones: Smartphones and Mobile Phones - Best Buy",
            "imageUrl": "https://pisces.bbystatic.com/image2/BestBuy_US/images/products/6570/6570299_sd.jpg;maxHeight=262;maxWidth=386?format=webp",
            "imageWidth": 260,
            "imageHeight": 262,
            "thumbnailUrl": "https://encrypted-tbn0.gstatic.com/images?q=tbn:ANd9GcRPAaLqPDD8X3sNs8IoY2xykyHUdbNCpQCPbQ&s",
            "thumbnailWidth": 224,
            "thumbnailHeight": 225,
            "source": "Best Buy",
            "domain": "www.bestbuy.com",
            "link": "https://www.bestbuy.com/site/electronics/mobile-cell-phones/abcat0800000.c?id=abcat0800000",
            "googleUrl": "https://www.google.com/imgres?imgurl=https%3A%2F%2Fpisces.bbystatic.com%2Fimage2%2FBestBuy_US%2Fimages%2Fproducts%2F6570%2F6570299_sd.jpg%3BmaxHeight%3D262%3BmaxWidth%3D386%3Fformat%3Dwebp&tbnid=n3VDTELw-O9nJM&imgrefurl=https%3A%2F%2Fwww.bestbuy.com%2Fsite%2Felectronics%2Fmobile-cell-phones%2Fabcat0800000.c%3Fid%3Dabcat0800000&docid=4NpNLEax11k9HM&w=260&h=262",
            "position": 45
        },
        {
            "title": "Mobiles | Baby Mobiles for Cribs – Walmart.com",
            "imageUrl": "https://i5.walmartimages.com/seo/Baby-Crib-Mobile-Relaxing-Music-Ceiling-Light-Projector-Stars-Hanging-Toys-Animals-Musical-Timer-Nursery-Toys-Babies-Ages-0-Older_641f2cb0-f8fc-4194-8f3c-c53480d0e1d2.d44ddc0187b752b7470cacd45a967b2c.png?odnHeight=320&odnWidth=320&odnBg=FFFFFF",
            "imageWidth": 320,
            "imageHeight": 320,
            "thumbnailUrl": "https://encrypted-tbn0.gstatic.com/images?q=tbn:ANd9GcRpgT5Qp4_aOppLEoRivUR4S3P40e48UdTWiw&s",
            "thumbnailWidth": 225,
            "thumbnailHeight": 225,
            "source": "Walmart",
            "domain": "www.walmart.com",
            "link": "https://www.walmart.com/browse/baby/crib-mobiles/5427_414099_8124526_133177",
            "googleUrl": "https://www.google.com/imgres?imgurl=https%3A%2F%2Fi5.walmartimages.com%2Fseo%2FBaby-Crib-Mobile-Relaxing-Music-Ceiling-Light-Projector-Stars-Hanging-Toys-Animals-Musical-Timer-Nursery-Toys-Babies-Ages-0-Older_641f2cb0-f8fc-4194-8f3c-c53480d0e1d2.d44ddc0187b752b7470cacd45a967b2c.png%3FodnHeight%3D320%26odnWidth%3D320%26odnBg%3DFFFFFF&tbnid=pM4-dDwcpMMDZM&imgrefurl=https%3A%2F%2Fwww.walmart.com%2Fbrowse%2Fbaby%2Fcrib-mobiles%2F5427_414099_8124526_133177&docid=9o0mx7Ds0ZewMM&w=320&h=320",
            "position": 46
        },
        {
            "title": "mobiles, \"hanging mobiles\", hotchkiss, tri-lumen, calder,",
            "imageUrl": "https://s.turbifycdn.com/aah/artmobiles/tri-lumen-tropical-hanging-mobile-50.jpg",
            "imageWidth": 1200,
            "imageHeight": 903,
            "thumbnailUrl": "https://encrypted-tbn0.gstatic.com/images?q=tbn:ANd9GcQQkga4_FV1bWPY1JhScrdP4XAxug9zwDDXvg&s",
            "thumbnailWidth": 259,
            "thumbnailHeight": 195,
            "source": "Hotchkiss Mobiles",
            "domain": "www.artmobiles.com",
            "link": "https://www.artmobiles.com/triltrop.html",
            "googleUrl": "https://www.google.com/imgres?imgurl=https%3A%2F%2Fs.turbifycdn.com%2Faah%2Fartmobiles%2Ftri-lumen-tropical-hanging-mobile-50.jpg&tbnid=gU0SNkh4X5CFkM&imgrefurl=https%3A%2F%2Fwww.artmobiles.com%2Ftriltrop.html&docid=XTXYgrlWst6PPM&w=1200&h=903",
            "position": 47
        },
        {
            "title": "Heroes of Goo Jit Zu Goo Mobiles Smash Thrash. Stretch 'em! Smash 'em!  Twist 'em! Fix Them and Start Again! Present for 4 Year Old Girls, Boys and  Goo ...",
            "imageUrl": "https://m.media-amazon.com/images/I/81Q8RKqfWAL._AC_UF894,1000_QL80_.jpg",
            "imageWidth": 807,
            "imageHeight": 1000,
            "thumbnailUrl": "https://encrypted-tbn0.gstatic.com/images?q=tbn:ANd9GcQmxlvp4YtUuwoPz1Su14JrUYYQXGjgtuTioA&s",
            "thumbnailWidth": 202,
            "thumbnailHeight": 250,
            "source": "Amazon.com",
            "domain": "www.amazon.com",
            "link": "https://www.amazon.com/Heroes-Goo-Jit-Zu-Mobiles/dp/B0CBC33S3Q",
            "googleUrl": "https://www.google.com/imgres?imgurl=https%3A%2F%2Fm.media-amazon.com%2Fimages%2FI%2F81Q8RKqfWAL._AC_UF894%2C1000_QL80_.jpg&tbnid=ER1J_871otY1wM&imgrefurl=https%3A%2F%2Fwww.amazon.com%2FHeroes-Goo-Jit-Zu-Mobiles%2Fdp%2FB0CBC33S3Q&docid=ex5yEqJfQeHrsM&w=807&h=1000",
            "position": 48
        },
        {
            "title": "Flensted Mobiles - Cherry Dreams Mobile | Connox",
            "imageUrl": "https://cdn.connox.com/m/100107/571939/media/Flensted-Mobiles/2022/Flensted-Mobiles-Cherry-Dreams-Mobile-Messing-Holz-mehrfarbig.jpg",
            "imageWidth": 720,
            "imageHeight": 720,
            "thumbnailUrl": "https://encrypted-tbn0.gstatic.com/images?q=tbn:ANd9GcT-hMqpVe1yOFrCPEPFnh7th0m2tQ6wumc76Q&s",
            "thumbnailWidth": 225,
            "thumbnailHeight": 225,
            "source": "Connox",
            "domain": "www.connox.com",
            "link": "https://www.connox.com/categories/accessories/home-decor/children-design-mobiles/flensted-mobiles-cherry-dreams-mobile.html",
            "googleUrl": "https://www.google.com/imgres?imgurl=https%3A%2F%2Fcdn.connox.com%2Fm%2F100107%2F571939%2Fmedia%2FFlensted-Mobiles%2F2022%2FFlensted-Mobiles-Cherry-Dreams-Mobile-Messing-Holz-mehrfarbig.jpg&tbnid=OVQua8s7I-P-5M&imgrefurl=https%3A%2F%2Fwww.connox.com%2Fcategories%2Faccessories%2Fhome-decor%2Fchildren-design-mobiles%2Fflensted-mobiles-cherry-dreams-mobile.html&docid=UUGMgtOe_QHyXM&w=720&h=720",
            "position": 49
        },
        {
            "title": "Much to T-Mobile's displeasure, here's all the vintage ...",
            "imageUrl": "https://preview.redd.it/much-to-t-mobiles-displeasure-heres-all-the-vintage-phones-v0-je7023oew8k91.jpg?width=1080&crop=smart&auto=webp&s=03118c118c38361d1eb631b474f7e0543412ebed",
            "imageWidth": 1080,
            "imageHeight": 1440,
            "thumbnailUrl": "https://encrypted-tbn0.gstatic.com/images?q=tbn:ANd9GcRgyaARdlVckmrWK0KHS41KubIl3-S21A1DNg&s",
            "thumbnailWidth": 194,
            "thumbnailHeight": 259,
            "source": "Reddit",
            "domain": "www.reddit.com",
            "link": "https://www.reddit.com/r/vintagemobilephones/comments/wz11y7/much_to_tmobiles_displeasure_heres_all_the/",
            "googleUrl": "https://www.google.com/imgres?imgurl=https%3A%2F%2Fpreview.redd.it%2Fmuch-to-t-mobiles-displeasure-heres-all-the-vintage-phones-v0-je7023oew8k91.jpg%3Fwidth%3D1080%26crop%3Dsmart%26auto%3Dwebp%26s%3D03118c118c38361d1eb631b474f7e0543412ebed&tbnid=DpMOsGJFc40Q6M&imgrefurl=https%3A%2F%2Fwww.reddit.com%2Fr%2Fvintagemobilephones%2Fcomments%2Fwz11y7%2Fmuch_to_tmobiles_displeasure_heres_all_the%2F&docid=V6XKqqZ4-YDD9M&w=1080&h=1440",
            "position": 50
        },
        {
            "title": "Vivo All New & Best Mobiles Price List 2024",
            "imageUrl": "https://i.ytimg.com/vi/8U0lmF53VHA/hq720.jpg?sqp=-oaymwEhCK4FEIIDSFryq4qpAxMIARUAAAAAGAElAADIQj0AgKJD&rs=AOn4CLAbz92XLRfvVV3H4bR2JuKHHP1Upw",
            "imageWidth": 686,
            "imageHeight": 386,
            "thumbnailUrl": "https://encrypted-tbn0.gstatic.com/images?q=tbn:ANd9GcQ04WGQrGS0wRq-2NgJkstNj_mxfZ63A0C_qQ&s",
            "thumbnailWidth": 299,
            "thumbnailHeight": 168,
            "source": "YouTube",
            "domain": "m.youtube.com",
            "link": "https://m.youtube.com/watch?v=8U0lmF53VHA",
            "googleUrl": "https://www.google.com/imgres?imgurl=https%3A%2F%2Fi.ytimg.com%2Fvi%2F8U0lmF53VHA%2Fhq720.jpg%3Fsqp%3D-oaymwEhCK4FEIIDSFryq4qpAxMIARUAAAAAGAElAADIQj0AgKJD%26rs%3DAOn4CLAbz92XLRfvVV3H4bR2JuKHHP1Upw&tbnid=rmVJoPmrjEqTJM&imgrefurl=https%3A%2F%2Fm.youtube.com%2Fwatch%3Fv%3D8U0lmF53VHA&docid=76eFAkhZhqqlVM&w=686&h=386",
            "position": 51
        },
        {
            "title": "Mobile manufacturing remained crippled from January to May ...",
            "imageUrl": "https://profit.pakistantoday.com.pk/wp-content/uploads/2023/07/pp.jpg",
            "imageWidth": 1200,
            "imageHeight": 671,
            "thumbnailUrl": "https://encrypted-tbn0.gstatic.com/images?q=tbn:ANd9GcSyT9DLosf_Rp-4KphATcKqBKLdJh25W8wpIw&s",
            "thumbnailWidth": 300,
            "thumbnailHeight": 168,
            "source": "Profit by Pakistan Today",
            "domain": "profit.pakistantoday.com.pk",
            "link": "https://profit.pakistantoday.com.pk/2023/07/11/mobile-manufacturing-remained-crippled-from-january-to-may-due-to-lack-of-lcs/",
            "googleUrl": "https://www.google.com/imgres?imgurl=https%3A%2F%2Fprofit.pakistantoday.com.pk%2Fwp-content%2Fuploads%2F2023%2F07%2Fpp.jpg&tbnid=YEe2dfj5KicF7M&imgrefurl=https%3A%2F%2Fprofit.pakistantoday.com.pk%2F2023%2F07%2F11%2Fmobile-manufacturing-remained-crippled-from-january-to-may-due-to-lack-of-lcs%2F&docid=A05oanoYnWSNWM&w=1200&h=671",
            "position": 52
        },
        {
            "title": "Custom Hanging Mobile Sculpture and Mies van der Rohe Daybed",
            "imageUrl": "https://www.marcomahler.com/Marco-Mahler-Mobile-92-hi-res.jpg",
            "imageWidth": 3240,
            "imageHeight": 4320,
            "thumbnailUrl": "https://encrypted-tbn0.gstatic.com/images?q=tbn:ANd9GcSn846GcxKLa4d2Yyvz7yQSH93v1Tp7HoSCzA&s",
            "thumbnailWidth": 194,
            "thumbnailHeight": 259,
            "source": "Marco Mahler",
            "domain": "www.marcomahler.com",
            "link": "https://www.marcomahler.com/custom-hanging-mobiles-kinetic-sculptures-art/",
            "googleUrl": "https://www.google.com/imgres?imgurl=https%3A%2F%2Fwww.marcomahler.com%2FMarco-Mahler-Mobile-92-hi-res.jpg&tbnid=RPVJoU2wSwwK6M&imgrefurl=https%3A%2F%2Fwww.marcomahler.com%2Fcustom-hanging-mobiles-kinetic-sculptures-art%2F&docid=cmO12BhCQ--dFM&w=3240&h=4320",
            "position": 53
        },
        {
            "title": "Cell Phones: Shop the Best Smartphones Online | Verizon",
            "imageUrl": "https://ss7.vzw.com/is/image/VerizonWireless/iphone-14-productred-fall22-a",
            "imageWidth": 303,
            "imageHeight": 400,
            "thumbnailUrl": "https://encrypted-tbn0.gstatic.com/images?q=tbn:ANd9GcQoKW5B7waM8cC_FTIt2Ph4K32qobMGsQvpTg&s",
            "thumbnailWidth": 195,
            "thumbnailHeight": 258,
            "source": "Verizon",
            "domain": "www.verizon.com",
            "link": "https://www.verizon.com/smartphones/",
            "googleUrl": "https://www.google.com/imgres?imgurl=https%3A%2F%2Fss7.vzw.com%2Fis%2Fimage%2FVerizonWireless%2Fiphone-14-productred-fall22-a&tbnid=ev8Xy1qWPB0KvM&imgrefurl=https%3A%2F%2Fwww.verizon.com%2Fsmartphones%2F&docid=qcMkb9bLQvwYmM&w=303&h=400",
            "position": 54
        },
        {
            "title": "Best small phones 2024: compact yet powerful mini mobiles | T3",
            "imageUrl": "https://cdn.mos.cms.futurecdn.net/u8ifVcCswaH4E54jPoxLdi-415-80.jpg",
            "imageWidth": 415,
            "imageHeight": 233,
            "thumbnailUrl": "https://encrypted-tbn0.gstatic.com/images?q=tbn:ANd9GcQC0-KlxtLeoPN0b2fF_FSJ0oiDNFcc_CkYhA&s",
            "thumbnailWidth": 300,
            "thumbnailHeight": 168,
            "source": "T3",
            "domain": "www.t3.com",
            "link": "https://www.t3.com/features/best-compact-phones",
            "googleUrl": "https://www.google.com/imgres?imgurl=https%3A%2F%2Fcdn.mos.cms.futurecdn.net%2Fu8ifVcCswaH4E54jPoxLdi-415-80.jpg&tbnid=HpeQ5bF9RVB7XM&imgrefurl=https%3A%2F%2Fwww.t3.com%2Ffeatures%2Fbest-compact-phones&docid=_82S2HzBgcSREM&w=415&h=233",
            "position": 55
        },
        {
            "title": "9 Best Baby Mobiles - 2019 | The Strategist",
            "imageUrl": "https://pyxis.nymag.com/v1/imgs/3c6/e74/6baac897c7b505fa4a5161a7f3ab4db55a-22-mobiles.1x.rsquare.w1400.jpg",
            "imageWidth": 1000,
            "imageHeight": 1000,
            "thumbnailUrl": "https://encrypted-tbn0.gstatic.com/images?q=tbn:ANd9GcSglA0Qm-FVEE8zyyHSy4nWHwgOxPlZPZv8iQ&s",
            "thumbnailWidth": 225,
            "thumbnailHeight": 225,
            "source": "New York Magazine",
            "domain": "nymag.com",
            "link": "https://nymag.com/strategist/article/best-baby-mobiles.html",
            "googleUrl": "https://www.google.com/imgres?imgurl=https%3A%2F%2Fpyxis.nymag.com%2Fv1%2Fimgs%2F3c6%2Fe74%2F6baac897c7b505fa4a5161a7f3ab4db55a-22-mobiles.1x.rsquare.w1400.jpg&tbnid=Df7VOXjJgKIhrM&imgrefurl=https%3A%2F%2Fnymag.com%2Fstrategist%2Farticle%2Fbest-baby-mobiles.html&docid=6INmqrxSiOm7kM&w=1000&h=1000",
            "position": 56
        },
        {
            "title": "Mobile Phone at best price in Chennai by G S M Impex | ID ...",
            "imageUrl": "http://3.imimg.com/data3/TP/PX/MY-11752594/mobile-500x500.png",
            "imageWidth": 500,
            "imageHeight": 429,
            "thumbnailUrl": "https://encrypted-tbn0.gstatic.com/images?q=tbn:ANd9GcTe7lnz9CUZMI9CQN1cu6fl_le_bavh1Ex-PQ&s",
            "thumbnailWidth": 242,
            "thumbnailHeight": 208,
            "source": "IndiaMART",
            "domain": "m.indiamart.com",
            "link": "https://m.indiamart.com/proddetail/mobile-phone-7867275112.html",
            "googleUrl": "https://www.google.com/imgres?imgurl=http%3A%2F%2F3.imimg.com%2Fdata3%2FTP%2FPX%2FMY-11752594%2Fmobile-500x500.png&tbnid=CLmGuH7JYECRiM&imgrefurl=https%3A%2F%2Fm.indiamart.com%2Fproddetail%2Fmobile-phone-7867275112.html&docid=58d5Ca21MRIDaM&w=500&h=429",
            "position": 57
        },
        {
            "title": "The Best Modern Mobiles for Your Grown Up, Adult Space ...",
            "imageUrl": "https://cdn.apartmenttherapy.info/image/upload/f_auto,q_auto:eco,c_fit,w_730,h_947/at%2Farchive%2Fee104273fd370b2c0396ba3aeac6add0e9d16ffa",
            "imageWidth": 730,
            "imageHeight": 947,
            "thumbnailUrl": "https://encrypted-tbn0.gstatic.com/images?q=tbn:ANd9GcRrh0tZ-tgmcco6Q1gMRYbgtZlj_3ewLV5g-A&s",
            "thumbnailWidth": 197,
            "thumbnailHeight": 256,
            "source": "Apartment Therapy",
            "domain": "www.apartmenttherapy.com",
            "link": "https://www.apartmenttherapy.com/mobiles-as-art-trend-36840847",
            "googleUrl": "https://www.google.com/imgres?imgurl=https%3A%2F%2Fcdn.apartmenttherapy.info%2Fimage%2Fupload%2Ff_auto%2Cq_auto%3Aeco%2Cc_fit%2Cw_730%2Ch_947%2Fat%252Farchive%252Fee104273fd370b2c0396ba3aeac6add0e9d16ffa&tbnid=fUtMxPbZUweVUM&imgrefurl=https%3A%2F%2Fwww.apartmenttherapy.com%2Fmobiles-as-art-trend-36840847&docid=HqJwNvCJJCG7PM&w=730&h=947",
            "position": 58
        },
        {
            "title": "Mobiles: Find the Latest Smartphones & Mobile Phones | LG ...",
            "imageUrl": "https://www.lg.com/levant_en/images/plp-b2c/levanten-mobilephones-hero-1-m.jpg",
            "imageWidth": 768,
            "imageHeight": 1080,
            "thumbnailUrl": "https://encrypted-tbn0.gstatic.com/images?q=tbn:ANd9GcR52GFY1i0qNFoa6ihpbBH_lCkfQnIzVUuP2g&s",
            "thumbnailWidth": 189,
            "thumbnailHeight": 266,
            "source": "LG",
            "domain": "www.lg.com",
            "link": "https://www.lg.com/levant_en/mobile-phones",
            "googleUrl": "https://www.google.com/imgres?imgurl=https%3A%2F%2Fwww.lg.com%2Flevant_en%2Fimages%2Fplp-b2c%2Flevanten-mobilephones-hero-1-m.jpg&tbnid=Fl6JDnw74K4CxM&imgrefurl=https%3A%2F%2Fwww.lg.com%2Flevant_en%2Fmobile-phones&docid=jt_rRFz64S_ZTM&w=768&h=1080",
            "position": 59
        },
        {
            "title": "Mobiles | Buy Latest Smartphones online at best price | Viveks",
            "imageUrl": "https://media.viveks.com/media/catalog/product/cache/43c523c8c25ec73ea5fa54c25c6f766c/6/1/61izqzxuh9l._sl1200_.jpg",
            "imageWidth": 320,
            "imageHeight": 320,
            "thumbnailUrl": "https://encrypted-tbn0.gstatic.com/images?q=tbn:ANd9GcTmOf4gKzmFN1jN2Be7MqUFqnvNRq6fW5wzMA&s",
            "thumbnailWidth": 225,
            "thumbnailHeight": 225,
            "source": "Viveks",
            "domain": "viveks.com",
            "link": "https://viveks.com/mobiles-wearables/mobile-phones",
            "googleUrl": "https://www.google.com/imgres?imgurl=https%3A%2F%2Fmedia.viveks.com%2Fmedia%2Fcatalog%2Fproduct%2Fcache%2F43c523c8c25ec73ea5fa54c25c6f766c%2F6%2F1%2F61izqzxuh9l._sl1200_.jpg&tbnid=B9RgTmEzTmZJzM&imgrefurl=https%3A%2F%2Fviveks.com%2Fmobiles-wearables%2Fmobile-phones&docid=R8zXqOaFzlG5sM&w=320&h=320",
            "position": 60
        },
        {
            "title": "Tik Tak | Stunning Baby Mobiles & Home Decor | All Natural ...",
            "imageUrl": "https://tiktakdesignco.com/cdn/shop/files/kiwibabymobile_1600x.jpg?v=1715846803",
            "imageWidth": 1024,
            "imageHeight": 1024,
            "thumbnailUrl": "https://encrypted-tbn0.gstatic.com/images?q=tbn:ANd9GcTrXtpFCPK7TV-6GS1tBDG616e4c_iA7k9_Ow&s",
            "thumbnailWidth": 225,
            "thumbnailHeight": 225,
            "source": "tiktakdesignco.com",
            "domain": "tiktakdesignco.com",
            "link": "https://tiktakdesignco.com/",
            "googleUrl": "https://www.google.com/imgres?imgurl=https%3A%2F%2Ftiktakdesignco.com%2Fcdn%2Fshop%2Ffiles%2Fkiwibabymobile_1600x.jpg%3Fv%3D1715846803&tbnid=khG_8v4pHLjOcM&imgrefurl=https%3A%2F%2Ftiktakdesignco.com%2F&docid=B1Y5QWf8h2nfgM&w=1024&h=1024",
            "position": 61
        },
        {
            "title": "Painted Leaf Mobiles - ARTBAR",
            "imageUrl": "https://www.artbarblog.com/wp-content/uploads/2016/09/leaf_mobile16-2.jpg",
            "imageWidth": 800,
            "imageHeight": 1108,
            "thumbnailUrl": "https://encrypted-tbn0.gstatic.com/images?q=tbn:ANd9GcTK_6uo_-5ItrL48cjpPNo5FwF_YPdzaTTxvA&s",
            "thumbnailWidth": 191,
            "thumbnailHeight": 264,
            "source": "Art Bar Blog",
            "domain": "www.artbarblog.com",
            "link": "https://www.artbarblog.com/painted-leaf-mobiles/",
            "googleUrl": "https://www.google.com/imgres?imgurl=https%3A%2F%2Fwww.artbarblog.com%2Fwp-content%2Fuploads%2F2016%2F09%2Fleaf_mobile16-2.jpg&tbnid=m9_swBwDu8DR3M&imgrefurl=https%3A%2F%2Fwww.artbarblog.com%2Fpainted-leaf-mobiles%2F&docid=qkXFv2sDqTWszM&w=800&h=1108",
            "position": 62
        },
        {
            "title": "Best Mobiles Phones Under 40000 In Pakistan (October, 2024 ...",
            "imageUrl": "https://www.buyyourphone.pk/static/mobile-images/xiaomi-redmi-13-buyyourphone-3507259475.webp/",
            "imageWidth": 500,
            "imageHeight": 500,
            "thumbnailUrl": "https://encrypted-tbn0.gstatic.com/images?q=tbn:ANd9GcToz9mqupCL57RE5mlcMtlTAy3_zEkUdgLw4A&s",
            "thumbnailWidth": 225,
            "thumbnailHeight": 225,
            "source": "BuyYourPhone",
            "domain": "www.buyyourphone.pk",
            "link": "https://www.buyyourphone.pk/best-mobiles-under-40000/",
            "googleUrl": "https://www.google.com/imgres?imgurl=https%3A%2F%2Fwww.buyyourphone.pk%2Fstatic%2Fmobile-images%2Fxiaomi-redmi-13-buyyourphone-3507259475.webp%2F&tbnid=FWRGoCblsHHEUM&imgrefurl=https%3A%2F%2Fwww.buyyourphone.pk%2Fbest-mobiles-under-40000%2F&docid=YDjboexO4bK3ZM&w=500&h=500",
            "position": 63
        },
        {
            "title": "5 Most Crucial problems of Samsung mobiles and its solutions",
            "imageUrl": "https://ifixscreens.com/storage/2020/08/Top-5-problems-of-Samsung-mobiles-in-2020-and-how-to-fix-it.jpg.webp",
            "imageWidth": 700,
            "imageHeight": 468,
            "thumbnailUrl": "https://encrypted-tbn0.gstatic.com/images?q=tbn:ANd9GcRh8p7BJXcRFJW4zB4OanMa1ybVxkARkso3vg&s",
            "thumbnailWidth": 275,
            "thumbnailHeight": 183,
            "source": "iFixScreens",
            "domain": "ifixscreens.com",
            "link": "https://ifixscreens.com/5-problems-of-samsung-mobiles/",
            "googleUrl": "https://www.google.com/imgres?imgurl=https%3A%2F%2Fifixscreens.com%2Fstorage%2F2020%2F08%2FTop-5-problems-of-Samsung-mobiles-in-2020-and-how-to-fix-it.jpg.webp&tbnid=WXdF80775iu1VM&imgrefurl=https%3A%2F%2Fifixscreens.com%2F5-problems-of-samsung-mobiles%2F&docid=tusMJ3C8u0xwPM&w=700&h=468",
            "position": 64
        },
        {
            "title": "Alexander Calder: Sculpture–Mobiles (1962) | Calder Foundation",
            "imageUrl": "https://calder.org/wp-content/uploads/historical-photos/alexander-calder-sculpture-mobiles-1962/alexander-calder-sculpture-mobiles-1962-768x591.jpg",
            "imageWidth": 768,
            "imageHeight": 591,
            "thumbnailUrl": "https://encrypted-tbn0.gstatic.com/images?q=tbn:ANd9GcSrDhwUok1YDywcp0Yss6pbLKdoFdm3MMPA9g&s",
            "thumbnailWidth": 256,
            "thumbnailHeight": 197,
            "source": "Calder Foundation",
            "domain": "calder.org",
            "link": "https://calder.org/historical-photos/alexander-calder-sculpture-mobiles-1962/",
            "googleUrl": "https://www.google.com/imgres?imgurl=https%3A%2F%2Fcalder.org%2Fwp-content%2Fuploads%2Fhistorical-photos%2Falexander-calder-sculpture-mobiles-1962%2Falexander-calder-sculpture-mobiles-1962-768x591.jpg&tbnid=FI-e2tccYR89VM&imgrefurl=https%3A%2F%2Fcalder.org%2Fhistorical-photos%2Falexander-calder-sculpture-mobiles-1962%2F&docid=TWVdTc3sMIXsQM&w=768&h=591",
            "position": 65
        },
        {
            "title": "Cell Phones: Shop the Best Smartphones Online | Verizon",
            "imageUrl": "https://ss7.vzw.com/is/image/VerizonWireless/apple-iphone-16-pro-desert-titanium",
            "imageWidth": 323,
            "imageHeight": 400,
            "thumbnailUrl": "https://encrypted-tbn0.gstatic.com/images?q=tbn:ANd9GcS7SJ9HlgFP-MwuHI3wbxOsjin5j8AtGbkC8A&s",
            "thumbnailWidth": 202,
            "thumbnailHeight": 250,
            "source": "Verizon",
            "domain": "www.verizon.com",
            "link": "https://www.verizon.com/smartphones/",
            "googleUrl": "https://www.google.com/imgres?imgurl=https%3A%2F%2Fss7.vzw.com%2Fis%2Fimage%2FVerizonWireless%2Fapple-iphone-16-pro-desert-titanium&tbnid=D_PC6B05IvTz1M&imgrefurl=https%3A%2F%2Fwww.verizon.com%2Fsmartphones%2F&docid=qcMkb9bLQvwYmM&w=323&h=400",
            "position": 66
        },
        {
            "title": "Organic Kids & Baby Clothes | Nursery Mobiles | Pehr US",
            "imageUrl": "https://pehr.com/cdn/shop/products/MFMO_MagicalForest_Mobile_WEB.jpg?v=1701194706&width=1000",
            "imageWidth": 1000,
            "imageHeight": 1000,
            "thumbnailUrl": "https://encrypted-tbn0.gstatic.com/images?q=tbn:ANd9GcR3bHjyPbQB-lYYmmSBcudWilGyinQs8CZa0w&s",
            "thumbnailWidth": 225,
            "thumbnailHeight": 225,
            "source": "Pehr",
            "domain": "pehr.com",
            "link": "https://pehr.com/collections/petit-mobiles",
            "googleUrl": "https://www.google.com/imgres?imgurl=https%3A%2F%2Fpehr.com%2Fcdn%2Fshop%2Fproducts%2FMFMO_MagicalForest_Mobile_WEB.jpg%3Fv%3D1701194706%26width%3D1000&tbnid=Ua5hzS9YQpRcrM&imgrefurl=https%3A%2F%2Fpehr.com%2Fcollections%2Fpetit-mobiles&docid=Q5LEKpqeYBN8NM&w=1000&h=1000",
            "position": 67
        },
        {
            "title": "7 Artists Who Created Innovative Mobiles—beyond Alexander ...",
            "imageUrl": "https://d7hftxdivxxvm.cloudfront.net/?quality=80&resize_to=width&src=https%3A%2F%2Fd32dm0rphc51dk.cloudfront.net%2Fk6c60ACjvzyGgMGNMxMVaA%2Fnormalized.jpg&width=910",
            "imageWidth": 910,
            "imageHeight": 595,
            "thumbnailUrl": "https://encrypted-tbn0.gstatic.com/images?q=tbn:ANd9GcROhIImgxcVHUGmtp1d-D_M-6Ws4Ekx4NblEQ&s",
            "thumbnailWidth": 278,
            "thumbnailHeight": 181,
            "source": "Artsy",
            "domain": "www.artsy.net",
            "link": "https://www.artsy.net/article/artsy-editorial-7-artists-created-innovative-mobiles-alexander-calder",
            "googleUrl": "https://www.google.com/imgres?imgurl=https%3A%2F%2Fd7hftxdivxxvm.cloudfront.net%2F%3Fquality%3D80%26resize_to%3Dwidth%26src%3Dhttps%253A%252F%252Fd32dm0rphc51dk.cloudfront.net%252Fk6c60ACjvzyGgMGNMxMVaA%252Fnormalized.jpg%26width%3D910&tbnid=q6HQSLU3pptpRM&imgrefurl=https%3A%2F%2Fwww.artsy.net%2Farticle%2Fartsy-editorial-7-artists-created-innovative-mobiles-alexander-calder&docid=bTCTnI17toHEVM&w=910&h=595",
            "position": 68
        },
        {
            "title": "Mobiles Tycoon on Steam",
            "imageUrl": "https://shared.cloudflare.steamstatic.com/store_item_assets/steam/apps/3022320/header.jpg",
            "imageWidth": 460,
            "imageHeight": 215,
            "thumbnailUrl": "https://encrypted-tbn0.gstatic.com/images?q=tbn:ANd9GcS8qR1ErTWJj843RfMHNvPp1KKOuP_RpG4vYQ&s",
            "thumbnailWidth": 329,
            "thumbnailHeight": 153,
            "source": "Steam",
            "domain": "store.steampowered.com",
            "link": "https://store.steampowered.com/app/3022320/Mobiles_Tycoon/",
            "googleUrl": "https://www.google.com/imgres?imgurl=https%3A%2F%2Fshared.cloudflare.steamstatic.com%2Fstore_item_assets%2Fsteam%2Fapps%2F3022320%2Fheader.jpg&tbnid=Mdwz-KeUyAVstM&imgrefurl=https%3A%2F%2Fstore.steampowered.com%2Fapp%2F3022320%2FMobiles_Tycoon%2F&docid=vmpEDdmJBiQkyM&w=460&h=215",
            "position": 69
        },
        {
            "title": "Have Anybody used G Five Mobiles? : r/IndiaNostalgia",
            "imageUrl": "https://i.redd.it/xv2itm52an1c1.jpg",
            "imageWidth": 225,
            "imageHeight": 225,
            "thumbnailUrl": "https://encrypted-tbn0.gstatic.com/images?q=tbn:ANd9GcR4pxijvg7eNf4Fp2JOUkxetMitfhcLrzLL4A&s",
            "thumbnailWidth": 225,
            "thumbnailHeight": 225,
            "source": "Reddit",
            "domain": "www.reddit.com",
            "link": "https://www.reddit.com/r/IndiaNostalgia/comments/180ai7o/have_anybody_used_g_five_mobiles/",
            "googleUrl": "https://www.google.com/imgres?imgurl=https%3A%2F%2Fi.redd.it%2Fxv2itm52an1c1.jpg&tbnid=MeAyC9EwSuiZMM&imgrefurl=https%3A%2F%2Fwww.reddit.com%2Fr%2FIndiaNostalgia%2Fcomments%2F180ai7o%2Fhave_anybody_used_g_five_mobiles%2F&docid=Ud2tjaQE4Yu43M&w=225&h=225",
            "position": 70
        },
        {
            "title": "Mobile Phones: Buy New Mobiles and Latest Mobile Online at ...",
            "imageUrl": "https://www.reliancedigital.in/medias/iPhone-16-544x306-M.jpg?context=bWFzdGVyfGltYWdlc3w5OTE1NHxpbWFnZS9qcGVnfGltYWdlcy9oYjQvaDNmLzEwMjAwODg5NzIwODYyLmpwZ3wzZDFhNzdkY2VlMjcyNDRhODkyMWIyY2FjNjlkNDk1MWVhZTA2YmY0YzY5MWUyMWIwNTRjZDJkOTMxNWQyMjAw",
            "imageWidth": 544,
            "imageHeight": 306,
            "thumbnailUrl": "https://encrypted-tbn0.gstatic.com/images?q=tbn:ANd9GcRAMku-ou6yx3hMX4UGlf_G-59jlvFpqklYgw&s",
            "thumbnailWidth": 300,
            "thumbnailHeight": 168,
            "source": "Reliance Digital",
            "domain": "www.reliancedigital.in",
            "link": "https://www.reliancedigital.in/smartphones/c/S101711",
            "googleUrl": "https://www.google.com/imgres?imgurl=https%3A%2F%2Fwww.reliancedigital.in%2Fmedias%2FiPhone-16-544x306-M.jpg%3Fcontext%3DbWFzdGVyfGltYWdlc3w5OTE1NHxpbWFnZS9qcGVnfGltYWdlcy9oYjQvaDNmLzEwMjAwODg5NzIwODYyLmpwZ3wzZDFhNzdkY2VlMjcyNDRhODkyMWIyY2FjNjlkNDk1MWVhZTA2YmY0YzY5MWUyMWIwNTRjZDJkOTMxNWQyMjAw&tbnid=lZKPFxvE1Q3VTM&imgrefurl=https%3A%2F%2Fwww.reliancedigital.in%2Fsmartphones%2Fc%2FS101711&docid=aYv_lpCiCvcNSM&w=544&h=306",
            "position": 71
        },
        {
            "title": "K5 Mobiles",
            "imageUrl": "https://lookaside.fbsbx.com/lookaside/crawler/media/?media_id=369001172144083",
            "imageWidth": 1290,
            "imageHeight": 1980,
            "thumbnailUrl": "https://encrypted-tbn0.gstatic.com/images?q=tbn:ANd9GcRdBVBfuy6S8zgMGGyh88qZVSEi8EZ5vOJAlw&s",
            "thumbnailWidth": 181,
            "thumbnailHeight": 278,
            "source": "Facebook",
            "domain": "www.facebook.com",
            "link": "https://www.facebook.com/k5mobileofficial/",
            "googleUrl": "https://www.google.com/imgres?imgurl=https%3A%2F%2Flookaside.fbsbx.com%2Flookaside%2Fcrawler%2Fmedia%2F%3Fmedia_id%3D369001172144083&tbnid=GY0pmqOe9zhlsM&imgrefurl=https%3A%2F%2Fwww.facebook.com%2Fk5mobileofficial%2F&docid=kbQ83DOz4d1-BM&w=1290&h=1980",
            "position": 72
        },
        {
            "title": "Upcoming Smartphones in July 2024: List of mobiles releasing ...",
            "imageUrl": "https://static.toiimg.com/thumb/msid-111407917,width-400,resizemode-4/111407917.jpg",
            "imageWidth": 400,
            "imageHeight": 225,
            "thumbnailUrl": "https://encrypted-tbn0.gstatic.com/images?q=tbn:ANd9GcSTea1RsauT90VM7jTgFHw7pbtFYZfQ3P3lGw&s",
            "thumbnailWidth": 300,
            "thumbnailHeight": 168,
            "source": "Times of India",
            "domain": "timesofindia.indiatimes.com",
            "link": "https://timesofindia.indiatimes.com/technology/mobiles-tabs/upcoming-smartphones-in-july-2024-list-of-mobiles-releasing-in-july-by-iqoo-samsung-and-other-popular-brands/articleshow/111407926.cms",
            "googleUrl": "https://www.google.com/imgres?imgurl=https%3A%2F%2Fstatic.toiimg.com%2Fthumb%2Fmsid-111407917%2Cwidth-400%2Cresizemode-4%2F111407917.jpg&tbnid=Ymw7U0ly29HKnM&imgrefurl=https%3A%2F%2Ftimesofindia.indiatimes.com%2Ftechnology%2Fmobiles-tabs%2Fupcoming-smartphones-in-july-2024-list-of-mobiles-releasing-in-july-by-iqoo-samsung-and-other-popular-brands%2Farticleshow%2F111407926.cms&docid=2OkJvNKJniec-M&w=400&h=225",
            "position": 73
        },
        {
            "title": "Smartphones, Mobile Phones & Cell Phones - Unlocked Phones ...",
            "imageUrl": "https://cdn-dynmedia-1.microsoft.com/is/image/microsoftcorp/Samsung-Galaxy-S20-Family-CC?wid=834&hei=470&fit=crop",
            "imageWidth": 834,
            "imageHeight": 470,
            "thumbnailUrl": "https://encrypted-tbn0.gstatic.com/images?q=tbn:ANd9GcT-eEqhPjhgJXamTePRQGr6Z_vv2_gSQsMoaw&s",
            "thumbnailWidth": 299,
            "thumbnailHeight": 168,
            "source": "Microsoft",
            "domain": "www.microsoft.com",
            "link": "https://www.microsoft.com/en-us/store/b/mobile",
            "googleUrl": "https://www.google.com/imgres?imgurl=https%3A%2F%2Fcdn-dynmedia-1.microsoft.com%2Fis%2Fimage%2Fmicrosoftcorp%2FSamsung-Galaxy-S20-Family-CC%3Fwid%3D834%26hei%3D470%26fit%3Dcrop&tbnid=21_OqXULgOfhGM&imgrefurl=https%3A%2F%2Fwww.microsoft.com%2Fen-us%2Fstore%2Fb%2Fmobile&docid=7-TzuYnb_JFoFM&w=834&h=470",
            "position": 74
        },
        {
            "title": "How to Hang Your Montessori Mobiles",
            "imageUrl": "https://blogger.googleusercontent.com/img/b/R29vZ2xl/AVvXsEgTKc_1zRfz0P_Me7L3a5MuKECHqeuTcI4jS8d86MJg7DJkT7D8HHDqTRET6uiWyIEMp_UqKcV_OsfwwlKBfF4kxPKxeOW9ZZfzEGhIoe1xnMhjC_849HnbhJxrNz0HsvH3wEVzQD2V51s/s1600/mobile1.jpg",
            "imageWidth": 735,
            "imageHeight": 1332,
            "thumbnailUrl": "https://encrypted-tbn0.gstatic.com/images?q=tbn:ANd9GcRxjE98NUfBk-q8S_aWqvpwkqJoetSTicmaQQ&s",
            "thumbnailWidth": 167,
            "thumbnailHeight": 302,
            "source": "The Kavanaugh Report",
            "domain": "www.thekavanaughreport.com",
            "link": "https://www.thekavanaughreport.com/2016/03/how-to-hang-your-montessori-mobiles.html",
            "googleUrl": "https://www.google.com/imgres?imgurl=https%3A%2F%2Fblogger.googleusercontent.com%2Fimg%2Fb%2FR29vZ2xl%2FAVvXsEgTKc_1zRfz0P_Me7L3a5MuKECHqeuTcI4jS8d86MJg7DJkT7D8HHDqTRET6uiWyIEMp_UqKcV_OsfwwlKBfF4kxPKxeOW9ZZfzEGhIoe1xnMhjC_849HnbhJxrNz0HsvH3wEVzQD2V51s%2Fs1600%2Fmobile1.jpg&tbnid=QRsEyjHT1nGjcM&imgrefurl=https%3A%2F%2Fwww.thekavanaughreport.com%2F2016%2F03%2Fhow-to-hang-your-montessori-mobiles.html&docid=txozngpYFj2Z4M&w=735&h=1332",
            "position": 75
        },
        {
            "title": "many modern mobile phones with different abstract textures ...",
            "imageUrl": "https://c8.alamy.com/comp/JAR8TY/many-modern-mobile-phones-with-different-abstract-textures-JAR8TY.jpg",
            "imageWidth": 1300,
            "imageHeight": 1153,
            "thumbnailUrl": "https://encrypted-tbn0.gstatic.com/images?q=tbn:ANd9GcT9tgBZpgj-R2elBJfou5e1l6BMCdSyQ9fwLg&s",
            "thumbnailWidth": 238,
            "thumbnailHeight": 211,
            "source": "Alamy",
            "domain": "www.alamy.com",
            "link": "https://www.alamy.com/stock-photo-many-modern-mobile-phones-with-different-abstract-textures-144341371.html",
            "googleUrl": "https://www.google.com/imgres?imgurl=https%3A%2F%2Fc8.alamy.com%2Fcomp%2FJAR8TY%2Fmany-modern-mobile-phones-with-different-abstract-textures-JAR8TY.jpg&tbnid=uRIsyopePGEi5M&imgrefurl=https%3A%2F%2Fwww.alamy.com%2Fstock-photo-many-modern-mobile-phones-with-different-abstract-textures-144341371.html&docid=jtfElHNs1LPsnM&w=1300&h=1153",
            "position": 76
        },
        {
            "title": "Mobile or Computers: Which Tech is More Secure? - Security ...",
            "imageUrl": "https://www.socinvestigation.com/wp-content/uploads/2023/01/Mobile_computer_which_is_secure.jpg",
            "imageWidth": 1920,
            "imageHeight": 1275,
            "thumbnailUrl": "https://encrypted-tbn0.gstatic.com/images?q=tbn:ANd9GcS4S0Pf1jPMcqsRvhlIpaXgmwuRoEhRaeg4PQ&s",
            "thumbnailWidth": 276,
            "thumbnailHeight": 183,
            "source": "Soc Investigation",
            "domain": "www.socinvestigation.com",
            "link": "https://www.socinvestigation.com/mobile-or-computers-which-tech-is-more-secure/",
            "googleUrl": "https://www.google.com/imgres?imgurl=https%3A%2F%2Fwww.socinvestigation.com%2Fwp-content%2Fuploads%2F2023%2F01%2FMobile_computer_which_is_secure.jpg&tbnid=CsKOkWRm8XAQRM&imgrefurl=https%3A%2F%2Fwww.socinvestigation.com%2Fmobile-or-computers-which-tech-is-more-secure%2F&docid=qP45gkHY2TwImM&w=1920&h=1275",
            "position": 77
        },
        {
            "title": "HANGING MOBILE — COSMIC PEACE STUDIO",
            "imageUrl": "https://cosmicpeacestudio.com/cdn/shop/products/CR151_400x533.jpg?v=1571438966",
            "imageWidth": 400,
            "imageHeight": 533,
            "thumbnailUrl": "https://encrypted-tbn0.gstatic.com/images?q=tbn:ANd9GcSzsb6Yf3dHMH5aKOt1nvz_IUyCp-r6yrLVOw&s",
            "thumbnailWidth": 194,
            "thumbnailHeight": 259,
            "source": "COSMIC PEACE STUDIO",
            "domain": "cosmicpeacestudio.com",
            "link": "https://cosmicpeacestudio.com/products/hanging-mobile",
            "googleUrl": "https://www.google.com/imgres?imgurl=https%3A%2F%2Fcosmicpeacestudio.com%2Fcdn%2Fshop%2Fproducts%2FCR151_400x533.jpg%3Fv%3D1571438966&tbnid=EHu7SNIqYi4aNM&imgrefurl=https%3A%2F%2Fcosmicpeacestudio.com%2Fproducts%2Fhanging-mobile&docid=jSPD-YyvhrFFxM&w=400&h=533",
            "position": 78
        },
        {
            "title": "14+ Best DIY Rainbow Mobile Ideas for Baby Cribs",
            "imageUrl": "https://www.crazylaura.com/wp-content/uploads/2022/08/14-Best-DIY-Rainbow-Mobiles-for-Baby-Cribs.jpg",
            "imageWidth": 820,
            "imageHeight": 550,
            "thumbnailUrl": "https://encrypted-tbn0.gstatic.com/images?q=tbn:ANd9GcQrum1EnUG40MfawpB7gPDXlbmFae_Fr5qkOw&s",
            "thumbnailWidth": 274,
            "thumbnailHeight": 184,
            "source": "Crazy Laura",
            "domain": "www.crazylaura.com",
            "link": "https://www.crazylaura.com/best-diy-rainbow-mobiles/",
            "googleUrl": "https://www.google.com/imgres?imgurl=https%3A%2F%2Fwww.crazylaura.com%2Fwp-content%2Fuploads%2F2022%2F08%2F14-Best-DIY-Rainbow-Mobiles-for-Baby-Cribs.jpg&tbnid=lif-HWR26svnhM&imgrefurl=https%3A%2F%2Fwww.crazylaura.com%2Fbest-diy-rainbow-mobiles%2F&docid=SvRdxeYId1mHYM&w=820&h=550",
            "position": 79
        },
        {
            "title": "The simplest paper mobile - Rebecca Desnos",
            "imageUrl": "https://rebeccadesnos.com/wp-content/uploads/2023/04/20181226-A-2_IMG_5075-1-1080x810_1024x1024.jpg?v=1568591360",
            "imageWidth": 1024,
            "imageHeight": 768,
            "thumbnailUrl": "https://encrypted-tbn0.gstatic.com/images?q=tbn:ANd9GcQHRdn8pBN5Nc2Baez_DRWC3r0Xk2NliRmnxA&s",
            "thumbnailWidth": 259,
            "thumbnailHeight": 194,
            "source": "Rebecca Desnos",
            "domain": "rebeccadesnos.com",
            "link": "https://rebeccadesnos.com/blogs/journal/the-simplest-paper-mobile/",
            "googleUrl": "https://www.google.com/imgres?imgurl=https%3A%2F%2Frebeccadesnos.com%2Fwp-content%2Fuploads%2F2023%2F04%2F20181226-A-2_IMG_5075-1-1080x810_1024x1024.jpg%3Fv%3D1568591360&tbnid=np5WGPF4Cxgz5M&imgrefurl=https%3A%2F%2Frebeccadesnos.com%2Fblogs%2Fjournal%2Fthe-simplest-paper-mobile%2F&docid=OPOVtIOVXXByoM&w=1024&h=768",
            "position": 80
        },
        {
            "title": "20 Best Baby Mobiles for Infants",
            "imageUrl": "https://images.ctfassets.net/6m9bd13t776q/3z5QgMl3zY2ZR76lM6o6wb/f99530b8063e16f0c4906017901e2d5a/Goukurlsma_Neutral_Boho_Rainbow_Baby_Mobile.webp?q=75",
            "imageWidth": 600,
            "imageHeight": 600,
            "thumbnailUrl": "https://encrypted-tbn0.gstatic.com/images?q=tbn:ANd9GcQL_SUn0V7G7BANr3AOnLcn92i2SD96TcePcg&s",
            "thumbnailWidth": 225,
            "thumbnailHeight": 225,
            "source": "The Bump",
            "domain": "www.thebump.com",
            "link": "https://www.thebump.com/a/best-crib-mobiles",
            "googleUrl": "https://www.google.com/imgres?imgurl=https%3A%2F%2Fimages.ctfassets.net%2F6m9bd13t776q%2F3z5QgMl3zY2ZR76lM6o6wb%2Ff99530b8063e16f0c4906017901e2d5a%2FGoukurlsma_Neutral_Boho_Rainbow_Baby_Mobile.webp%3Fq%3D75&tbnid=6JzwsL4zsvgV5M&imgrefurl=https%3A%2F%2Fwww.thebump.com%2Fa%2Fbest-crib-mobiles&docid=tRAy6K24tEmfCM&w=600&h=600",
            "position": 81
        },
        {
            "title": "Buy Mobiles, Tablets, Gadgets, Laptops & Smart Tv- Supreme ...",
            "imageUrl": "https://suprememobiles.in/cdn/shop/files/mobiles.jpg?crop=center&height=2048&v=1664280076&width=2048",
            "imageWidth": 500,
            "imageHeight": 500,
            "thumbnailUrl": "https://encrypted-tbn0.gstatic.com/images?q=tbn:ANd9GcRNquXdGvP_KJNOdh_q0dDJYSUDi_BWqAIKQw&s",
            "thumbnailWidth": 225,
            "thumbnailHeight": 225,
            "source": "suprememobiles.in",
            "domain": "suprememobiles.in",
            "link": "https://suprememobiles.in/",
            "googleUrl": "https://www.google.com/imgres?imgurl=https%3A%2F%2Fsuprememobiles.in%2Fcdn%2Fshop%2Ffiles%2Fmobiles.jpg%3Fcrop%3Dcenter%26height%3D2048%26v%3D1664280076%26width%3D2048&tbnid=4ZIPcrTb-56gpM&imgrefurl=https%3A%2F%2Fsuprememobiles.in%2F&docid=hY66ZOrVgMxU8M&w=500&h=500",
            "position": 82
        },
        {
            "title": "Tecno Spark 10 Price in Pakistan 2024 | PriceOye",
            "imageUrl": "https://images.priceoye.pk/tecno-spark-10-pakistan-priceoye-jookw.jpg",
            "imageWidth": 1200,
            "imageHeight": 1200,
            "thumbnailUrl": "https://encrypted-tbn0.gstatic.com/images?q=tbn:ANd9GcQDgqK2_CH7YqLtA6dEcKkcdGyNIOtyUk27PQ&s",
            "thumbnailWidth": 225,
            "thumbnailHeight": 225,
            "source": "PriceOye",
            "domain": "priceoye.pk",
            "link": "https://priceoye.pk/mobiles/tecno/tecno-spark-10",
            "googleUrl": "https://www.google.com/imgres?imgurl=https%3A%2F%2Fimages.priceoye.pk%2Ftecno-spark-10-pakistan-priceoye-jookw.jpg&tbnid=u8VO33fKu-o4OM&imgrefurl=https%3A%2F%2Fpriceoye.pk%2Fmobiles%2Ftecno%2Ftecno-spark-10&docid=5KTNEYZ5JymJ5M&w=1200&h=1200",
            "position": 83
        },
        {
            "title": "No Mobiles Cell Phones Template | PosterMyWall",
            "imageUrl": "https://d1csarkz8obe9u.cloudfront.net/posterpreviews/no-mobiles-cell-phones-template-design-a196cf8c7a35a75b1e75dc444dff7665_screen.jpg?ts=1636981743",
            "imageWidth": 462,
            "imageHeight": 693,
            "thumbnailUrl": "https://encrypted-tbn0.gstatic.com/images?q=tbn:ANd9GcQW6QCmkvnAO28dE6BPal9zOBsEkoxuFiTIjA&s",
            "thumbnailWidth": 183,
            "thumbnailHeight": 275,
            "source": "PosterMyWall",
            "domain": "www.postermywall.com",
            "link": "https://www.postermywall.com/index.php/art/template/a196cf8c7a35a75b1e75dc444dff7665/no-mobiles-cell-phones-template-design",
            "googleUrl": "https://www.google.com/imgres?imgurl=https%3A%2F%2Fd1csarkz8obe9u.cloudfront.net%2Fposterpreviews%2Fno-mobiles-cell-phones-template-design-a196cf8c7a35a75b1e75dc444dff7665_screen.jpg%3Fts%3D1636981743&tbnid=BvGW-OWlsQ_FoM&imgrefurl=https%3A%2F%2Fwww.postermywall.com%2Findex.php%2Fart%2Ftemplate%2Fa196cf8c7a35a75b1e75dc444dff7665%2Fno-mobiles-cell-phones-template-design&docid=LCNzf3f0oJCJOM&w=462&h=693",
            "position": 84
        },
        {
            "title": "New Cell Phones for Sale | Buy Smartphones Online or In-Store",
            "imageUrl": "https://cdn.tmobile.com/content/dam/t-mobile/en-p/cell-phones/Motorola/Motorola-edge-2024/Midnight-Blue/Motorola-edge-2024-Midnight-Blue-thumbnail.png",
            "imageWidth": 274,
            "imageHeight": 440,
            "thumbnailUrl": "https://encrypted-tbn0.gstatic.com/images?q=tbn:ANd9GcQoebSp-E2vNc-FyaPSeiYA-oXEJI6rNPQ6OQ&s",
            "thumbnailWidth": 177,
            "thumbnailHeight": 285,
            "source": "T-Mobile",
            "domain": "www.t-mobile.com",
            "link": "https://www.t-mobile.com/cell-phones",
            "googleUrl": "https://www.google.com/imgres?imgurl=https%3A%2F%2Fcdn.tmobile.com%2Fcontent%2Fdam%2Ft-mobile%2Fen-p%2Fcell-phones%2FMotorola%2FMotorola-edge-2024%2FMidnight-Blue%2FMotorola-edge-2024-Midnight-Blue-thumbnail.png&tbnid=u_XAhXeEbQ1g-M&imgrefurl=https%3A%2F%2Fwww.t-mobile.com%2Fcell-phones&docid=dxmizf9vOXISyM&w=274&h=440",
            "position": 85
        },
        {
            "title": "Large Custom Calder-Style Mobile at Snowy Park",
            "imageUrl": "https://www.marcomahler.com/calder-style-mobile-with-snow-flurry.gif",
            "imageWidth": 800,
            "imageHeight": 600,
            "thumbnailUrl": "https://encrypted-tbn0.gstatic.com/images?q=tbn:ANd9GcTMNCZAMx9wLFbyrE5S-MCd-gqwD1jjHiaCcg&s",
            "thumbnailWidth": 259,
            "thumbnailHeight": 194,
            "source": "Marco Mahler",
            "domain": "www.marcomahler.com",
            "link": "https://www.marcomahler.com/large-calder-style-mobile-custom-sale/",
            "googleUrl": "https://www.google.com/imgres?imgurl=https%3A%2F%2Fwww.marcomahler.com%2Fcalder-style-mobile-with-snow-flurry.gif&tbnid=rlIaTde5ByFlhM&imgrefurl=https%3A%2F%2Fwww.marcomahler.com%2Flarge-calder-style-mobile-custom-sale%2F&docid=yMeuTOcFyOxIYM&w=800&h=600",
            "position": 86
        },
        {
            "title": "Flensted Mobiles - Cherry Dreams Mobile | Connox",
            "imageUrl": "https://cdn.connox.com/m/100109/571940/media/Flensted-Mobiles/2022/Flensted-Mobiles-Cherry-Dreams-Mobile-Messing-Holz-mehrfarbig-Ambiente.jpg",
            "imageWidth": 720,
            "imageHeight": 720,
            "thumbnailUrl": "https://encrypted-tbn0.gstatic.com/images?q=tbn:ANd9GcRONDM7TghwQ480XelfVv9x6hqcDeVPcqJhSQ&s",
            "thumbnailWidth": 225,
            "thumbnailHeight": 225,
            "source": "Connox",
            "domain": "www.connox.com",
            "link": "https://www.connox.com/categories/accessories/home-decor/children-design-mobiles/flensted-mobiles-cherry-dreams-mobile.html",
            "googleUrl": "https://www.google.com/imgres?imgurl=https%3A%2F%2Fcdn.connox.com%2Fm%2F100109%2F571940%2Fmedia%2FFlensted-Mobiles%2F2022%2FFlensted-Mobiles-Cherry-Dreams-Mobile-Messing-Holz-mehrfarbig-Ambiente.jpg&tbnid=t1GNdYIWnG0lXM&imgrefurl=https%3A%2F%2Fwww.connox.com%2Fcategories%2Faccessories%2Fhome-decor%2Fchildren-design-mobiles%2Fflensted-mobiles-cherry-dreams-mobile.html&docid=UUGMgtOe_QHyXM&w=720&h=720",
            "position": 87
        },
        {
            "title": "Safari Mobile | Crib & Nursery Mobiles | Nestig",
            "imageUrl": "https://www.nestig.com/cdn/shop/products/Nestig_169copiar.jpg?v=1678134882&width=1946",
            "imageWidth": 1946,
            "imageHeight": 1946,
            "thumbnailUrl": "https://encrypted-tbn0.gstatic.com/images?q=tbn:ANd9GcRLyjKwPjhLpXSUIWAV4GXuW4waE9926QBNEg&s",
            "thumbnailWidth": 225,
            "thumbnailHeight": 225,
            "source": "Nestig",
            "domain": "www.nestig.com",
            "link": "https://www.nestig.com/products/safari-mobile",
            "googleUrl": "https://www.google.com/imgres?imgurl=https%3A%2F%2Fwww.nestig.com%2Fcdn%2Fshop%2Fproducts%2FNestig_169copiar.jpg%3Fv%3D1678134882%26width%3D1946&tbnid=Bq6P-RNnMCmrGM&imgrefurl=https%3A%2F%2Fwww.nestig.com%2Fproducts%2Fsafari-mobile&docid=gfTFwlVe8vLimM&w=1946&h=1946",
            "position": 88
        },
        {
            "title": "Best Mobiles Under ₹ 20000 | Samsung India",
            "imageUrl": "https://images.samsung.com/is/image/samsung/assets/in/smartphones/mobiles-by-price/Smartphones-under-20000-Mob.jpg?$720_N_JPG$",
            "imageWidth": 720,
            "imageHeight": 800,
            "thumbnailUrl": "https://encrypted-tbn0.gstatic.com/images?q=tbn:ANd9GcRA2zVk7nBLx1lX_R2acpVba49u4EIHz9xVKw&s",
            "thumbnailWidth": 213,
            "thumbnailHeight": 237,
            "source": "Samsung",
            "domain": "www.samsung.com",
            "link": "https://www.samsung.com/in/smartphones/mobiles-by-price/under-rs20000/",
            "googleUrl": "https://www.google.com/imgres?imgurl=https%3A%2F%2Fimages.samsung.com%2Fis%2Fimage%2Fsamsung%2Fassets%2Fin%2Fsmartphones%2Fmobiles-by-price%2FSmartphones-under-20000-Mob.jpg%3F%24720_N_JPG%24&tbnid=MHzmh13UcF76cM&imgrefurl=https%3A%2F%2Fwww.samsung.com%2Fin%2Fsmartphones%2Fmobiles-by-price%2Funder-rs20000%2F&docid=GjJ77QX9qqnPiM&w=720&h=800",
            "position": 89
        },
        {
            "title": "Whale Baby Mobile Fish Mobile Moon Baby Crib Mobile Grey ...",
            "imageUrl": "https://i.etsystatic.com/14466268/r/il/7453a1/2189968674/il_1080xN.2189968674_n3wg.jpg",
            "imageWidth": 1080,
            "imageHeight": 1080,
            "thumbnailUrl": "https://encrypted-tbn0.gstatic.com/images?q=tbn:ANd9GcRrGprBo7XnLMWeN77OQE5ylLQaQ66QKM-Y5g&s",
            "thumbnailWidth": 225,
            "thumbnailHeight": 225,
            "source": "Etsy",
            "domain": "www.etsy.com",
            "link": "https://www.etsy.com/listing/737380429/whale-baby-mobile-fish-mobile-moon-baby",
            "googleUrl": "https://www.google.com/imgres?imgurl=https%3A%2F%2Fi.etsystatic.com%2F14466268%2Fr%2Fil%2F7453a1%2F2189968674%2Fil_1080xN.2189968674_n3wg.jpg&tbnid=mOMdsLLxYJhWOM&imgrefurl=https%3A%2F%2Fwww.etsy.com%2Flisting%2F737380429%2Fwhale-baby-mobile-fish-mobile-moon-baby&docid=lTNAPtz5M287mM&w=1080&h=1080",
            "position": 90
        },
        {
            "title": "Best quality-price mobiles. What mobile do I buy? [August ...",
            "imageUrl": "http://cdn-files.kimovil.com/deal_screenshot/0010/68/thumb_967550_deal_screenshot_x_big.png",
            "imageWidth": 1200,
            "imageHeight": 600,
            "thumbnailUrl": "https://encrypted-tbn0.gstatic.com/images?q=tbn:ANd9GcTgIAeasb4hs87PMBsgiMfcBKbHQrFQ7eP85Q&s",
            "thumbnailWidth": 318,
            "thumbnailHeight": 159,
            "source": "Kimovil",
            "domain": "www.kimovil.com",
            "link": "https://www.kimovil.com/en/best-smartphones-price-quality",
            "googleUrl": "https://www.google.com/imgres?imgurl=http%3A%2F%2Fcdn-files.kimovil.com%2Fdeal_screenshot%2F0010%2F68%2Fthumb_967550_deal_screenshot_x_big.png&tbnid=Iedor1-7p7awRM&imgrefurl=https%3A%2F%2Fwww.kimovil.com%2Fen%2Fbest-smartphones-price-quality&docid=EsNOJmEmbG9QrM&w=1200&h=600",
            "position": 91
        },
        {
            "title": "The best smartphones of 2024, tried and tested – but are ...",
            "imageUrl": "https://www.telegraph.co.uk/content/dam/recommended/2024/01/03/TELEMMGLPICT000361477035_17042812974650_trans_NvBQzQNjv4BqqVzuuqpFlyLIwiB6NTmJwfSVWeZ_vEN7c6bHu2jJnT8.jpeg?imwidth=350",
            "imageWidth": 350,
            "imageHeight": 219,
            "thumbnailUrl": "https://encrypted-tbn0.gstatic.com/images?q=tbn:ANd9GcQHo4CJvWTsg2IaAu-8tRsnFnQjzG_q0Dwa8Q&s",
            "thumbnailWidth": 284,
            "thumbnailHeight": 177,
            "source": "The Telegraph",
            "domain": "www.telegraph.co.uk",
            "link": "https://www.telegraph.co.uk/recommended/tech/best-smartphones/",
            "googleUrl": "https://www.google.com/imgres?imgurl=https%3A%2F%2Fwww.telegraph.co.uk%2Fcontent%2Fdam%2Frecommended%2F2024%2F01%2F03%2FTELEMMGLPICT000361477035_17042812974650_trans_NvBQzQNjv4BqqVzuuqpFlyLIwiB6NTmJwfSVWeZ_vEN7c6bHu2jJnT8.jpeg%3Fimwidth%3D350&tbnid=fdAWCwVdza2iKM&imgrefurl=https%3A%2F%2Fwww.telegraph.co.uk%2Frecommended%2Ftech%2Fbest-smartphones%2F&docid=9RRs5cqNHktMNM&w=350&h=219",
            "position": 92
        },
        {
            "title": "Mobiles",
            "imageUrl": "https://lightart.imgix.net/products/Mobile/lightart-custom-mobile-marshfield-cancer-center_Cropped.png?auto=compress%2Cformat&crop=focalpoint&fit=crop&fp-x=0.5&fp-y=0.5&h=483&q=80&w=724&s=0b9f1ca59e5d7790e13ed8c6eab0881d",
            "imageWidth": 724,
            "imageHeight": 483,
            "thumbnailUrl": "https://encrypted-tbn0.gstatic.com/images?q=tbn:ANd9GcTaOlSgfSBJudt06zG375S64JXV23DN5dwLJQ&s",
            "thumbnailWidth": 275,
            "thumbnailHeight": 183,
            "source": "LightArt",
            "domain": "lightart.com",
            "link": "https://lightart.com/products/types/mobiles",
            "googleUrl": "https://www.google.com/imgres?imgurl=https%3A%2F%2Flightart.imgix.net%2Fproducts%2FMobile%2Flightart-custom-mobile-marshfield-cancer-center_Cropped.png%3Fauto%3Dcompress%252Cformat%26crop%3Dfocalpoint%26fit%3Dcrop%26fp-x%3D0.5%26fp-y%3D0.5%26h%3D483%26q%3D80%26w%3D724%26s%3D0b9f1ca59e5d7790e13ed8c6eab0881d&tbnid=ASoeX5-Er54ubM&imgrefurl=https%3A%2F%2Flightart.com%2Fproducts%2Ftypes%2Fmobiles&docid=De5N97r58iYJxM&w=724&h=483",
            "position": 93
        },
        {
            "title": "Materials Spotlight: Montessori Mobiles",
            "imageUrl": "https://lirp.cdn-website.com/53d04bb3/dms3rep/multi/opt/Blog-0912-1e00b223-640w.jpg",
            "imageWidth": 640,
            "imageHeight": 213,
            "thumbnailUrl": "https://encrypted-tbn0.gstatic.com/images?q=tbn:ANd9GcQm3db07AZiijTgPJZGKZBIlftpfRdyMJuyag&s",
            "thumbnailWidth": 390,
            "thumbnailHeight": 129,
            "source": "The Montessori School of the Berkshires",
            "domain": "www.berkshiremontessori.org",
            "link": "https://www.berkshiremontessori.org/msb-blog/materials-spotlight-montessori-mobiles",
            "googleUrl": "https://www.google.com/imgres?imgurl=https%3A%2F%2Flirp.cdn-website.com%2F53d04bb3%2Fdms3rep%2Fmulti%2Fopt%2FBlog-0912-1e00b223-640w.jpg&tbnid=n_Ja07Rnt5LH1M&imgrefurl=https%3A%2F%2Fwww.berkshiremontessori.org%2Fmsb-blog%2Fmaterials-spotlight-montessori-mobiles&docid=s7S3nKOxOimcsM&w=640&h=213",
            "position": 94
        },
        {
            "title": "Make Your Own Montessori Mobiles – Rhyme and Reason Academy",
            "imageUrl": "https://www.rhymeandreasonacademy.com/wp-content/uploads/2022/05/PinterestPins.002-683x1024.jpeg",
            "imageWidth": 683,
            "imageHeight": 1024,
            "thumbnailUrl": "https://encrypted-tbn0.gstatic.com/images?q=tbn:ANd9GcRX-ShEOabeoBCcgsn_21tc4VKK2e_AGI04Vw&s",
            "thumbnailWidth": 183,
            "thumbnailHeight": 275,
            "source": "Rhyme and Reason Academy",
            "domain": "www.rhymeandreasonacademy.com",
            "link": "https://www.rhymeandreasonacademy.com/montessori-mobiles/",
            "googleUrl": "https://www.google.com/imgres?imgurl=https%3A%2F%2Fwww.rhymeandreasonacademy.com%2Fwp-content%2Fuploads%2F2022%2F05%2FPinterestPins.002-683x1024.jpeg&tbnid=lGJBMg66RtWcPM&imgrefurl=https%3A%2F%2Fwww.rhymeandreasonacademy.com%2Fmontessori-mobiles%2F&docid=gjtgFpgl9qaNrM&w=683&h=1024",
            "position": 95
        },
        {
            "title": "Best-Selling Mobiles: 10 Best-Selling Mobiles on Amazon ...",
            "imageUrl": "https://m.economictimes.com/thumb/msid-104056500,width-1600,height-900,resizemode-4,imgsize-59286/10-best-selling-mobiles-on-amazon-offering-the-best-performance-2024.jpg",
            "imageWidth": 1600,
            "imageHeight": 900,
            "thumbnailUrl": "https://encrypted-tbn0.gstatic.com/images?q=tbn:ANd9GcTvkk6Lc_vOvMxgKD5EAacKawQikOUYQ1o16w&s",
            "thumbnailWidth": 300,
            "thumbnailHeight": 168,
            "source": "The Economic Times",
            "domain": "m.economictimes.com",
            "link": "https://m.economictimes.com/top-trending-products/mobile-phones/best-selling-mobiles-on-amazon-discover-the-best-performance/articleshow/104056500.cms",
            "googleUrl": "https://www.google.com/imgres?imgurl=https%3A%2F%2Fm.economictimes.com%2Fthumb%2Fmsid-104056500%2Cwidth-1600%2Cheight-900%2Cresizemode-4%2Cimgsize-59286%2F10-best-selling-mobiles-on-amazon-offering-the-best-performance-2024.jpg&tbnid=mYJzU5F1OkpA7M&imgrefurl=https%3A%2F%2Fm.economictimes.com%2Ftop-trending-products%2Fmobile-phones%2Fbest-selling-mobiles-on-amazon-discover-the-best-performance%2Farticleshow%2F104056500.cms&docid=mge2y48_rEUOtM&w=1600&h=900",
            "position": 96
        },
        {
            "title": "Mobiles | Buy Latest Smartphones online at best price | Viveks",
            "imageUrl": "https://media.viveks.com/media/catalog/product/cache/43c523c8c25ec73ea5fa54c25c6f766c/6/1/61_czeoob1l._sl1200_.jpg",
            "imageWidth": 320,
            "imageHeight": 320,
            "thumbnailUrl": "https://encrypted-tbn0.gstatic.com/images?q=tbn:ANd9GcQu3vJzQxuFik_YUEsTjDezn-WWZBuMJpkpzg&s",
            "thumbnailWidth": 225,
            "thumbnailHeight": 225,
            "source": "Viveks",
            "domain": "viveks.com",
            "link": "https://viveks.com/mobiles-wearables/mobile-phones",
            "googleUrl": "https://www.google.com/imgres?imgurl=https%3A%2F%2Fmedia.viveks.com%2Fmedia%2Fcatalog%2Fproduct%2Fcache%2F43c523c8c25ec73ea5fa54c25c6f766c%2F6%2F1%2F61_czeoob1l._sl1200_.jpg&tbnid=AVhsAB-Gl4rkVM&imgrefurl=https%3A%2F%2Fviveks.com%2Fmobiles-wearables%2Fmobile-phones&docid=R8zXqOaFzlG5sM&w=320&h=320",
            "position": 97
        },
        {
            "title": "online shopping of mobiles, online shopping of mobiles ...",
            "imageUrl": "https://s.alicdn.com/@sc04/kf/Hd271b20aee514e81a7b2075ab22275daL.jpg_300x300.jpg",
            "imageWidth": 300,
            "imageHeight": 300,
            "thumbnailUrl": "https://encrypted-tbn0.gstatic.com/images?q=tbn:ANd9GcRodFfvc1QMqkDszXxJAbLR9VvdUMrnqLXxNA&s",
            "thumbnailWidth": 225,
            "thumbnailHeight": 225,
            "source": "Alibaba",
            "domain": "www.alibaba.com",
            "link": "https://www.alibaba.com/showroom/online-shopping-of-mobiles.html",
            "googleUrl": "https://www.google.com/imgres?imgurl=https%3A%2F%2Fs.alicdn.com%2F%40sc04%2Fkf%2FHd271b20aee514e81a7b2075ab22275daL.jpg_300x300.jpg&tbnid=OgK0e22Yke9zDM&imgrefurl=https%3A%2F%2Fwww.alibaba.com%2Fshowroom%2Fonline-shopping-of-mobiles.html&docid=7ty2ykJr5FH_LM&w=300&h=300",
            "position": 98
        }
    ],
    "credits": 2
}